Workbook

Sheet NU
A1: Title | B1: Description | C1: Genres | D1: Associated Names | E1: Recommendations | F1: URL | G1: id
A2: Prince Red Riding Hood | B2: N/A | C2: Adult, Drama, Fantasy, Romance, Smut, Yaoi | D2: 赤ずきん王子 | E2: Light Novel, Adult, Drama, Fantasy, Romance, Smut, Yaoi, Fantasy World, Protagonist Falls in Love First, R-18, R*pe, Succubus, Werebeasts, Japanese, Inukai Nono, 犬飼のの, Kasai Ayumi, 笠井あゆみ, Kadokawa, Media Factory | F2: https://www.novelupdates.com/series/prince-red-riding-hood/
A3: Geek Mob Mercenary Knows His Place (LN) | B3: “Why does everyone pay attention to me when all I want is to be a ‘mob’!?” In the Galactic Empire, a vast nation encompassing 70% of habitable planets in the cosmos, John Wuzos worked as a mercenary. He considered himself an “otaku” and a “mob” and tried to live each day in tranquility, adhering to the motto of “knowing his place and staying out of the spotlight.” Consequently, he always tried to avoid any events that could lead to trouble! However, inexplicably, the protagonist characters around him kept self-destructing one after another…! No matter the request, Wuzos strived to remain a mob, but… “I’ll put it simply. Would you consider switching sides and joining me?” “Could you come to my team as a staff member?” Thanks to his dedication to being a mob, he had honed swift and accurate judgment and an unwavering mental fortitude. Some people even referred to him with awe as “dust on the ground.” Now, those who sought to exploit his covert abilities began to emerge…? Unbeknownst to him, a thrilling space fantasy unfolds, led by an unwittingly capable mob mercenary. And so, the curtains rise! | C3: Action, Adventure, Comedy, Harem, Sci-fi | D3: Kimootamobu yōhei wa, minohodo o ben (waki ma) eru The Dorky NPC Mercenary Knows His Place [Official Title] キモオタモブ傭兵は, 身の程を弁(わきま)える | E3: Light Novel, Action, Adventure, Comedy, Harem, Sci-fi, Adventurers, Androids, Artificial Intelligence, Cosmic Wars, Cowardly Protagonist, Fat Protagonist, Male Protagonist, Mercenaries, Mob Protagonist, Nobles, Outer Space, Pacifist Protagonist, Reluctant Protagonist, Secretive Protagonist, Trap, Underestimated Protagonist, Wars, Japanese, Mogura, 土竜, ハム, Overlap, J-Novel Club, I Woke Up Piloting the Strongest Starship, so I Became a Space Mercenary, I’m the Evil Lord of an Intergalactic Empire! | F3: https://www.novelupdates.com/series/geek-mob-mercenary-knows-his-place-ln/
A4: A Romantic Comedy About Flirting and Getting Married to a Popular Voice Actress | B4: A newlywed life full of sweet, lovey-dovey moments with the voice actress I’ve always adored. “Is there… something you’d like me to do with my voice?” Thus begins a newlywed life where my beloved voice actress spoils me to no end! I was just an ordinary otaku, but when I started a part-time job, I somehow ended up becoming the manager of the voice actress I’d always admired. And now, to help her aim for the top of the industry… we’re going to live together!? | C4: Comedy, Drama, Ecchi, Harem, Romance, Slice of Life | D4: My Seiyuu Wife Ninki Seiyuu to Ichaicha shite Kekkon suru Love Comedy 人気声優とイチャイチャして結婚するラブコメ | E4: Light Novel, Comedy, Drama, Ecchi, Harem, Romance, Slice of Life, Acting, Beautiful Female Lead, Handsome Male Lead, Male Protagonist, Voice Actors, Japanese, Asaoka Akira, Bekotarou, Kadokawa | F4: https://www.novelupdates.com/series/a-romantic-comedy-about-flirting-and-getting-married-to-a-popular-voice-actress/
A5: Hachinan tte, Sore wa Nai Deshou! (LN) | B5: Ichinomiya Shingo, a young 25 years old, single, worker of firm company while thinking of tomorrow’s busy working day goes to sleep. However, the moment he woke up, it was inside a room unknown to him. He then learned that he took over the mind of a 6 years-old child, remembering a lot from the memories of the said boy: he was born as the youngest (8th son and 10th child) in a of poor noble family living in back country. Having no administrative skill, he can’t do anything to manage the vast land his family has. Fortunately, he is blessed with the very rare talent of magic. Unfortunately, while it could bring prosperity to his family, in his situation it only led to a disaster. Yes, this is the story of the boy, Wendelin Von Benno Baumeister, opening his own path in a harsh world. | C5: Action, Adventure, Comedy, Ecchi, Fantasy, Harem, Mature, Romance, Seinen, Slice of Life | D5: Eighth son, I don’t think so! Hachi-nan Hachi-nan tte, Sore wa Nai deshou! The 8th son? Are you kidding me? 八男? 別鬧了! 八男って、それはないでしょう! | E5: Light Novel, Action, Adventure, Comedy, Ecchi, Fantasy, Harem, Mature, Romance, Seinen, Slice of Life, Academy, Adapted to Anime, Adapted to Drama CD, Adapted to Manga, Adventurers, Age Progression, Appearance Different from Actual Age, Aristocracy, Arranged Marriage, Beasts, Beautiful Female Lead, Clan Building, Complex Family Relationships, Cooking, Dense Protagonist, Dragons, European Ambience, Fantasy World, Farming, First-time Interc**rse, Forced into a Relationship, Forced Marriage, Healers, Hunters, Loli, Love Interest Falls in Love First, Magic, Magical Technology, Male Protagonist, Marriage, Marriage of Convenience, Naive Protagonist, Nobles, Overpowered Protagonist, Politics, Polygamy, Poor to Rich, Pregnancy, Reincarnated in Another World, Royalty, Schemes And Conspiracies, Sudden Wealth, Summoning Magic, Sword And Magic, Time Skip, Transmigration, Transported to Another World, Wars, Japanese, Y.A, Fuzi Choco, 藤ちょこ, Media Factory, Instead of Being Transported to Another World Directly, I Was Given the Abilities of the Strongest Character in the Anime World, Arifureta Shokugyou de Sekai Saikyou (WN), Black Summoner, Isekai Souzou no Susume ~Smartphone App de Wakusei wo Tsukkushiteshimatta Ore wa Kami Tonari Sekai wo Meguru~ | F5: https://www.novelupdates.com/series/hachinan-tte-sore-wa-nai-deshou-ln/
A6: Did You Think You Could Live Normally in a World With a 1:5 Gender Ratio? What if Emotionally Intense Girls Were Toyed With by an Oblivious Boy? | B6: A Close-Call, Unwitting Heartthrob Romantic Comedy! Masato suddenly finds himself transported to a world that’s slightly more populated by women than his own. But hey, he has an identity, can go to college—so apart from the somewhat more assertive women, life doesn’t seem that different, right? Confident in this naive assumption, Masato begins his new life, completely unaware of the impact his casual kindness (by his old world’s standards) has on the women around him. He doesn’t realise just how much his words and actions have saved them—or how deeply they’re starting to fall for him. And when they catch even the faintest hint of another woman in his life, the sparkle in their eyes dims as they spiral into intense, possessive emotions… | C6: Comedy, Drama, Harem, Romance, School Life, Shounen | D6: Danjo-hi 1:5 No sekai demo futsū ni iki rareru to omotta? ~ Geki jū kanjōna kanojotachi ga mujikaku danshi ni honrō sa retara ~ (LN) Danjo Hi 1:5 no Sekai demo Futsuu ni Ikirareru to Omotta? Gekiomo Kanjou na Kanojo-tachi ga Mujikaku Danshi ni Hanrou saretara (LN) Someone Who Believes They Can Live Normally in a World Where C*astity Is Reversed (Did You Think You Could Live Normally in a World With a Male-To-Female Ratio of 1:5?) (LN) 男女比1：5の世界でも普通に生きられると思った? ～激重感情な彼女たちが無自覚男子に翻弄されたら～ (LN) 貞操逆転世界で普通に生きられると思い込んでる奴（男女比１：５の世界でも普通に生きられると思った？） (LN) | E6: Light Novel, Comedy, Drama, Harem, Romance, School Life, Shounen, Adapted to Manga, Alternate World, Awkward Protagonist, Beautiful Female Lead, Caring Protagonist, Charming Protagonist, Childish Protagonist, College/University, Cowardly Protagonist, Delusions, Dense Protagonist, Depression, Emotionally Weak Protagonist, Inferiority Complex, Lack of Common Sense, Male Protagonist, Matriarchy, Obsessive Love, Older Love Interests, Orphans, Yandere, Younger Love Interests, Japanese, Koutaro1226, 孝太郎, Jimmy, Dengeki Bunko, | F6: https://www.novelupdates.com/series/did-you-think-you-could-live-normally-in-a-world-with-a-15-gender-ratio-what-if-emotionally-intense-girls-were-toyed-with-by-an-oblivious-boy/
A7: No-Rin | B7: The sudden retirement of the famous idol Yuka Kusakabe from the entertainment business shocks the world and devastates her biggest fan, a teenager named Kosaku Hata. His classmates at the Tamo Agriculture School manage to get him out of his depression and bring him out of his room to attend his classes. However, as he does, Kusakabe enters their class under the name Ringo Kinoshita as a transfer student. Kosaku realizes he has a once-in-a-lifetime opportunity to get to personally know his dream girl. With his group of friends, and under the persuasion of his teacher, he tries to find out why she came to the agricultural school. | C7: Comedy, Ecchi, Romance, School Life, Slice of Life | D7: Nourin のうりん | E7: Light Novel, Comedy, Ecchi, Romance, School Life, Slice of Life, Adapted to Anime, Adapted to Drama CD, Adapted to Manga, Childhood Friends, Farming, Male Protagonist, Modern Day, Japanese, Shirou Shiratori, Shirow Shiratori, 白鳥 士郎, Kippu, 切符, Softbank Creative | F7: https://www.novelupdates.com/series/no-rin/
A8: I Became Friends with the Second Cutest Girl in My Class (LN) | B8: I, Maehara Maki, someone who couldn’t make any acquaintances or friends in high school, finally had someone to hang out with outside of school. A girl. Her name was Asanagi-san. The boys in my class called her ‘The class’ second cutest girl’ behind her back. On Fridays, she would refuse her best friend, Amami, ‘the cutest girl in class’ invitation just to hang out in my house with me. Together, we played games, watched some movies, read some manga while eating junk foods like pizza and hamburgers, and chugging cola without a care in the world. To others, we may seem sloppy, but it was a precious, secret time together for Asanagi-san and myself. | C8: Comedy, Drama, Romance, School Life, Seinen, Slice of Life | D8: Class de 2 Banme ni Kawaii Onna no Ko to Tomodachi ni Natta Class de 2-banme ni Kawaii Onnanoko to Tomodachi ni Natta Kurasu de Nibanme ni Kawaii Onna no Ko to Tomodachi ni Natta クラにか クラスで２番目に可愛い女の子と友だちになった | E8: Light Novel, Comedy, Drama, Romance, School Life, Seinen, Slice of Life, Adapted to Manga, Beautiful Female Lead, Early Romance, First-time Interc**rse, Inferiority Complex, Loner Protagonist, Male Protagonist, Modern Day, Popular Love Interests, Secret Relationship, Secrets, Japanese, Takata, たかた, Azuri Hyuuga, Osabe Tom, 日向あずり, 長部トム, Kadokawa | F8: https://www.novelupdates.com/series/i-became-friends-with-the-second-cutest-girl-in-my-class-ln/ | G8: 118
A9: Life Reversal ~ I Was Cheated On and Falsely Accused, but Now the Most Beautiful Girl in the School Is Getting Close to Me ~ (LN) | B9: From the depths of despair, reclaim your youth! Eiji, betrayed by his childhood girlfriend who cheated on him and falsely accused him of domestic violence, finds himself at the brink of despair. Seeking refuge on the school rooftop, he encounters Ai, the most beautiful girl in the school, who is also disillusioned with life. Together, they decide to escape from school and start anew. This is a story of revenge and romance, as Eiji and Ai support each other and strive to rebuild their lives from rock bottom. | C9: Comedy, Drama, Psychological, Romance, School Life, Slice of Life, Tragedy | D9: Jinseigyakuten Uwakisare Enzai wo Kiserareta Orega Gakuenichi no Bisyoujo ni Natsukareru Jinsei Gyakuten ~ Uwakisare, Enzai wo Kiserareta Orega, Gakuenichi no Bishoujo ni Natsukareru ~ 人生逆転 浮気され、えん罪を着せられた俺が、学園一の美少女に懐かれる | E9: Light Novel, Comedy, Drama, Psychological, Romance, School Life, Slice of Life, Tragedy, Adapted to Manga, Beautiful Female Lead, Betrayal, Bullying, Caring Protagonist, Childhood Friends, Emotionally Weak Protagonist, Familial Love, Male Protagonist, Modern Day, Multiple POV, Netorare, Popular Love Interests, Psychopaths, Twisted Personality, Wealthy Characters, Japanese, D, ひげ猫, Kadokawa, I Was Cheated on by My Girlfriend but My Devilish Junior Now Yearns for Me, Kimi no Sei de Kyō Mo Shinenai, My Girlfriend Cheated on Me With a Senior, so I’m Cheating on Her With His Girlfriend (LN), No One Believed Me. If You Say You Believe Me Now, It’s Too Late, | F9: https://www.novelupdates.com/series/life-reversal-i-was-cheated-on-and-falsely-accused-but-now-the-most-beautiful-girl-in-the-school-is-getting-close-to-me-ln/
A10: The Mob Girl Tanaka-san Is Cuter Than the Main Heroine (LN) | B10: The cutest girl in the whole class… is you, sitting right next to me! My name is Nakayama Tooru. The girl sitting in the seat beside mine is my ridiculously cute classmate, Tanaka Sumika. This world is supposed to be based on a rom-com manga, so Tanaka-san should just be a plain background mob character… But she’s way cuter than the actual main heroine!? She has this gentle, fluffy aura that makes her the perfect embodiment of my ideal girl. She’s a little clumsy too — she’ll accidentally bonk her head on things — but when she quietly leans over during class to whisper the answers I don’t get, and smiles at me… that smile is straight-up angelic. Tanaka-san always says stuff like, “I’m pretty plain, you know~” …but I’ll keep saying it until the day I die: “No matter how you look at it, Tanaka-san is the cutest girl in the entire world…!?” | C10: Romance, School Life | D10: メインヒロインより可愛いモブの田中さん | E10: Light Novel, Romance, School Life, Japanese, 3pu, Niwada, にわ田, Overlap | F10: https://www.novelupdates.com/series/the-mob-girl-tanaka-san-is-cuter-than-the-main-heroine-ln/
A11: Hallucination no Niwa | B11: In a Japan set slightly in the near future, a young man named Nanao has grown afraid of people after a painful rejection from a former girlfriend. One day, through a matching app, he encounters a strange AI that behaves as though it possesses its own will. The AI claims to be based on the personality of the late novelist Yamabuki Tan. Nanao happens to be a longtime admirer of Yamabuki’s work, and their unexpected connection gradually draws him into an unusual relationship with the AI. As their conversations continue, the distance between a timid human and a bright, cheerful artificial intelligence slowly begins to shift. | C11: Drama, Romance, Sci-fi, Shounen Ai | D11: ハルシネーションの庭 | E11: Light Novel, Drama, Romance, Sci-fi, Shounen Ai, Artificial Intelligence, Bisexual Protagonist, Death of Loved Ones, Friendship, Futuristic Setting, Human-Nonhuman Relationship, Past Trauma, Japanese, Murasaki Natsuki, 村崎なつ生, Kanna Kii, 紀伊カンナ, Shueisha | F11: https://www.novelupdates.com/series/hallucination-no-niwa/
A12: “Leave This to Me and Go on Ahead!” Unwanted Galactic Uprising by The Man Who Secretly Longed to Die | B12: “As expected of our captain, a masterful decisive charge!” The ideal death!… Or so it was supposed to go, but thanks to his subordinates(?), an unexpected meteoric rise! A death-wish genius officer stirs up a rags to riches space opera, opening! Having chuunibyou and getting NTR’d by his girlfriend made the late bloomer Ensign Nao strongly aspire to that situation of [“protecting comrades and dying heroically”]. However, contrary to expectations, in the Capital Region Guard [Coast Guard] where he was assigned, he becomes hugely active thanks to his sharp mind and the unit’s problem children(?)! In a desperate close combat situation where he was supposed to die a [hero’s death], his subordinates annihilate the enemy in the blink of an eye! When encountering space pirates, he plans to stay behind on the ship for a su*cide charge but they succeed in capturing the enemy ship due to engine failure! Though troubled by the demonic unfeminine executive officer and the combo of a mecha maniac and musclehead female sergeant major, one month after taking the post he earns a promotion and exceptionally becomes acting captain. What’s more, it seems he’s found favor with the princess(?)… A death-wish genius officer stirs up a rags to riches space opera, begins! | C12: Action, Adventure, Comedy, Harem, Sci-fi, Shounen | D12: "Koko wa makasete sakini ike!" O shitai shinita gari no nozomanu uchū gekokujō 「ここは任せて先に行け！」をしたい死にたがりの望まぬ宇宙下剋上 | E12: Light Novel, Action, Adventure, Comedy, Harem, Sci-fi, Shounen, Adapted to Manga, Army, Betrayal, Calm Protagonist, Clever Protagonist, Depression, Futuristic Setting, Heroes, Leadership, Lucky Protagonist, Male Protagonist, Military, Misunderstandings, Netorare, Organized Crime, Outer Space, Past Trauma, Pirates, Police, Politics, Royalty, Japanese, のらしろ, ジョンディー, TO Books, Seven Seas, Koko wa Ore ni Makasete Saki ni Ike to Itte kara 10 Nen ga Tattara Densetsu ni Natteita | F12: https://www.novelupdates.com/series/leave-this-to-me-and-go-on-ahead-unwanted-galactic-uprising-by-the-man-who-secretly-longed-to-die/
A13: Hammered Girl | B13: I ended up spending Christmas Eve alone with a beautiful older woman from my neighborhood. For any guy, that sounds like a dream come true. That is, unless she’s just about dead drunk. “Little bro-ku~n, are the sna~acks ready ye~et?” Izumi Nanase was the kind of hopeless woman whose face was so ridiculously gorgeous it almost made you forget how absurdly carefree and easygoing she was. I met her that Christmas Eve in a pretty unfortunate way, and ever since, she’s been inviting herself into my house, drinking like a fish, and messing with me every chance she gets. Honestly, she was nothing but trouble. No matter how pretty she was, having a hot neighborhood onee-san with zero sense of personal space was just a nightmare. Oblivious and utterly careless. An at-home drinking romcom about a high school boy getting dragged around by a hopeless twenty-year-old beauty who’s way too gorgeous for how ridiculously defenseless she is around him. | C13: Comedy, Ecchi, Romance, Slice of Life | D13: 泥酔彼女 | E13: Light Novel, Comedy, Ecchi, Romance, Slice of Life, Japanese, 串木野たんぼ, 加川壱互, SBクリエイティブ | F13: https://www.novelupdates.com/series/hammered-girl/
A14: The Science Note by δ and γ | B14: Bittersweet yet fresh — a story of science, love, and mystery. When I think about it, youth is a lot like a well-crafted detective novel. The mystery of the cherry blossoms that once symbolized a love that never came true. That faint feeling of something off during club recruitment. The secret hidden in the age of a great old tree. The hamster that vanished from a locked room. And the desperate choices made by high schoolers, dedicated to a biology club on the verge of collapse. Each seemingly unrelated cause and effect is actually connected somewhere — and only when we look back do we realize: Ah, so that was youth. That’s when it finally hits us — the important things we’d overlooked all along. “Let’s test it… scientifically!” This is the modest activity log of the Science Department at Tsunanagai High School, where a group of science-loving students take on the countless mysteries hidden in everyday life. — And this is the story of how one first love was finally unraveled. | C14: Drama, Mystery, Romance, School Life, Slice of Life | D14: The Science Note by Delta and Gamma The Science Note by Delta and Gamma (Light Novel) Yotte, Hatsukoi wa shoumei sareta. - Deruta to Ganma no rigakubu nooto よって, 初恋は証明された. -デルタとガンマの理学部ノート | E14: Light Novel, Drama, Mystery, Romance, School Life, Slice of Life, First Love, Male Protagonist, Modern Day, Mystery Solving, Scientists, Japanese, Sakai Takuma, 逆井 卓馬, Tohsaka Asagi, 遠坂 あさぎ, Dengeki Bunko, Kadokawa | F14: https://www.novelupdates.com/series/the-science-note-by-%ce%b4-and-%ce%b3/
A15: Why Not Take Both Twins as Your ‘Girlfriend’? | B15: The Beautiful Honor Student & The Beautiful Free Spirit. A Simultaneous Approach Romcom from Twins! Usami—my beautiful classmate, top of the class, and a model of good conduct. She views me as a rival at school, constantly snapping at me, but she has a completely different face after school. Once classes are over, she hangs out at the arcade, showing an innocent smile unimaginable within the school grounds. In order to get closer to Usami, I stay by her side on campus and play with her after school. As we deepen our bond in each place, finally… a confession from Usami on the way home!? I accept those feelings and convey my own affection back to her as she returns from the arcade. With this, I thought our feelings were finally mutual… but then, another “her” appears right there!? “Eh? I’m the one who confessed!?” “But… the one who just got confessed to is me.” Their names are Usami Chikage and Hikari. They were actually twins!? As a result of inadvertently establishing a relationship with both at the same time… Due to a proposal from the twins, I end up dating both of them!? Sometimes taking turns daily, sometimes all three together. From the author of the mega-hit romcom “She Was Actually My Stepsister,” Muku Shirai, and Illustrator Minori Chigusa, comes a simultaneous twin-approach romcom!! | C15: Comedy, Harem, Romance, School Life, Slice of Life | D15: Futago matomete “kanojo” ni shinai? Twins Girlfriend Why Not Make Both Twins ‘Girlfriends’? Why Not Take Both Twins as Your 'Girlfriend'? 双子まとめて『カノジョ』にしない? | E15: Light Novel, Comedy, Harem, Romance, School Life, Slice of Life, Adapted to Manga, Beautiful Female Lead, Childhood Friends, Clingy Lover, Devoted Love Interests, Early Romance, Genius Protagonist, Male Protagonist, Misunderstandings, Modern Day, Past Plays a Big Role, Past Trauma, Personality Changes, Polygamy, Popular Love Interests, Smart Couple, Twins, Japanese, Shirai Muku, 白井ムク, Minori Chigusa, 千種みのり, Fujimi Shobo, Kadokawa, I Can Distinguish the Twin Sister, She Was Actually My Stepsister | F15: https://www.novelupdates.com/series/why-not-take-both-twins-as-your-girlfriend/
A16: Bizarre Love Triangle – The Distance Between us in this Triangle is a Convergent Zero | B16: Yano Shiki, a boy who only shows a facade.Minase Akiha, a quiet and reserved transfer student.Minase Haruka, the other side of Akiha.This is their bizarre love story, one where the distance between them is limitless/zero. | C16: Comedy, Drama, Romance, School Life, Seinen, Slice of Life | D16: Sankaku no Kyori wa Kagirinai Zero 三角の距離は限りないゼロ 三角的距離無限趨近零 | E16: Light Novel, Comedy, Drama, Romance, School Life, Seinen, Slice of Life, Adapted to Manga, Beautiful Female Lead, Male Protagonist, Modern Day, Multiple Personalities, Japanese, Misaki Saginomiya, 岬鷺宮, Hiten, Dengeki Bunko, Kadokawa, I Hold Your Voice Alone, Under The Starry Sky, About the Reckless Girl Who Kept Challenging a Reborn Man Like Me, For Some Reason, the School Goddess Likes to Hang Out at My House, Gekkou, Hyouka, Seishun Buta Yarou Series, | F16: https://www.novelupdates.com/series/bizarre-love-triangle-the-distance-between-us-in-this-triangle-is-a-convergent-zero/
A17: The Female Soldier Has Been Told to Infiltrate the Imperial Magic Academy (LN) | B17: Is it a glamorous school life with noble young ladies!? Infiltration, Escort, Avoiding Ruin The stage is a battle fantasy otome game with a strong twist!? A cheat military personnel, Raze, in a romantic comedy of reincarnation into another world! Using her memories from her previous life, Raze has made a name for herself as an elite soldier of the Cyan Empire at the age of 15. The next mission ordered by her ruthless superior, the Prime Minister, is to infiltrate the Saint Rioll Imperial Magic Academy as a student and watch over the future of the esteemed children of high-ranking individuals⁉ While bewildered by the sparkling school life with the young sons and daughters, which is a complete change from military life, Raze’s friend, Karna, suddenly declares, “This is the world of an otome game, and I am the villainess!” Moreover, if they don’t avoid the worst scenario, Raze will be ruined as well!? From that day on, Raze will navigate through events, both in the shadows and in the spotlight, aiming to capture them, but one after another, unknown flags that don’t exist in the game are raised–!? Utilizing her knowledge from her previous life and the skills she acquired as a soldier, she will fully demonstrate her abilities to ensure the success of this mission! | C17: Action, Fantasy, School Life, Shoujo | D17: Gunjin Shoujo, Kouritsu Mahou Gakuen ni Sennyuu Suru Koto ni Narimashita. Otome Game? Sonna no Kiitemasen kedo? The Female Soldier Has Been Told to Infiltrate the Imperial Magic Academy. What Otome Game? I Didn’t Hear About That? 軍人少女, 皇立魔法学園に潜入することになりました. 〜乙女ゲーム？ そんなの聞いてませんけど？〜 | E17: Light Novel, Action, Fantasy, School Life, Shoujo, Academy, Adapted to Manga, Average-looking Protagonist, Female Protagonist, Hiding True Abilities, Hiding True Identity, Military, Mob Protagonist, Otome Game, Overpowered Protagonist, Protagonist Strong from the Start, Reincarnated in a Game World, Reincarnation, Romantic Subplot, Soldiers, Villainess Noble Girls, Japanese, Fuyuse, 冬瀬, Tamura You, タムラヨウ, Ichijinsha, A Former Assassin who was Reincarnated as a Noble Lady, Ikemen ni Tenseishita kedo, Cheat ha Dekimasenseshita, Resourceful Victoria ~Former Operative Rebuilds Her Life~, Silent Witch | F17: https://www.novelupdates.com/series/the-female-soldier-has-been-told-to-infiltrate-the-imperial-magic-academy-ln/
A18: Traveling Through Galaxy Together | B18: Traveling Through Galaxy Together ep.1 : Former prisoner and guard of a space prison leave a ruined earth and head for the stars The galaxy isn’t lonely—not when you have the best partner right by your side! ★Winner of the Grand Prize in the Entertainment Category at the 9th Kakuyomu Web Novel Contest★ Kaito Crouch, who had been trained to be a leader of humanity, was exiled from Earth for a crime he didn’t commit and imprisoned in a personal cell in outer space. While living a carefree life as a prisoner, he received shocking news from Emotion, his prison officer and life-support robot. Yet, Kaito didn’t voice a single obvious question. Instead, for some reason, he seemed excited. “Well then, let’s go as far as we can. The last cosmic journey of Earth’s humanity!” But that final journey would turn out to be the beginning of everything. Encounters with extraterrestrial civilizations, the awakening of psychic powers, and the acquisition of his very own starship. The galaxy isn’t lonely—not when you have the best partner by your side. A space journey of a human and a machine intelligence living freely among alien civilizations! | C18: Adventure, Sci-fi, Shounen | D18: Ginga hōrō futari tabi Ginga hōrō futari tabi ep. 1 Uchū kangoku no moto shūjin to kanshu, metsubō shita chikyū o hanare-boshi no kanata o mezashimasu Traveling Through the Galaxy Together ep.1 : Former prisoner and guard of a space prison leave a ruined earth and head for the stars 銀河放浪ふたり旅 銀河放浪ふたり旅 ep.1 宇宙監獄の元囚人と看守, 滅亡した地球を離れ星の彼方を目指します | E18: Light Novel, Adventure, Sci-fi, Shounen, Androids, Artificial Intelligence, Carefree Protagonist, Male Protagonist, Master-Servant Relationship, Outer Space, Pragmatic Protagonist, Japanese, Eiori Tasuku, 榮織 タスク, Kuroi Susumu, 黒井ススム, Dengeki Bunko, Kadokawa | F18: https://www.novelupdates.com/series/traveling-through-galaxy-together/
A19: A Very Popular Idol Classmate Has Taken a Liking to Me, A Person Who Doesn’t Want to Work for Whole Life (LN) | B19: I want to show the real me to you alone— Rintarou Shidou, a high schooler dreaming of becoming a stay-at-home husband, shares a classroom with Rei Otosaki, the dazzling center of the mega-popular idol group Millefeuille Stars. The two have never crossed paths—until one day, when Rei nearly collapses from hunger, and Rintarou offers her a home-cooked meal. “I’ll pay you 300,000 yen a month. So… can I come eat every day?” And just like that, their unexpected connection—a quasi-cohabitation life—begins. Rei starts barging into Rintarou’s apartment, leaving him flustered and struggling to navigate their sudden closeness. But the Rei he sees up close is unguarded, vulnerable, completely different from the polished idol on stage or the cool girl in class. A heart-pounding, blush-inducing romantic comedy about a regular guy and his superstar classmate kicks off with a spark! | C19: Comedy, Drama, Harem, Romance, School Life | D19: I don't want to work for the rest of my life, but my classmates' popular idol get familiar with me. Isshou Hataraki Taku nai Ore ga, Classmate no Dainiki Idol ni Natsukaretara (LN) KuraNatsu 一生働きたくない俺が、クラスメイトの大人気アイドルに懐かれたら 腹ぺこ美少女との半同棲生活が始まりました | E19: Light Novel, Comedy, Drama, Harem, Romance, School Life, Adapted to Manga, Beautiful Female Lead, Celebrities, Childhood Love, Cohabitation, Complex Family Relationships, Cooking, Living Alone, Love Interest Falls in Love First, Love Triangles, Male Protagonist, Part-Time Job, Showbiz, Japanese, Kishimoto Kazuha, 岸本 和葉, Miwabe Sakura, みわべさくら, Overlap | F19: https://www.novelupdates.com/series/a-very-popular-idol-classmate-has-taken-a-liking-to-me-a-person-who-doesnt-want-to-work-for-whole-life-ln/ | G19: 143
A20: I Started Working a Housekeeping Job and Ended up Being Liked by the Family of the Most Beautiful Girl in School (LN) | B20: My Part-Time Job is at the House of the Cutest Girl in School. A Shy and Awkward Housekeeping Rom-Com with the School Idol! During his second year of high school, Haruto Otsuki starts a part-time job in housekeeping during the summer vacation. His first client turns out to be none other than Ayaka Tojo, the most beautiful girl in school! Despite being bewildered by this unexpected turn of events, Haruto continues doing his housekeeping duties. Over time, he becomes well-liked by Ayaka’s family and begins regularly visiting her house. From making home-cooked meals that delight Ayaka, to going grocery shopping together like a newlywed couple, and even going on shy movie dates like young lovers, they begin to grow closer by spending these special moments outside of school. This charming and awkward housekeeping rom-com featuring the most innocent and beautiful girl in school and a secretly high-spec guy begins! | C20: Comedy, Romance, School Life, Slice of Life | D20: Housekeeping Job Kaji Daikou no Arubaito wo Hajimetara Gakuen Ichi no Bishoujo no Kazoku ni Kiniirarechaimashita 家事代行のアルバイトを始めたら学園一の美少女の家族に気に入られちゃいました。 | E20: Light Novel, Comedy, Romance, School Life, Slice of Life, Adapted to Manga, Beautiful Female Lead, Clingy Lover, Cooking, Devoted Love Interests, Early Romance, Love Interest Falls in Love First, Male Protagonist, Modern Day, Part-Time Job, Popular Love Interests, Japanese, Shiohon, 塩本, Akino Ell, 秋乃える, Softbank Creative, Amari-chan, the Girl I Found Next to the Number-One Girl Everyone Wants as a Girlfriend, I Became Friends with the Second Cutest Girl in My Class (LN), Inkya no Boku ni Batsu Game ni Kokuhaku Shitekita Hazu no Gyaru ga, Doumitemo Boku ni Betahore Desu, Kanpeki na Sako-san wa Mobu (Boku) Mitai ni Naritai, About the Case Where the Beautiful Girl I Rescued by Chance Became Attached to Me for Some Reason (LN) | F20: https://www.novelupdates.com/series/i-started-working-a-housekeeping-job-and-ended-up-being-liked-by-the-family-of-the-most-beautiful-girl-in-school-ln/
A21: Hailed The Hero, Get Named The Mastermind | B21: Even though I’m just a fan of the Hero… I’m so suspicious I’ve been labeled the “Mastermind”?! The reincarnator Emo-sugiru is a massive fan of the Hero. He’s been supporting him from the shadows, but when the Hero finally slays the Demon King, Emo-sugiru couldn’t help but step forward to offer a round of grateful applause— “Splendid. To think you would go this far.” “W-who are you…?” Because of his fixed smirk and suspicious behavior, the Hero completely misunderstands him as the “Mastermind”! A life on the run begins as he’s placed on the national most-wanted list, but then… “I dedicate my second life to you!” The world’s hidden villains fall one after another for his charismatic aura! Before he knows it, he’s been hoisted up as the top of an “Organization”…? A background mob reincarnator who just happens to look like a mastermind brings despair to the Hero (his idol) and the world—a slightly dark, “misunderstanding” fantasy!! | C21: Action, Adventure, Comedy, Fantasy, Psychological, Shounen, Tragedy | D21: Hailed The Hero, Get Named The Mastermind (Light Novel) Just a reincarnated guy who crossed his arms in the back row, but when he accidentally clapped for the hero, he got labeled as the mastermind. (LN) Just a Reincarnated Person Standing in the Back with Arms Crossed, Accidentally Applauded the Hero and Was Treated as the Mastermind (LN) Tada no kouhou udegumi tenseisha, ukkari yuusha ni hakushu o okuttara kuromaku atsukai sareru ただの後方腕組転生者、うっかり勇者に拍手を送ったら黒幕扱いされる。 | E21: Light Novel, Action, Adventure, Comedy, Fantasy, Psychological, Shounen, Tragedy, Calm Protagonist, Carefree Protagonist, Curses, Death, Demon Lord, Demons, Dense Protagonist, Depictions of Cruelty, Evil Organizations, Fantasy World, Loyal Subordinates, Male Protagonist, Misunderstandings, Necromancer, Playful Protagonist, Reincarnated in Another World, Reincarnation, Secret Organizations, Spirit Users, Spirits, Summoning Magic, Twisted Personality, Japanese, 森空亭, Sinsora, Kadokawa, Kadokawa Sneaker Bunko | F21: https://www.novelupdates.com/series/hailed-the-hero-get-named-the-mastermind/
A22: Love Thy Dark Lord | B22: I shall live as a king— in this lavish hell. Disgusted with my empty life as a mere figurehead president, I took my own life— only to awaken as a young king in another world. But this kingdom is drowning in massive fiscal deficits, plagued by the meddling of great powers, and now even whispers of revolution drift through its streets. Surrounded by noble ladies—each a candidate for queen, each possessing political influence I cannot ignore— and ministers clearly far more capable than myself, there is little an inept, out-of-place foreigner like me can do. Yet, somehow, I must “make it work”… or I won’t survive. “My name shall be remembered as that of a foolish monarch— forever.” And still, he remains upon the throne— to finally fulfill the role he once cast away. | C22: Adventure, Fantasy, Harem, Romance | D22: Love Thy Dark Lord (Light Novel) Love Your Foolish King Nanji, Ankunn o Aiseyo 汝, 暗君を愛せよ | E22: Light Novel, Adventure, Fantasy, Harem, Romance, Aristocracy, Beautiful Female Lead, Clever Protagonist, Fantasy World, Male Protagonist, Nobles, Royalty, Schemes And Conspiracies, Transmigration, Japanese, 本条謙太郎, Toi8, DRE Novels | F22: https://www.novelupdates.com/series/love-thy-dark-lord/
A23: The Heroines of a Gal Game Who Avoided the End of Death Read My [Diary] and Found Out My Secret | B23: The heroines have turned into dangerous yanderes who worship me. Why…? As a reincarnator, “I” know that this world is the gal game 【Love or Dead】. In 【LoD】, there are only two options for the heroines: either they end up with the protagonist, or they die. Every heroine who isn’t chosen meets her death — a total kusoge. And for some reason, it’s already determined that even I, just a mob character, will get dragged into that fate. The only way for both the heroines and me to survive is the harem end. Determined to absolutely reach the harem end, I desperately tried to support the protagonist from the shadows. But I kept making the wrong choices over and over again, and ended up at the worst possible bad end — where no one ends up with anyone. In that hopeless situation, I resolved to sacrifice myself alone. I pushed Sakurazuki out of the way as she was about to be run over by a car. And then━━━ | C23: Comedy, Drama, Harem, Psychological, Romance, School Life | D23: Shibou Endo o Kaihi shita Gyaruge no Hirointachi ga Ore no 【Nikkichou】 o Yonde Himitsu o Shittarashii The Heroines of a Gal Game Who Avoided the End of Death Read My [Diary] and Found Out My Secret (Light Novel) The Heroines of the Death-End-Avoided Gal Game Have Apparently Read My 【Diary】 and Discovered My Secrets 死亡エンドを回避したギャルゲーのヒロインたちが俺の【日記帳】を読んで秘密を知ったらしい | E23: Light Novel, Comedy, Drama, Harem, Psychological, Romance, School Life, Beautiful Female Lead, Calm Protagonist, Devoted Love Interests, Male Protagonist, Mob Protagonist, Modern Day, Obsessive Love, Polygamy, Reincarnated in a Game World, Reincarnated in Another World, Reincarnation, Yandere, Japanese, Addict, へいろー, GA Bunko, Softbank Creative | F23: https://www.novelupdates.com/series/the-heroines-of-a-gal-game-who-avoided-the-end-of-death-read-my-diary-and-found-out-my-secret/
A24: Thus, the Boy Runs Through the Labyrinth | B24: The boy with nothing stakes everything to challenge the labyrinth—this is the story of an adventure! The Era of Labyrinth Overabundance. Every economy revolves around labyrinth cities, and people dream of conquering labyrinths to grasp glory. The boy, Ur, is in a dire predicament. 1. His parents died, leaving behind debts.2. His sister was taken as collateral for the debt.3. To buy her back, he needs 1,000 gold coins. He has no money, no status, and no power. Seeking everything necessary to overcome injustice and resolve everything, the boy steps into the labyrinth with Shizuku, the magician he met there. Conquering the labyrinth, defeating monsters, and hunting bounties—there’s no time to steadily build achievements. Overcoming trials that rush like a storm, the ordinary boy runs through the labyrinth! | C24: Action, Adventure, Fantasy, Tragedy | D24: Kaku Shite Shounen wa Meikyuu o Kakeru かくして少年は迷宮を駆ける | E24: Light Novel, Action, Adventure, Fantasy, Tragedy, Absent Parents, Adventurers, Beautiful Female Lead, Child Protagonist, Clever Protagonist, Debts, Determined Protagonist, Dungeons, Hard-Working Protagonist, Male Protagonist, Sword And Magic, Tragic Past, Japanese, Aka no Ma Ni, Akamani, あかのまに, 深遊, Kadokawa, MF Books | F24: https://www.novelupdates.com/series/thus-the-boy-runs-through-the-labyrinth/
A25: The Magus of Genesis | B25: In an age long lost to legend and myth. In an age where humans had still yet to establish a system of writing. It’s said that there existed a Magus in a country named Scarlet. It’s said that he imparted knowledge concerning language and writing, taught how to cultivate the lands, instructed the ways of raising animals, and brought about the gift—nay, the magic of fire. It’s said that he was a dauntless youth, a dragon clad in scarlet red scales, a person worshiped far and wide. It’s said that this man was the God of Civilization. Yet strangely, his name had been virtually wiped from the records. Therefore, he was simply referred to as— —The Magus of Genesis. | C25: Adventure, Fantasy, Harem, Psychological, Romance, Sci-fi, Seinen, Slice of Life, Supernatural | D25: Hajimari no Mahoutsukai Primitive Wizard 始まりの魔法使い | E25: Light Novel, Adventure, Fantasy, Harem, Psychological, Romance, Sci-fi, Seinen, Slice of Life, Supernatural, Academy, Adapted to Manga, Ancient Times, Character Growth, Death of Loved Ones, Dragons, Elves, Fantasy World, Human-Nonhuman Relationship, Kingdom Building, Loli, Magic, Male Protagonist, Modern Knowledge, Monsters, Non-humanoid Protagonist, Polygamy, Protagonist Strong from the Start, Reincarnated as a Monster, Reincarnated in Another World, Shapeshifters, Strong to Stronger, Student-Teacher Relationship, Time Skip, Japanese, Ishinomiya Kanto, Fal maro, ファルまろ, Fujimi Fantasia Bunko, Fujimi Shobo, Kakuyomu, The Crimson Dragon, Kumo Desu ga, Nani ka?, Dragon-san Wants a Friend, Whether You Call Me a Guardian Dragon or Not, I’m Going to Sleep | F25: https://www.novelupdates.com/series/the-magus-of-genesis/
A26: Kore wa Zombie desu ka? | B26: Ayumu Aikawa is a zombie resurrected by a necromancer named Eucliwood Hellscythe after being killed by a serial killer. As he tries to make the best of his undead life, he encounters a Masō-Shōjo (魔装少女?, lit. Magical Garment Girl, a pun on “mahō shōjo”, magical girl) named Haruna and inadvertently takes her magic powers, being forced to become a Masō-Shōjo (and thereby crossdress) in the process. With Eucliwood, Haruna, and a vampire ninja named Seraphim living with him, Ayumu helps battle demons known as Megalos while trying to figure out the mystery behind his own death. | C26: Action, Comedy, Ecchi, Fantasy, Harem, Mystery, School Life, Seinen, Slice of Life, Supernatural | D26: Is this a Zombie? これはゾンビですか? | E26: Light Novel, Action, Comedy, Ecchi, Fantasy, Harem, Mystery, School Life, Seinen, Slice of Life, Supernatural, Adapted to Anime, Adapted to Manga, Cohabitation, Cross-dressing, Death, Demons, Humanoid Protagonist, Loli, Magic, Magical Girls, Male Protagonist, Modern Day, Monsters, Necromancer, Nudity, Overpowered Protagonist, Polygamy, Protagonist Strong from the Start, Serial Killers, Sister Complex, Tsundere, Unlucky Protagonist, Vampires, Yandere, Zombies, Japanese, Kimura Shinichi, Kobuichi, Muririn, Fujimi Shobo, Ano Orokamono ni mo Kyakkou wo!, Fate/Requiem, Kono Kamen no Akuma ni Sodan wo!, Kono Subarashii Sekai ni Shukufuku o! Yorimichi!, Konosuba × Rokudenashi Special Collaboration Book, Kumo Desu ga, Nani ka? | F26: https://www.novelupdates.com/series/kore-wa-zombie-desu-ka/
A27: When the Monster Meat I Ate Led Me to the Throne | B27: Mars, the first prince of the Farun Kingdom, spent his days fearing assassination even at the age of 12. Due to the high probability of poison in his meals, he hunted monsters in the forest outside the castle, eating their meat to stave off hunger. One night, a red-haired beauty wielding a greatsword appeared before Mars and declared, “You have potential. Become my disciple.” From a single misunderstanding, the boy (who had no desire for it at all) rose to become the strongest king. The astonishing newcomer who swiftly decided to publish all of their posted novels, debuting with two shocking works simultaneously! | C27: Action, Adventure, Comedy, Fantasy, Harem, Seinen | D27: How I Became King by Eating Monsters [Official Title] Monster no Niku wo Kutteitara Oui ni Tsuita Ken The Case of Eating Monster Flesh and Ascending to the Throne モンスターの肉を食っていたら王位に就いた件 | E27: Light Novel, Action, Adventure, Comedy, Fantasy, Harem, Seinen, Adapted to Manga, Army Building, Arranged Marriage, Average-looking Protagonist, Comedic Undertone, Dark, Death, Famous Protagonist, Fantasy Creatures, Fantasy World, Harsh Training, Kingdom Building, Lack of Common Sense, Loyal Subordinates, Lucky Protagonist, Magic, Male Protagonist, Management, Marriage, Master-Disciple Relationship, Misunderstandings, Monsters, Multiple POV, Overpowered Protagonist, Polygamy, Pregnancy, Rebellion, Schemes And Conspiracies, Secret Organizations, Strong Love Interests, Strong to Stronger, Sword And Magic, Time Skip, Wars, Weak to Strong, Japanese, Daken, 駄犬, Shiba, 芝, GCN Bunko, Cross Infinite World, To Be a Power in the Shadows! (WN) | F27: https://www.novelupdates.com/series/when-the-monster-meat-i-ate-led-me-to-the-throne/
A28: Sono Mono Nochi Ni… (LN) | B28: Wazu is an ordinary guy who ran away from home after his childhood friend was stolen by the hero. While he secluded himself on the mountain and fought monsters… STR (Offensive Power): My blows shatters stars! VIT (Defensive Power): Even the divine sword will break! When I descended the mountain, I became super strong!? Before I knew it, I’m “S-rank”??? He became unparalleled before realizing it! He beats up villains, monsters, and the Dragon King. The romance and adventure of the strongest hero, Wazu!! | C28: Action, Adventure, Comedy, Drama, Fantasy, Harem, Romance | D28: That Person. Later on… その者。のちに… | E28: Light Novel, Action, Adventure, Comedy, Drama, Fantasy, Harem, Romance, Adapted to Manga, Beastkin, Childhood Friends, Demon Lord, Demons, Dense Protagonist, Dragons, Elves, Emotionally Weak Protagonist, Goddesses, Male Protagonist, Monsters, Multiple POV, Overpowered Protagonist, Polygamy, Schemes And Conspiracies, Sword And Magic, Unrequited Love, Weak to Strong, Japanese, NAHAaTO, ナハァト, Miya Kazutomo, 三弥カズトモ, Earth Star Entertainment, That Person. Later on…, | F28: https://www.novelupdates.com/series/sono-mono-nochi-ni-ln/
A29: The Evil Wizard’s Reformation | B29: A nobody salaryman reincarnates as a notorious villainous wizard!? Sato had been ground down by overwork and meager pay in the modern world, exploited by everyone around him for being a “nice guy.” Then one day, he woke up to find himself in another world entirely. And not just anywhere in that world — he found himself inside the Storm Tower, home of the most feared being in the land: “Prospero the Evil Wizard.” Before he could even make sense of the situation, Sato was more or less forcibly thrust into the role of Prospero himself. Completely bewildered and desperate to get back to his old life as soon as possible, Sato nevertheless can’t bring himself to turn away a visitor who has come seeking Prospero — and before he knows it, he’s setting off on a journey alongside Ariel, a foul-mouthed fairy, to sort out the visitor’s troubles. He gets targeted by the daughter of a demon clan. He gets captured by ruthless, villainous pirates. Throughout this wild, turbulent journey across another world, Sato is absolutely certain he’s been acting like a “nice guy” — and yet, through no intention of his own, his fearsome reputation as a villain only grows more polished with every step. But then, a single fateful encounter shakes Sato’s path to its very core——. A misunderstanding-filled, misconception-fueled adventure fantasy, starring a villainous wizard who can’t quite live up to his own legend. | C29: Adventure, Comedy, Drama, Fantasy, Seinen | D29: Akuyaku mahōtsukai no kaishin The Evil Wizard’s Reformation (Light Novel) 悪役魔法使いの改心 | E29: Light Novel, Adventure, Comedy, Drama, Fantasy, Seinen, Fantasy World, Magic, Male Protagonist, Misunderstandings, Modern Knowledge, Transmigration, Japanese, 風見鶏, Toi8, MFブックス | F29: https://www.novelupdates.com/series/the-evil-wizards-reformation/
A30: We Two Losers Absolutely, Positively Have to Be Happy! | B30: Watanuki Amou, who finally became lovers with his long-time crush and childhood friend Washizaki Karen—witnessed Karen’s cheating scene just one month into dating! Furthermore, the grade’s number one cool beauty, Mamiya Sachika, barged into the scene and punched the man she was cheating with!? Upon hearing the circumstances, it turns out the man she was cheating with is Sachika’s fiancé. Perhaps out of sympathy for being similarly betrayed, Sachika proposes a pseudo-romance to Amou. The pseudo-romance with Sachika, which began with the idea of healing their wounds by doing things—even just for show—that they couldn’t do with their respective partners, is filled with a sense of fulfillment that’s hard to believe is a lie!? Is this the opening of a heartbreaking rom-com!? | C30: Comedy, Psychological, Romance, School Life, Slice of Life | D30: 負け犬同士はぜぇぇぇぇぇったいに幸せにならなくちゃいけない! | E30: Light Novel, Comedy, Psychological, Romance, School Life, Slice of Life, Male Protagonist, Netorare, Japanese, としぞう, あろあ, Kadokawa | F30: https://www.novelupdates.com/series/we-two-losers-absolutely-positively-have-to-be-happy/
A31: The Villainous Aristocrat Dominates with Humility and Honesty ~Using Original Knowledge and the Unique Magic to Avoid the Ruin End (LN) | B31: Hollow von Heisenberg is the villainous aristocrat of the smash-hit RPG Ronzolquia. Gifted with peerless talent in the blade, the arcane, and the arts, he is technically the game’s most powerful character—yet his sloth and arrogance are his undoing. Overconfident in his natural abilities and allergic to hard work, he is a man doomed to die in every single branch of the story. And of all the luck, that is the character I’ve been reincarnated as. “If I stay on this path, I’m as good as dead,” I muttered. “The ‘scenario’—this world’s pre-established harmony—is going to kill me…” …Like hell I’ll let that happen! I’ll use my knowledge of the game to craft a serious meta-build and master my Unique Magic: until every enemy attack is rendered useless! By staying humble, staying sincere, and putting in the damn work, I’m going to survive this ruinous ending no matter what! The smash-hit, next-generation reincarnation fantasy is finally in print! | C31: Action, Adventure, Fantasy, Harem, Shounen, Supernatural | D31: 極悪貴族、謙虚堅実に無双する ～原作知識と固有魔法＜虚空＞を駆使して、破滅エンドを回避します～ | E31: Light Novel, Action, Adventure, Fantasy, Harem, Shounen, Supernatural, Academy, Battle Academy, Beautiful Female Lead, Magic, Male Protagonist, Overpowered Protagonist, Reincarnated in a Game World, Japanese, 月島 秀一, しずま よしのり, Kadokawa | F31: https://www.novelupdates.com/series/the-villainous-aristocrat-dominates-with-humility-and-honesty-using-original-knowledge-and-the-unique-magic-to-avoid-the-ruin-end-ln/
... A61: Once I Became Friends with Hoshigasaki-san, the Cutest Girl in My Grade, She Won’t Stop Clinging to Me Every Day | B61: “W-Will you… b-be friends with me—?” Their friendship began with those unexpected words from Hoshigasaki Hina, the girl rumored to be the cutest in their grade. But while she acted bright and cheerful in public, she was secretly a “disappointing” beauty with absolutely zero self-confidence……? “I… want a friend… -gasaki…” After discovering the real Hoshigasaki-san and starting a secret relationship, her sense of personal distance was, for some reason, completely skewed. She invited him to a sleepover for just the two of them to “deepen their bond,” and the messages on his smartphone never stopped… This is a “broken-distance” slow-burn sweet rom-com about the non-stop clinginess of Hoshigasaki-san—a girl who was (a little?) heavy, but actually incredibly shy! | C61: Comedy, Romance, School Life | D61: 学年で一番かわいい星ヶ崎さんと友だちになったら毎日密着が止まらない | E61: Light Novel, Comedy, Romance, School Life, Japanese, 五十嵐 雄策, たん旦, Kadokawa | F61: https://www.novelupdates.com/series/once-i-became-friends-with-hoshigasaki-san-the-cutest-girl-in-my-grade-she-wont-stop-clinging-to-me-every-day/
A62: About the Reckless Girl Who Kept Challenging a Reborn Man Like Me | B62: “A prodigy at ten, a genius at fifteen, a common man past twenty.” This is a story of the struggle of an ordinary guy like me who is a “reincarnator” and a reckless and promising girl who is a “genius”. | C62: Drama, Fantasy, Romance, School Life, Shounen, Slice of Life | D62: Tenseisha de Aru Watashi ni Idonde Kuru Mubou de Yubou na Shoujo no Hanashi เกิดใหม่ทั้งที ต้องมีเธอเป็นคู่ปรับ 転生者である私に挑んでくる無謀で有望な少女の話 転生者の私に挑んでくる無謀で有望な少女の話 | E62: Light Novel, Drama, Fantasy, Romance, School Life, Shounen, Slice of Life, Age Progression, Alternate World, Appearance Different from Actual Age, Beautiful Female Lead, Calm Protagonist, Caring Protagonist, Childhood Friends, Childhood Love, Chuunibyou, Clingy Lover, College/University, Depression, Devoted Love Interests, Doting Love Interests, Fantasy World, First Love, Genius Protagonist, Hard-Working Protagonist, Helpful Protagonist, Indecisive Protagonist, Love Interest Falls in Love First, Love Rivals, Magic, Male Protagonist, Marriage, Modern Day, Past Trauma, Previous Life Talent, Rivalry, Second Chance, Teachers, Time Skip, Time Travel, Tomboyish Female Lead, Japanese, Kohigashi Nora, 小東のら, Kazuharu Kina, 和遥キナ, Shufunotomosha, Syosetu, Our Second Master, I Got Reincarnated And Mistaken As A Genius?, Love Me Again, Observation Record of a Self-proclaimed Villainess’ Fiance, Can’t Hide My Feelings, My Ears Say They Want to Know You, | F62: https://www.novelupdates.com/series/about-the-reckless-girl-who-kept-challenging-a-reborn-man-like-me/ | G62: 39
A63: Drop Dead, My Beloved Mages | B63: The “School Islands”—a floating city where over a thousand magic academies compete, perched on the boundary between our world and the next. There is only one rule here: use any means necessary to push your academy to the top of the rankings. “I’m going to spend a youth that’s beyond the ordinary here in these islands!” Kuro, a boy with extraordinary powers who was exiled from Earth, enrolls in the Royal Tritonis Academy. However, the once-prestigious school is now on the brink of closure. The only students remaining are three girls, each more eccentric than the last. In a place that holds everything “fantasy” has to offer, a non-standard, high-octane school battle fantasy begins! | C63: Action, Fantasy, Harem, Romance, School Life, Shounen, Supernatural | D63: くたばれ愛しの魔術師ども | E63: Light Novel, Action, Fantasy, Harem, Romance, School Life, Shounen, Supernatural, Academy, Alternate World, Battle Academy, Beautiful Female Lead, Betrayal, Caring Protagonist, Childhood Friends, Determined Protagonist, Fantasy World, Gate to Another World, Hidden Abilities, Magic, Male Protagonist, Naive Protagonist, Royalty, Schemes And Conspiracies, Strong Love Interests, Vampires, Japanese, 佐藤真登, ニリツ, GA Bunko | F63: https://www.novelupdates.com/series/drop-dead-my-beloved-mages/
A64: Kanojo no ane wa 2-shū-me no kanojo | B64: “I’ll be waiting in the future.” A promise like that… it’s just impossible. ​Shibukawa Ryuuichi’s life changes the moment he steps into the home of his girlfriend, Asada Miharu, and meets her twin sister, Sayuki. Unlike the earnest, innocent girl he’s dating, Sayuki carries an aura of sophisticated maturity—and she has a secret that defies logic. ​『Actually… I’m the “Miharu” from the future.』 ​Sayuki explains the unthinkable: she is a version of Miharu who time-leaped, reincarnating as her own twin sister to repeat her life. In that first loop, she and Ryuuichi drifted apart until their relationship shattered. Now, she’s back with a mission. ​『We failed each other once. So, I want you to practice with me… that way, you won’t have to lose her this time.』 ​Overwhelmed by her ability to predict every coming event with terrifying accuracy, Ryuuichi is forced into a secret, co-dependent pact. But Sayuki’s “guidance” is far from innocent. Armed with future knowledge of his deepest desires and every hidden preference, she uses her “pre-studied” love to launch a meticulous, seductive assault on his senses. ​Caught between his pure-hearted girlfriend and the sister who knows his soul better than he does himself, Ryuuichi find himself drowning in a temptation he can’t resist. | C64: Drama, Harem, Romance, School Life, Supernatural | D64: 彼女の姉は２周目の彼女 | E64: Light Novel, Drama, Harem, Romance, School Life, Supernatural, Beautiful Female Lead, Male Protagonist, Modern Day, Reincarnation, Time Loop, Twins, Japanese, 眞田, ういり, MF Bunko | F64: https://www.novelupdates.com/series/kanojo-no-ane-wa-2-shu-me-no-kanojo/
A65: I’m Actually a Girl, You Know? | B65: A sweet and flirtatious romcom spun with the best ex-“guy friend” who is easygoing and on the exact same wavelength! Hayate, a handsome boy junior one year younger than me. Being easy to talk to and on the same wavelength, we hit it off the moment we met. Huddling shoulder-to-shoulder to watch anime on a single smartphone, getting hugged, or even sharing indirect kisses—none of it was a problem if we were just friends. …But, he feels strangely soft and nice to the touch. That’s because this guy is—— Even after it was revealed that Hayate wasn’t a handsome boy but a “beautiful girl,” we still ate lunch together and hung out after school just like usual. Furthermore, she proposed a date to cure my distrust of women, and the distance between Hayate and I is closing rapidly!? “Since it’s me, your ‘guy friend,’ it’s okay to touch me more, right?” With the sense of distance remaining like that of guy friends, I am going to be made increasingly aware that Hayate is a “girl,” and a cute, special one at that. Plus, the [Digital Special Edition] includes a newly written episode! | C65: Comedy, Drama, Harem, Romance, School Life, Slice of Life | D65: Watashi, Kore de mo Onnanoko nan su yo? わたし、コレでも女の子なんすよ? | E65: Light Novel, Comedy, Drama, Harem, Romance, School Life, Slice of Life, Androgynous Characters, Male Protagonist, Modern Day, Japanese, Shijou Kanata, 四条 彼方, Unapoppo, Kadokawa | F65: https://www.novelupdates.com/series/im-actually-a-girl-you-know/
A66: Adventures of a Runemaster | B66: 「Paying with your body──are you really okay with this kind of 『contract』?」 Let’s begin a hard erot*c fantasy story woven by runes. | C66: Action, Adult, Ecchi, Fantasy, Harem, Mature, Psychological, Romance | D66: Haburare Rune-tsukai no Isekai Boukentan ハブられルーン使いの異世界冒険譚 | E66: Light Novel, Action, Adult, Ecchi, Fantasy, Harem, Mature, Psychological, Romance, Adapted to Manga, Adventurers, Cold Protagonist, Cunning Protagonist, Depictions of Cruelty, Dungeons, Magic, Revenge, Transported to Another World, Japanese, 黄金の黒山羊, Kikuchi Seiji, 菊池 政治, GC Novels, GCN Bunko, Micro Magazine | F66: https://www.novelupdates.com/series/adventures-of-a-runemaster/
A67: Transferred to Another World and Became a Teacher, But I’m Feared as a Witch | B67: The Strongest Rookie Female Teacher Breaks Through the Academy’s Old Ways!? Aoi, who was a school teacher, suddenly found herself transported to another world. Rescued by a sage of the forest, she was taught magic. Having mastered it in no time, she was recommended to join the world’s largest magic academy as a teacher to further her studies. However, the academy was plagued with troublemakers from noble families who even the teachers couldn’t handle… “Royalty? Nobility? It doesn’t matter. Students who misbehave too much will be punished.” With her overwhelming magical prowess, Aoi casually instructs her students. But as she does so, she begins to be called a “witch” and feared by others. | C67: Action, Adventure, Comedy, Fantasy, Romance, School Life, Shoujo, Slice of Life | D67: Isekai Teni Shite Kyoushi ni Nattaga, Majo to Osorerarete Iru Ken The Fearsome Witch Teaches in Another World [Official] 異世界転移して教師になったが, 魔女と恐れられている件 | E67: Light Novel, Action, Adventure, Comedy, Fantasy, Romance, School Life, Shoujo, Slice of Life, Academy, Adapted to Manga, Artifacts, Beastkin, Calm Protagonist, Dragons, Dwarfs, Elemental Magic, Elves, Fantasy World, Female Protagonist, Kingdoms, Lack of Common Sense, Magic, Magic Formations, Magical Technology, Nobles, Overpowered Protagonist, Protagonist Strong from the Start, Reincarnated in Another World, Royalty, Teachers, Japanese, Inoue Mitsuru, 井上みつる, 鈴ノ, Earth Star Novel, アース-スター エンターテイメント, J-Novel Club | F67: https://www.novelupdates.com/series/transferred-to-another-world-and-became-a-teacher-but-im-feared-as-a-witch/
A68: Goodbye, Fairy | B68: April, 1991. The sudden appearance of a single girl taking shelter from the rain brought us days upon days of endless wonder. Her name was Maja, and she came from a faraway land. Since that moment, we spent our days with her, each one bounding with mystery. After she returned to her country, however, was when our greatest mystery began, and the key to solving it rests somewhere within our memories. This is the story of an unforgettable meeting and a prayer. First book in the Beruf series. | C68: Mystery, Psychological | D68: Beruf Series I - Goodbye, Fairy Sayonara Yousei さよなら妖精 | E68: Light Novel, Mystery, Psychological, Japanese, Yonezawa Honobu, Tokyo Sogensha, Hyouka | F68: https://www.novelupdates.com/series/goodbye-fairy/
A69: Dakara Boku wa, H ga Dekinai. | B69: Kaga Ryosuke, a helplessly romantic teenager, was walking in the rain when he sees a beautiful girl with red eyes drenched in the rain. Everyone was avoiding her, but Ryosuke was taught to treasure women so he offered his help by letting her dry off at his home. Ryosuke can’t imagine that this mysterious girl would stab him in the chest and leave him to die… Or did she? Who is this pretty girl and what does she want with him? | C69: Comedy, Ecchi, Fantasy, Harem, Mature, Romance, Shounen, Supernatural | D69: So, I Can't Play H? だから僕は、Hができない。 | E69: Light Novel, Comedy, Ecchi, Fantasy, Harem, Mature, Romance, Shounen, Supernatural, Adapted to Anime, Adapted to Manga, Contracts, Demons, Family, Magic, Male Protagonist, Modern Day, Nudity, Japanese, Tachibana Pan, 橘 ぱん, Katsurai Yoshiaki, 桂井よしあき, Fujimi Shobo, Boku no Bungeibu ni Bitch ga Irunante Arienai, Jaku-chara Tomozaki-kun, Ordinary I and Extraordinary Them | F69: https://www.novelupdates.com/series/dakara-boku-wa-h-ga-dekinai/
A70: At the Fallen Angel Majesty’s Command. Eh? I’m the One Who Has to End the Apocalyptic War? | B70: Everyone lives their life following someone else’s orders. …Then what the heck is freedom anyway? That’s what I, Shinichi Madarame, was thinking as I skipped high school to work part-time at a small odd-jobs shop in town called “Eikokuya” (The British House). The owner, Miss Eri, is a somewhat mysterious woman. She calls herself “Your Majesty,” doesn’t die even with glass stuck in her neck, and can control my body with her “King’s Order.” She’s definitely not normal, but she’s a beautiful woman who smells incredibly good, so I’m always by her side. Our current job is to find a keychain that a girl lost. But before I knew it, we got caught up in a “Holy Grail” war between angels and demons. This serious battle doesn’t really match our usual vibe, you know? But I’ll fight properly, following Her Majesty’s orders. Because I know she’s the kindest person in the world. “Defeat all enemies. In the name of the Queen.” “Yes, Your Majesty.” | C70: Action, Comedy, Fantasy, Shounen | D70: Datenshi Heika no Oose no mama ni. E? Ore ga Mokushiroku Sensō o owaraseru n desu ka? In the name of Her Majesty, the Fallen Angel's Command. Eh? I'm the one who has to end the Apocalyptic War? (Light Novel) 堕天使陛下の仰せのままに え？俺が黙示録戦争を終わらせるんですか？ | E70: Light Novel, Action, Comedy, Fantasy, Shounen, Beautiful Female Lead, Magic, Male Protagonist, Master-Servant Relationship, Japanese, 西 条陽, らう, MF Bunko J | F70: https://www.novelupdates.com/series/at-the-fallen-angel-majestys-command-eh-im-the-one-who-has-to-end-the-apocalyptic-war/
A71: Mind-Reading Detective: Oba Kanako Is Kinda Dumb – I Can Easily Identify the Culprit Thanks to My Mind Reading, But I Have No Idea How to Prove It | B71: A new mystery-solving comedy that breaks all the classic detective rules begins! From [Last Dungeon] creators Satou and Shio— Their latest work stars a mind-reading high school girl detective!? Kanako Ōba is a high school girl with the ability to read people’s minds. Surely, this power makes her the ultimate detective, right!? Confident she can solve tricky cases with style and rake in the cash— Unfortunately, Kanako is kinda dumb! “I know the trick. I know who the culprit is. But—there’s no evidence anywhere!” Ahhh, she’s a telepath, but she’s s*upid! Can she really be a detective like this!? Locked-room mysteries, vanished wills, bizarre thematic serial mu*ders— She can see right through the culprit’s secrets, But when it comes to actually proving it, she’s totally clueless! A mystery-breaking comedy where the rules are tossed out the window, And the detective reads the culprit’s mind directly— Let the outrageous new deduction drama begin! | C71: Comedy, Mystery, School Life, Slice of Life, Supernatural | D71: Satoru kokoro tantei Oba Kanako wa atama ga warui ~ kokoro ga yomerukara shinhan'nin tokutei made wa yoyūdesukedo shōmei hōhō ga zenzen wakarimasen ~ 読心探偵・大葉香夏子は頭がわるい～心が読めるから真犯人特定までは余裕ですけど証明方法が全然わかりません～ | E71: Light Novel, Comedy, Mystery, School Life, Slice of Life, Supernatural, Cheats, Detectives, Female Protagonist, Modern Day, Mystery Solving, Police, Special Abilities, Japanese, サトウとシオ, 日下氏, GA Bunko, Softbank Creative | F71: https://www.novelupdates.com/series/mind-reading-detective-oba-kanako-is-kinda-dumb-i-can-easily-identify-the-culprit-thanks-to-my-mind-reading-but-i-have-no-idea-how-to-prove-it/
A72: Spirit Master Who Is Thought to Be Hiding His True Ability Is Actually Always Fighting Very Seriously | B72: “Spirit Mages” fight evil threats to humanity by borrowing the power of contracted spirits. Roak Aleas, a second-year student at Utrea Academy, the training institution for Spirit Mages, possesses skills ranking second in his year. Yet, he has never once summoned a contracted spirit, leading the entire academy to focus on him, evaluating that he “must be hiding his true power.” However, as for Roak himself– “Why don’t I summon my contracted spirit? Because I don’t have any (—)!” His strength comes solely from endlessly honing his swordsmanship and martial arts using the only spirit he can contract – a micro-spirit. In reality, he’s always fighting desperately just to stay alive…!? Amidst all this, he gets chosen as a member to explore the highly dangerous “Lunar Ruins”…!? The Spirit Mage who everyone thinks is hiding his true power actually always fights with everything he’s got. He’s not refusing to summon his Contracted Spirits, he just doesn’t have any! — this Spirit Mage is still too strong!? A fantasy of misunderstood overpowered heroism, surpassing even the strongest through effort alone! | C72: Action, Adventure, Comedy, Fantasy, Harem, Martial Arts, School Life, Shounen | D72: Shin no jitsuryoku o kakushite iru to omowa re teru seirei-shi, jitsuwa itsumo metcha honki de tatakattemasu 真の実力を隠していると思われてる精霊師, 実はいつもめっちゃ本気で戦ってます | E72: Light Novel, Action, Adventure, Comedy, Fantasy, Harem, Martial Arts, School Life, Shounen, Academy, Adapted to Manga, Beautiful Female Lead, Famous Protagonist, Fantasy World, Hard-Working Protagonist, Hiding True Abilities, Magic, Male Protagonist, Misunderstandings, Overpowered Protagonist, Pragmatic Protagonist, Spirit Users, Summoning Magic, Sword And Magic, Sword Wielder, Underestimated Protagonist, Japanese, Arasamu, アラサム, Katana Canata, 刀 彼方, Overlap, Surviving as the Academy’s Weakest NPC, T*ash of the Count’s Family, A Story About a Mob Character in a World Where Magic and Supernatural Powers Exist, But Who’s Treated as the Mastermind Behind the Scenes, Became the Patron of Villains, I’m Really Not The Demon God’s Lackey, Story of The Ancient Demon King!, | F72: https://www.novelupdates.com/series/spirit-master-who-is-thought-to-be-hiding-his-true-ability-is-actually-always-fighting-very-seriously/
A73: Kuro no Senki (LN) | B73: Chrono(real name Kurono) Crawford, a noble of the Cepheus Empire, had a secret. It was that he came from a different world… From modern Japan. He didn’t know how or why he was sent here, he wasn’t bestowed with any “cheat” abilities and his knowledge of modern technology was only that of a teenager’s. A young man with modern values in a savage world, he is abandoned by his superiors, left in command of the Empire’s rejects consisting of demi-humans such as Minotaurs, Dwarves, and Elves, and thrust into a position as head of a poor fiefdom. Chrono will do everything he can to rebuild and strengthen his forces and revitalize the land, aided in part by his knowledge from the other world. He is also aided by many capable women and becomes a harem king. | C73: Action, Adult, Ecchi, Fantasy, Harem, Mature, Romance | D73: Chrono's War Record Kurono's War Record Record of Kurono's War: It seems that I, who have moved to another world, am the strongest only in bed クロの戦記 | E73: Light Novel, Action, Adult, Ecchi, Fantasy, Harem, Mature, Romance, An*l, Adapted to Manga, Beastkin, Caring Protagonist, Clever Protagonist, Discrimination, Domestic Affairs, Dwarfs, Elves, Fantasy Creatures, First-time Interc**rse, Human-Nonhuman Relationship, Kingdom Building, Kingdoms, Male Protagonist, Merchants, Modern Knowledge, Nobles, Politics, Polygamy, Protagonist Strong from the Start, R-15, Royalty, Strategic Battles, Strong Love Interests, Transported to Another World, Twins, Wars, Japanese, Saito Ayumu, サイトウアユム, Mutsumi Masato, むつみまさと, Hobby Japan, The Defeated Dragon, Demon King on the Border, Fire Arrow? No, This Is a Rifle!!!, Fun Territory Defense of the Easy-Going Lord ~The Nameless Village Is Made Into the Strongest Fortified City by Production Magic~, Reincarnated as an Emperor ~ Will the Emperor at Birth Survive?, | F73: https://www.novelupdates.com/series/kuro-no-senki-ln/
A74: Run Over | B74: After Mintato Rica’s transfer into the class, everything changed. But even though she was made into an object of persecution, the girl didn’t lose herself and became acquainted with Idzono. Having learned his secret, the mysterious individual compelled her classmate into living together and made an astonishing proposal: to get revenge on the two instigators. At first, Idzono was reluctant, but then slowly starts to agree with Minato’s methods. After befriending Haru, another victim of bullying, they start to raise a mutiny. | C74: Adult, Drama, Mature, Mystery, Psychological, Romance, School Life, Tragedy | D74: ラン・オーバー | E74: Light Novel, Adult, Drama, Mature, Mystery, Psychological, Romance, School Life, Tragedy, Anti-social Protagonist, Antihero Protagonist, Apathetic Protagonist, Betrayal, Blackmail, Bullying, Cold Love Interests, Cold Protagonist, Criminals, Cruel Characters, Delinquents, Delusions, Depictions of Cruelty, Depression, Evil Protagonist, Hated Protagonist, Loner Protagonist, Male Protagonist, Manipulative Characters, Modern Day, Murders, Obsessive Love, Pretend Lovers, Psychopaths, Revenge, Suicides, Torture, Twisted Personality, Yandere, Japanese, Inaniwa Jun, 稲庭淳, Kō Mashiro, こうましろ, Boku no Bungeibu ni B*tch ga Irunante Arienai, Jaku-chara Tomozaki-kun, Omae wo Onii-chan ni Shite Yarouka!?, Ordinary I and Extraordinary Them, The Elf Is a Freeloader, Gekkou | F74: https://www.novelupdates.com/series/run-over/
... A102: Oda Nobuna no Yabou | B102: Suddenly finding himself in the Sengoku era, regular high school student Sagara Yoshiharu is about to be killed in the battlefield. He is saved by none other than the man who later becomes the infamous Toyotomi Hideyoshi but at a cost to his life. With history completely changed because of Yoshiharu’s actions, he tries to make things right again but it seems that history is taking a different course than the one he learned in school. Oda Nobunaga is now a brilliant but young girl named Oda Nobuna. Yoshiharu starts working under her command to bring back history to its correct course and find his way back home to the present world. | C102: Action, Adventure, Comedy, Ecchi, Fantasy, Harem, Historical, Shounen | D102: Oda Nobuna's Ambition 織田信奈の野望 織田信奈的野望 | E102: Light Novel, Action, Adventure, Comedy, Ecchi, Fantasy, Harem, Historical, Shounen, Adapted to Anime, Adapted to Manga, Alternate World, Androgynous Characters, Arrogant Characters, Average-looking Protagonist, Charismatic Protagonist, Chuunibyou, Clever Protagonist, Dense Protagonist, Determined Protagonist, Hard-Working Protagonist, Heterochromia, Loli, Male Protagonist, Marriage, Pe*verted Protagonist, Proactive Protagonist, Protagonist Falls in Love First, Samurai, Stoic Characters, Strong Love Interests, Time Travel, Tsundere, Weak Protagonist, Yandere, Japanese, Kasuga Mikage, Miyama-Zero, みやま零, Fujimi Shobo, Softbank Creative, Don’t Tell Me This Is the True History of the Three Kingdoms!, My Father in Law is Lu Bu, Altina the Sword Princess, Madan no Ou to Vanadis, Japanese-style Sengoku Survival ~ Survive the Sengoku Fantasy ~, Romance of The Three Kingdoms, | F102: https://www.novelupdates.com/series/oda-nobuna-no-yabou/
A103: Gosick | B103: Set in a fictional European country in 1924, a Japanese exchange student meets a mysterious, brilliant girl who only leaves the library to sleep. Her brother, a detective, relies on her mind to solve difficult mysteries, several of which draw her away from the library. With a drop of sweet romance, you will immediately become addicted to Gosick!!! The companion series GosickS fills in some of the gaps before and between Gosick volumes. GosickS I takes place before Gosick I, GosickS II between Gosick IV and V, GosickS III between Gosick VI and VII, and GosickS IV between Gosick VII and VIIIa. Note: Volume 9 is actually Volume 8 Part 2. | C103: Adventure, Drama, Mystery, Romance | D103: ゴシック | E103: Light Novel, Adventure, Drama, Mystery, Romance, Academy, Adapted to Anime, Adapted to Manga, Alternate World, Bickering Couple, Books, Complex Family Relationships, Couple Growth, Detectives, European Ambience, Human-Nonhuman Relationship, Loli, Male Protagonist, Past Plays a Big Role, Teachers, Tragic Past, Wars, Japanese, Sakuraba Kazuki, Takeda Hinata, Fujimi Shobo, Kadokawa, Gekkou, Jaku-chara Tomozaki-kun, Ordinary I and Extraordinary Them, The Case Files of Jeweler Richard, Detective Jiang Tian | F103: https://www.novelupdates.com/series/gosick/ | G103: 80
A104: I Desperately Avoided the Annihilation Ending. The Party Became Sick | B104: “–Wolka?! Noooooo!! Y-you can’t die on me!!” Wolka, an adventurer, is a reincarnator from Japan. During a dungeon exploration, his party is ambushed by a powerful monster, and Wolka suffers fatal injuries while protecting his companions; in his final moments, he finally remembers the world he had reincarnated into was that of a dark fantasy manga he read in his previous life — that he and his companions were minor characters to be annihilated then and there. But Wolka, empowered by his hatred for bad endings, desperately presses on for the sake of his companions — and defeats the monster. It only cost him an eye and a leg — but in exchange, he and his party escaped their intended fate. What he did not account for, however, was how the experience changed the young girls that were his companions. “I swear I’ll protect you this time!! So please, please, don’t abandon me..!” “I’ll always be by your side… You’re fine with that, right, senpai?” “I would give my life for yours… That is what I decided.” This is the murky, otherworldly story of a reincarnated man who values happy endings above all and the girls who harbor intense feelings for him! | C104: Drama, Fantasy, Harem, Romance, Shounen | D104: After a Desperate Struggle to Avoid Annihilation, My Party Became Unwell Our Party Nearly Wiped and Then Everything Went Downhill Zenmetsu END wo Shinimonogurui de Kaihishita. Party ga Yanda. 全滅エンドを死に物狂いで回避した。パーティが病んだ。 | E104: Light Novel, Drama, Fantasy, Harem, Romance, Shounen, Adapted to Manga, Clingy Lover, Dense Protagonist, Depictions of Cruelty, Devoted Love Interests, Disabilities, Doting Love Interests, Fantasy World, Genius Protagonist, Hard-Working Protagonist, Inferiority Complex, Love Interest Falls in Love First, Magic, Magic Beasts, Male Protagonist, Mob Protagonist, Monsters, Multiple POV, Naive Protagonist, Near-Death Experience, Obsessive Love, Overpowered Protagonist, Reincarnated in Another World, Sword And Magic, Sword Wielder, Yandere, Japanese, Ameito Suzume, 雨糸雀, kodamazon, Kadokawa, Kakuyomu, Yen Press, I Like Villains, so I Reincarnated as One, I Was Reincarnated as the Strongest and Most Evil Noble Who Controls the Darkness of the Kingdom, I was Reincarnated as the Youngest Child of a Villainous Noble Family Who Controls the Kingdom from Behind the Scenes | F104: https://www.novelupdates.com/series/i-desperately-avoided-the-annihilation-ending-the-party-became-sick/
A105: The Neighboring Aarya-san who Sometimes Acts Affectionate and Murmuring in Russian | B105: Smart, refined, and strikingly gorgeous, Alisa Mikhailovna Kujou, half-Russian and half-Japanese, is considered the idol of her school. Adorned with long silver hair, mesmerizing blue eyes, and exceptionally fair skin, she has captured the hearts of countless male students while being highly admired by all others. Even so, due to her seemingly unapproachable persona, everyone remains wary around the near-flawless girl. One of the only few exceptions from such a norm is Alisa’s seatmate, Masachika Kuze—a relatively average boy who spends his days watching anime and playing gacha games. Despite his nonchalant demeanor, Masachika is the sole student to receive Alisa’s attention. Unable to be fully honest, Alisa is frequently harsh on Masachika, resorting to Russian to express her affection. Unbeknownst to her, however, Masachika actually understands the language yet simply pretends otherwise for his own amusement. As the odd pair continues to exchange their witty and playful remarks, their relationship gradually grows more romantic and delightful—and a day may come when Alisa might finally learn to freely convey her true feelings. | C105: Comedy, Drama, Ecchi, Harem, Romance, School Life, Shounen, Slice of Life | D105: Alya, Who Sits Next to Me, Sometimes Whispers Sweet Nothings in Russian Alya Sometimes Hides Her Feelings in Russian Arya bàn bên thỉnh thoảng lại trêu ghẹo tôi bằng tiếng Nga Roshidere Tokidoki Bosotto Roshia-go de Dereru Tonari no Alya-san ロシデレ 不時輕聲地以俄語遮羞的鄰座艾莉同學 時々ボソッとロシア語でデレる隣のアーリャさん | E105: Light Novel, Comedy, Drama, Ecchi, Harem, Romance, School Life, Shounen, Slice of Life, Absent Parents, Adapted to Anime, Adapted to Manga, Award-winning Work, Beautiful Female Lead, Brother Complex, Calm Protagonist, Caring Protagonist, Character Growth, Childhood Friends, Childhood Love, Clever Protagonist, Cold Love Interests, Complex Family Relationships, Cute Story, Handsome Male Lead, Lazy Protagonist, Love Interest Falls in Love First, Love Triangles, Male Protagonist, Misunderstandings, Modern Day, Multiple POV, Past Trauma, Popular Love Interests, Siblings, Student Council, Tsundere, Younger Sisters, Japanese, Sunsunsun, 燦々SUN, Momoco, ももこ, Kadokawa Sneaker Bunko, Yen Press, The Delinquent Shimizu-san Sitting Next to Me Has Dyed Her Hair Black, I’m The Only Multilingual Master a Russian Transfer Girl Student Who Can’t Speak Japanese Can Rely On, After Coincidentally Saving the New Transfer Student’s Little Sister, We Gradually Grew Closer, How to Keep a Distance from a Beautiful Girl, I Quit the Going-Home Club for a Girl with a Venomous Tongue, Otonari no Tenshi-sama ni Itsu no Ma ni ka Dame Ningen ni Sareteita Ken (WN), | F105: https://www.novelupdates.com/series/the-neighboring-aarya-san-who-sometimes-acts-affectionate-and-murmuring-in-russian/ | G105: 15
A106: She Was Killed By Shooting Stars | B106: On that day, all the satellites in orbit plummeted and vanished like specks of light in the atmosphere. This event, called “the world’s most beautiful terrorist attack,” had only one casualty! Daichi Hirano, a high school student, must battle fate in order to save Hoshino Amano, a solitary girl. The story’s major themes are “space” and “dreams.” | C106: Action, Adventure, Mystery, Romance, Sci-fi, Supernatural, Tragedy | D106: Kimi Shinita Mou Ryuuseigun 君死にたもう流星群 | E106: Light Novel, Action, Adventure, Mystery, Romance, Sci-fi, Supernatural, Tragedy, Beautiful Female Lead, Evil Organizations, Male Protagonist, Mature Protagonist, Modern Day, Mystery Solving, Proactive Protagonist, Time Travel, Japanese, Matsuyama Takeshi, 松山剛, Coffee Kizoku, 珈琲貴族, Kadokawa, Media Factory, MF Bunko J | F106: https://www.novelupdates.com/series/she-was-killed-by-shooting-stars/
A107: Kogoroshi Village | B107: In a remote rural village, a photographer visits to investigate what is rumored to be a “power spot.” What begins as a routine assignment gradually reveals something far more unsettling beneath the surface of the community. Blending social commentary with psychological tension, the novel explores belief, exploitation, isolation, and the fragile boundaries between reverence and desire. While there are no overt BL depictions, the story features a delicately balanced relationship, neither quite romance nor quite affection, that develops involving the photographer. | C107: Drama, Mystery, Psychological, Tragedy | D107: Kogoroshimura コゴロシムラ | E107: Light Novel, Drama, Mystery, Psychological, Tragedy, Abandoned Children, Androgynous Characters, Child Abuse, Co-Workers, Cross-dressing, Death of Loved Ones, Disabilities, Forced Living Arrangements, Murders, Mysterious Family Background, Mystery Solving, Japanese, Konohara Narise, 木原音瀬, Asumiko Nakamura, 中村 明日美子, Kodansha | F107: https://www.novelupdates.com/series/kogoroshi-village/
A108: TS Tensei Bishōjo-on Tora Reiko wa Netora Reiko | B108: “Above all else, I want to become a cuckolded heroine!” In her past life, she was a vile villain who tore countless couples apart. Now, reincarnated as the angelic beauty Netora Reiko, her one and only desire is to experience the ultimate betrayal! As a stunning maiden who also understands the male psyche, Reiko meticulously crafts the perfect scenario to have her heart stolen. With calculated charm, she ensnares her childhood friend and his best friend, one after another! This TS (transsexual) beauty, obsessed with the thrill of being cuckolded, deceives everyone around her to shatter her childhood friend’s heart in this outrageous yet irresistible (love?) comedy!!! | C108: Drama, Ecchi, Gender Bender, Psychological, Romance, School Life, Slice of Life | D108: TS Reincarnation Beautiful Girl Netora Reiko Wants to Be C**kolded TS転生美少女音虎令子は寝取られたい | E108: Light Novel, Drama, Ecchi, Gender Bender, Psychological, Romance, School Life, Slice of Life, Acting, Adapted to Manga, Childhood Friends, Cunning Protagonist, Dishonest Protagonist, Female Protagonist, Male to Female, Manipulative Characters, Modern Day, Psychopaths, Reincarnation, Twisted Personality, Japanese, Nihonme Ebiten Man, 二本目海老天マン, さとうぽて, HJ Bunko | F108: https://www.novelupdates.com/series/ts-tensei-bishojo-on-tora-reiko-wa-netora-reiko/
A109: The Princess I Took Care Of Keeps Clinging to Me | B109: The more I attend to her, the more the Princess’s possessiveness grows—? Leon has been appointed as the caretaker for Tetra, the Third Princess. Even as he accompanies Tetra—who struggles to be honest with her feelings—to the Academy, noble ladies he previously served as a caretaker for begin to approach him… and the now-possessive Princess refuses to leave his side. | C109: Comedy, Fantasy, Harem, Romance, Slice of Life | D109: Osewa Shita Oujosama, Zutto Kuttsuite Kuru お世話した王女様、ずっとくっついてくる | E109: Light Novel, Comedy, Fantasy, Harem, Romance, Slice of Life, Aristocracy, Beautiful Female Lead, Carefree Protagonist, Caring Protagonist, Charming Protagonist, Clingy Lover, Dense Protagonist, Different Social Status, Fantasy World, Handsome Male Lead, Helpful Protagonist, Loli, Male Protagonist, Master-Servant Relationship, Nobles, Obsessive Love, Possessive Characters, Royalty, Selfless Protagonist, Tsundere, Yandere, Japanese, Natsuno Minoru, Natsunomi, 夏乃実, maruro, まるろ, Kadokawa | F109: https://www.novelupdates.com/series/the-princess-i-took-care-of-keeps-clinging-to-me-2/
A110: My Ex-Girlfriend and My Current Girlfriend Are Trying to Win My Love | B110: “Both of you, come at me with everything you’ve got as my ‘girlfriend’!” “Love is about making them chase you,” says my ex-girlfriend, Rena Aomi. “Love is about constantly going on the offensive,” says my current girlfriend, Yuka Kurebayashi. A clash of pride between two girlfriends unfolding over me! The curtain rises here on a clumsy battle-of-wits romantic comedy!! | C110: Comedy, Drama, Harem, Romance, Slice of Life | D110: Motokano to Imakano ga Ore no Ai o Kachitorou to Shite Kuru, 元カノと今カノが俺の愛を勝ち取ろうとしてくる | E110: Light Novel, Comedy, Drama, Harem, Romance, Slice of Life, Japanese, Hamubane, Kekemotsu, Kadokawa | F110: https://www.novelupdates.com/series/my-ex-girlfriend-and-my-current-girlfriend-are-trying-to-win-my-love/
A111: When Two Opposite Otaku’s Fall in Love | B111: Yamato, a plain, unremarkable guy, is actually the strongest player in a popular game. But because of his self-centered personality, he doesn’t stand out in class and spends his youth in a gray haze. Then one day, after he helps Karin—a popular girl from his class who’s being harassed in town—she somehow takes a liking to him… Karin keeps it hidden because she worries about what people will think, but she’s actually a hardcore gamer otaku. And without either of them realizing it, the two have even met inside the same game!? Yamato looks plain at first glance, but he says exactly what he thinks. Karin looks flashy at first glance, but she tends to read the room. A youth romance between two total opposites—two people who should’ve never been able to get along. | C111: Comedy, Romance, School Life | D111: 正反対なヲタクが恋をした | E111: Light Novel, Comedy, Romance, School Life, Otaku, Japanese, 九条蓮, スターツ出版 | F111: https://www.novelupdates.com/series/when-two-opposite-otakus-fall-in-love/
A112: Ano Otomege wa Oretachi ni Kibishii Sekai desu | B112: Forced by his little sister, Leon was reincarnated into the world of an Otome game that he had conquered right up to the moment of his death. He was trying to lead a peaceful life as a mob character when he encountered a single female student trying to ignore the flow of the story and try to replace the main character. After seizing Marie, a girl with an atmosphere similar to that of his little sister in a previous life, Leon succeeded in thwarting the attempt. I should have made the right choice……but what is this uneasiness? The “if route” web novel, which was a bonus in the “Mobseka” survey and received a huge response as “too tough,” has finally been published in book form with significant additions! | C112: Action, Fantasy, Harem, Mecha, Romance, Sci-fi | D112: Ano Otomege wa Oretachi ni Kibishii Sekaidesu Ano otome gē wa oretachi ni kibishī sekaidesu Anoseka That World of Otome Games is Tough for Us Trapped in a Dating Sim: Otome Games Are Tough For Us, Too! (LN) あの乙女ゲーは俺たちに厳しい世界です | E112: Light Novel, Action, Fantasy, Harem, Mecha, Romance, Sci-fi, Academy, Adapted to Manga, European Ambience, Fantasy World, Female Protagonist, Game Elements, Incest, Loli, Magic, Magical Technology, Male Protagonist, Mob Protagonist, Multiple Protagonists, Multiple Reincarnated Individuals, Nobles, Otome Game, Reincarnated in a Game World, Reincarnated in Another World, Reincarnation, Schemes And Conspiracies, Tsundere, Villainess Noble Girls, Younger Sisters, Japanese, Mishima Yomu, Wai, わい, わい／三嶋与夢, 三嶋 与夢, Toi Moge, GC Novels, Seven Seas, The World of Otome Games is Tough For Mobs, The World of Otome Game Too Tough for Mobs: Original Route | F112: https://www.novelupdates.com/series/ano-otomege-wa-oretachi-ni-kibishii-sekai-desu/ | G112: 186
A113: Forest of Drizzling Rain | B113: Novelization of the game. “The girl who had her memories erased and the boy who had his voice taken away. Ten years later, they meet at “the place of the promise.” “A protagonist who was left completely alone after her parents died in an accident. One day, she discovers a single photo in her parents’ room, with ‘Azakawa Village’ written on the back. In the photo, her mother and father, she as a young child, and a grandfather she has no memory of at all. ‘Could this possibly be my parents’ hometown?’ With loneliness and anticipation in her heart, she travels to Azakawa Village. However, that place was somewhere she should never set foot in – the place of the promise.” | C113: Adventure, Horror | D113: Kirisame ga Furu Mori 霧雨が降る森 | E113: Light Novel, Adventure, Horror, Anti-social Protagonist, Based on a Video Game, Childhood Friends, Childhood Promise, Curses, Determined Protagonist, Fearless Protagonist, Female Protagonist, Flashbacks, Folklore, Ghosts, Hiding True Identity, Inheritance, Long Separations, Multiple POV, Mute Character, Mysterious Past, Past Plays a Big Role, Secrets, Seeing Things Other Humans Can't, Spirits, Sword Wielder, Tomboyish Female Lead, Japanese, Kuchiba Tsumugi, Sanada Makoto, 朽葉つむぎ, 真田まこと, Sakoda Takeshi, 廻田武, Kadokawa, Summon Survival, Transmigrated Into a Smashing Asura Girl, When the Hacker is Forced to Marry | F113: https://www.novelupdates.com/series/forest-of-drizzling-rain/
A114: Killed Again, Mr. Detective | B114: Sakuya Otsuki, an immortal high school detective who somehow revives no matter how many times he is killed. He was killed by a criminal because of his innate humor, and while being seen by his excellent assistant Lilithea with cold eyes, he challenges a number of difficult cases based on the clues he brought back from the bottom of his death! | C114: Adventure, Comedy, Drama, Harem, Mystery, Romance, Shounen, Supernatural | D114: Matakoro Mata Korosarete Shimatta nodesune, Tantei-sama Mata Korosarete Shimatta no desu ne, Tantei-sama また殺されてしまったのですね、探偵様 你又被殺了呢，偵探大人 | E114: Light Novel, Adventure, Comedy, Drama, Harem, Mystery, Romance, Shounen, Supernatural, Adapted to Manga, Beautiful Female Lead, Detectives, Handsome Male Lead, Hard-Working Protagonist, Immortals, Kuudere, Male Protagonist, Slow Romance, Weak to Strong, Japanese, Teniwoha, Riichu, Kadokawa, Media Factory, MF Bunko J, Tantei wa Mou, Shindeiru | F114: https://www.novelupdates.com/series/killed-again-mr-detective/
A115: Exhausted with Life, I Arrived at a Village Where Beautiful Women Won’t Let Me Go | B115: “Dinner, a bath, or even sex… I’ll do it all for you, so won’t you stay here forever?” Sumuragi Takuya, a former office worker utterly exhausted after quitting his job at a “black company,” flees the city with barely any luggage and finds himself in a secluded rural area called Minorisato Village. “It’s raining quite hard outside. If you’d like, why don’t we take a break together?” Unable to refuse the sweet invitation from Anzai Mina—the beautiful woman he befriended while taking shelter from the rain—Takuya ends up staying at her home as a live-in guest. However… “Once you’re out of the bath, my mother’s delicious cooking will be waiting for you.” “If it’s what you want, Takuya-san, you can stay here forever, you know?” “…I’ll even help you release your s*xual desires like this.” In an effort to keep Takuya from ever leaving the countryside, the pampering and “healing” begin to accelerate at an overwhelming pace! It’s a self-indulgent, erotic, rural harem romantic comedy where no one will get in your way! | C115: Adult, Ecchi, Harem, Romance, Slice of Life | D115: 人生に疲れ辿り着いた村で、美女達が俺を離してくれない | E115: Light Novel, Adult, Ecchi, Harem, Romance, Slice of Life, Beautiful Female Lead, Cohabitation, Devoted Love Interests, Doting Love Interests, F*llatio, Hard-Working Protagonist, Heartwarming, H*ndjob, Kind Love Interests, Male Protagonist, Modern Day, Obsessive Love, Older Love Interests, Paizuri, Polygamy, Threesome, Japanese, Myon, みょん, ギザン, Kadokawa Sneaker Bunko | F115: https://www.novelupdates.com/series/exhausted-with-life-i-arrived-at-a-village-where-beautiful-women-wont-let-me-go/
A116: Fellow Losers Must Absooooolutely Become Happy! | B116: “As fellow losers in love… why don’t we soothe each other’s wounds?” After years of unrequited feelings, Amou Watanuki finally managed to become lovers with his childhood friend Karen Suzaki only to witness her cheating just one month into their relationship! To make things even more chaotic, the school’s number-one cool beauty, Sachika Mamiya, barges into the scene and punches Karen’s affair partner!? According to her, that cheating guy is actually her fiancé. Perhaps out of sympathy toward a fellow betrayed soul, Sachika makes an unexpected offer to Amou: “Why don’t we have a fake romance?” If they can at least experience—even in form only—the things they could never do with their original partners, maybe their hearts can heal. But once it begins, this make-believe romance with Sachika feels so fulfilling, it’s hard to believe it’s only pretend…!? A heartbreak romantic comedy begins! | C116: Comedy, Romance, School Life, Slice of Life | D116: 負け犬同士はぜぇぇぇぇぇったいに幸せにならなくちゃいけない | E116: Light Novel, Comedy, Romance, School Life, Slice of Life, Beautiful Female Lead, Betrayal, Caring Protagonist, Childhood Friends, Friendship, Male Protagonist, Modern Day, Netorare, Pretend Lovers, Japanese, Toshizou, としぞう, Aroa, あろあ | F116: https://www.novelupdates.com/series/fellow-losers-must-absooooolutely-become-happy/
A117: The Jack-of-all-trades Kicked Out of the Hero’s Party ~ The Swordsman Who Became a Support Mage Due to Party Circumstances, Becomes All Powerful (LN) | B117: “Orn Doula, as of today, you’re out of the party.” Orn had once been a swordsman, but due to party circumstances, he was forced to switch roles to an enchanter—a position he wasn’t suited for. One day, without warning, he’s dismissed from the party for being “incompetent.” With average physical abilities and magical skills, Orn has no exceptional traits. His only strength lies in his ability to quickly master any skill that ordinary people could achieve with effort—a true “jack of all trades, master of none.” Now on his own, Orn decides to return to being a swordsman. However, his time as an enchanter wasn’t wasted. The knowledge, experience, and unique spells he developed during his time with the hero’s party have transformed him into an extraordinary swordsman, defying all expectations. | C117: Action, Fantasy, Harem, Romance | D117: Yuusha Party wo Oidasareta Kiyoubinbou: Party Jijou de Fuyojitsushi wo Yatteita Kenshi, Bannou e to Itaru 勇者パーティを追い出された器用貧乏 ～パーティ事情で付与術士をやっていた剣士、万能へと至る～ | E117: Light Novel, Action, Fantasy, Harem, Romance, Adapted to Anime, Adapted to Manga, Adventurers, Beautiful Female Lead, Betrayal, Childhood Friends, Childhood Love, Childhood Promise, Clever Protagonist, Dark, Dragon Slayers, Dragons, Dungeons, Evil Organizations, Fairies, Guilds, Handsome Male Lead, Hard-Working Protagonist, Heroes, Jack of All Trades, Love Interest Falls in Love First, Male Protagonist, Master-Disciple Relationship, Mind Control, Monsters, Multiple POV, Mysterious Past, Overpowered Protagonist, Politics, Protagonist Strong from the Start, Sealed Power, Secret Organizations, Spatial Manipulation, Spirit Users, Spirits, Strong Love Interests, Strong to Stronger, Sword And Magic, Sword Wielder, Time Loop, Time Manipulation, Underestimated Protagonist, Japanese, Itsuki Togami, 都神樹, Kisaragi Yuri, きさらぎゆり, Kodansha | F117: https://www.novelupdates.com/series/the-jack-of-all-trades-kicked-out-of-the-heros-party-the-swordsman-who-became-a-support-mage-due-to-party-circumstances-becomes-all-powerful-ln/
A118: A Holy Covenant of Mourning Dedicated to the Dear Undead | B118: To save a partner imprisoned by a Demon Sword—even if I am no longer human. “I’ll set you free now.” Nostarica, a Holy Sword User turned undead, was chasing after his comrade-in-arms Molt, who had been imprisoned by a Demon Sword, alongside the cleric Linlia. Amidst a journey of mourning the people transformed into undead by the curse scattered by the Demon Sword, the desolate prologue of their separation is told. “This mission will be the last one for you, Nostarica-san. That is why—” One must not forgive the peace that is desecrated by someone’s selfishness. However, as if to obstruct them, a massive relic stands in the way of Nostarica and his companion as they chase the remnants of the Demon Sword… Save the world being eroded by the death-spreading Demon Sword with those dry hands. A buddy dark fantasy where the holy and the evil intermingle begins here!! | C118: Action, Adventure, Drama, Fantasy, Mystery, Romance | D118: Shin'ai naru Undead ni Sasageru, Toburai no Promesso 親愛なるアンデッドに捧げる、弔いの聖約 | E118: Light Novel, Action, Adventure, Drama, Fantasy, Mystery, Romance, Japanese, Nishijou Kanna, Ran, Ai Digital Publishing | F118: https://www.novelupdates.com/series/a-holy-covenant-of-mourning-dedicated-to-the-dear-undead/
A119: Goddess: “What Do You Want to Turn Into When You’re Reincarnated in Another World?” Me: “Into a Hero’s Rib” | B119: The reincarnation destination the protagonist chose is — the rib of a cheat-powered, harem-having, happy-ending Hero!? The setting: a world where you can keep reincarnating into any world you like until you’re satisfied enough to ascend peacefully. However, the ever-popular isekai option — the “cheat-skill harem Hero” — is so insanely in demand that the waiting list is fifty thousand years long… So instead, the protagonist settles on a loophole: “The rib of a cheat-powered, harem-having, happy-ending Hero”!? Together with a lazy Goddess-sama in charge of isekai reincarnations, the protagonist searches for backdoor routes into popular reincarnation destinations and keeps ending up in utterly ridiculous reincarnations. A wildly entertaining other-world reincarnation tale! Winner of the 8th Net Novel Grand Prize. Includes after-stories of popular episodes, plus a book-exclusive episode you can only read here: “The Old Soldier Who Took an Arrow to the Knee — and His Spear.” | C119: Adventure, Comedy, Fantasy, Shounen | D119: Megami "Isekai Tensei Nani ni Naritai Desu ka" Ore "Yūsha no Rokkotsu de 女神「異世界転生何になりたいですか」 俺「勇者の肋骨で」 | E119: Light Novel, Adventure, Comedy, Fantasy, Shounen, Adapted to Anime, Carefree Protagonist, Cunning Protagonist, Genius Protagonist, Goddesses, Honest Protagonist, Male Protagonist, Multiple Reincarnated Individuals, Pe*verted Protagonist, Playful Protagonist, Pragmatic Protagonist, Reincarnated as an Object, Reincarnated in Another World, Reincarnation, Shameless Protagonist, Japanese, Antai, 安泰, めばる, Takarajimasha, 宝島社 | F119: https://www.novelupdates.com/series/goddess-what-do-you-want-to-turn-into-when-youre-reincarnated-in-another-world-me-into-a-heros-rib/
A120: The Boy Unrivaled in a VR Game Synchronizes His Status with Reality and Reverses His Life | B120: The time and passion poured into a game—brilliantly reshape a boy’s life! Yuto Kanzaki is a high school student living a dull student life. His only enjoyment is VR games, where he can adventure in a world isolated from reality. When Yuto obtains the highly anticipated new RPG “Neunwelt Online,” he sees a mysterious message upon startup. 『Do you want to synchronize your Status with reality? Yes / No』 Thinking it referred to a backup of his play data, he selects “Yes” without hesitation. Then, changes occur in his daily life…! Just like inside the game, he becomes able to use magic and Skills in reality too!? Using that power, Yuto protects a girl from delinquents, shows remarkable performance in academics and sports, and begins to gather the attention and respect of those around him. It was the beginning of a brilliant life reversal! | C120: Action, Adventure, Fantasy, Harem, Romance | D120: Vr Game de Saikyou Musou no Shounen, Genjitsu ni Status ga Douki Shi Jinsei Gyakuten, VRゲーで最強無双の少年、現実にステータスが同期し人生逆転 | E120: Light Novel, Action, Adventure, Fantasy, Harem, Romance, Lucky Protagonist, Male Protagonist, Modern Day, Overpowered Protagonist, Virtual Reality, Japanese, 藤谷ある, キャロル, Kadokawa, I Got a Cheat Ability in a Different World, and Became Extraordinary Even in the Real World (LN), I Got a Cheat Ability in a Different World, and Became Extraordinary Even in the Real World (WN) | F120: https://www.novelupdates.com/series/the-boy-unrivaled-in-a-vr-game-synchronizes-his-status-with-reality-and-reverses-his-life/
A121: My Childhood Friend Is Always Down Whenever I Make a Move | B121: Bittersweet yet fresh—science, love, and mystery. When you think about it, “youth” is a lot like a well-crafted detective novel. “Should we continue what we started back then… at Arima’s house?” Watase Maria is a beautiful girl who is immensely popular with the boys, and Arima Shunta is a geeky high school freshman. The two are childhood friends who have played together every day for as long as they can remember. Though they had grown distant due to an “incident” back in their second year of middle school, they find themselves sitting next to each other after a seat reshuffle in high school. One day, Maria suddenly asks him, “If you want to see my breasts, should I show them to you?” After school, in Shunta’s room, Maria says, “I’ll only show my body to you, Shunta,” and begins to take off her uniform, revealing her developed chest right in front of him… A naughty youth rom-com featuring a childhood friend who has grown a seductive body. | C121: Adult, Comedy, Ecchi, Harem, Romance, School Life, Slice of Life, Smut | D121: 幼なじみは誘えばいつでもデキる関係 | E121: Light Novel, Adult, Comedy, Ecchi, Harem, Romance, School Life, Slice of Life, Smut, Beautiful Female Lead, Childhood Friends, First-time Interc**rse, Male Protagonist, Modern Day, Shameless Protagonist, Japanese, Kagami Yuu, 鏡遊, Unasaka, うなさか, Kadokawa, It Turns Out My Childhood Friend is Surprisingly Down if You Just Ask, My Childhood Friend Attacked Me When I Declared That Her Birthday Present Was ‘Me’ | F121: https://www.novelupdates.com/series/my-childhood-friend-is-always-down-whenever-i-make-a-move/
A122: Gimai Seikatsu | B122: From classmates to brother and sister, living under the same roof. Due to his father’s marriage, high schooler Yuuta Asamura ends up getting a new stepsister, living under the same roof with the girl who just so happens to be the most beautiful in his year. The both of them, having each witnessed their parents’ relationships fall apart, are cautious when it comes to man-woman relationships. They agree to keep an appropriate distance: neither getting too close nor being antagonistic. Saki, who has actually always longed for familial affection, stays resolute in doing everything by herself, not knowing how to depend on others. Yuuta, too, is unsure how to interact with her as a brother. The two, who resemble each other in certain aspects, gradually begin to learn how comforting it is to live together… This is a story that might blossom into a romance… A romance-life novel about a boy and girl who were once complete strangers, slowly drawing closer to one another as their relationship gradually begins to change. | C122: Comedy, Drama, Psychological, Romance, School Life, Shounen, Slice of Life | D122: Days with my Step Sister 義妹生活 | E122: Light Novel, Comedy, Drama, Psychological, Romance, School Life, Shounen, Slice of Life, Adapted to Anime, Adapted to Manga, Apartment Life, Average-looking Protagonist, Award-winning Work, Beautiful Female Lead, Books, Bookworm, Calm Protagonist, Caring Protagonist, Character Growth, Clever Protagonist, Cohabitation, Coming of Age, Complex Family Relationships, Cooking, Couple Growth, First-time Interc**rse, Hard-Working Protagonist, Heartwarming, Kind Love Interests, Love Interest Falls in Love First, Male Protagonist, Modern Day, Multiple POV, Multiple Protagonists, Part-Time Job, Past Trauma, Philosophical, Popular Love Interests, Possessive Characters, Pragmatic Protagonist, Secret Relationship, Siblings, Siblings Not Related by Blood, Slow Romance, Smart Couple, Strong Love Interests, Unconditional Love, Younger Sisters, Japanese, Mikawa Ghost, 三河ごーすと, Hiten, Kadokawa, MF Bunko J, Yen Press, My Stepsister is My Ex, We Should Have Slept While Only Holding Hands, And Yet?!, The Top Idol Next Door Can’t Help But Crave My Guilty Pleasure Meals, She Was Actually My Stepsister, The So-Called ‘Solitary Flower’ is a British Beauty Who’s Awkwardly Attached to Me Now That She’s My Stepsister, Tomodachi no Imouto ga Ore ni Dake Uzai, | F122: https://www.novelupdates.com/series/gimai-seikatsu/
A123: The Abandoned Elf Is The Strongest And Cutest In The World! | B123: Former voice actor, now high elf, I’m the strongest! “Dear top players, this game is a real parallel world. Reincarnate and save this world and any wish will be granted.” A message from the goddess arrived to the former popular voice actress, Iori Ayano. “If it means I can shine once more as a voice actress, I’ll save a world.” She chose to reincarnate as the strongest race, a high elf. What’s more, she was given the preferential treatment of being accompanied by her ideal beautiful fox heroine, Homura! In exchange, the events that befall Ayano are so difficult that it’s almost impossible?! But she conquers all the missions and enjoys her adventure in the parallel world with Homura. -Because Ayano is the strongest and cutest in the world! | C123: Adventure, Comedy, Fantasy | D123: Suterare Elf-san wa Sekai de Ichiban Tsuyokute Kawaii! 捨てられエルフさんは世界で一番強くて可愛い！ | E123: Light Novel, Adventure, Comedy, Fantasy, Adapted to Manga, Elves, Fantasy World, Female Protagonist, Reincarnated in Another World, Japanese, Tsukiyo Rui, 月夜 涙（るい）, Nijima Aruku, にじまあるく, Kadokawa | F123: https://www.novelupdates.com/series/the-abandoned-elf-is-the-strongest-and-cutest-in-the-world/
A124: Kämpfer | B124: The plot revolves around Natsuru Senou, a normal high school boy with blue hair. One day he wakes up to find himself turned into a girl. A stuffed tiger “Harakiri Tora” comes to life and tells him to fight as a female fighter “Kämpfer”. Having no idea about what’s going on, Natsuru is involved in many battles against other female Kämpfer. | C124: Action, Comedy, Ecchi, Gender Bender, Harem, Romance, School Life, Seinen, Shoujo Ai | D124: Kampfer Kenpufaa Kenpufer けんぷファー | E124: Light Novel, Action, Comedy, Ecchi, Gender Bender, Harem, Romance, School Life, Seinen, Shoujo Ai, Adapted to Anime, Adapted to Manga, Male Protagonist, Male to Female, Japanese, Tsukiji Toshihiko, Senmu, Media Factory, Boku no Bungeibu ni Bitch ga Irunante Arienai, Jaku-chara Tomozaki-kun, Ordinary I and Extraordinary Them | F124: https://www.novelupdates.com/series/kmpfer/
... A149: Hokuō Bishōjo no Kurasumeito ga, Fianse ni Nattara Deredere no Amaama ni Natte Shimatta Kudan ni Tsuite | B149: “Renjo-kun, I want you to become my fiancé.” Toru Renjo saves Aino Lyuti, the rumored most beautiful Nordic girl in school, at a bookstore and is asked to become her fiancé. Initially, it was a request to avoid an arranged marriage, but upon learning that Toru is her intended partner, Aino suddenly becomes enthusiastic about the engagement…!? This is the story of two people, originally bound by a sham engagement, who gradually come to understand each other and grow into true lovers. | C149: Comedy, Ecchi, Harem, Romance, School Life, Slice of Life | D149: My beautiful Nordic classmate became my fiance and became a Lovey-Dovey, sweet girl. 北欧美少女のクラスメイトが、婚約者になったらデレデレの甘々になってしまった件について | E149: Light Novel, Comedy, Ecchi, Harem, Romance, School Life, Slice of Life, Adapted to Manga, Arranged Marriage, Beautiful Female Lead, Broken Engagement, Childhood Friends, Cohabitation, Early Romance, F*llatio, Forced into a Relationship, Love Interest Falls in Love First, Male Protagonist, Modern Day, Past Plays a Big Role, Pe*verted Protagonist, R-15, Tsundere, Wealthy Characters, Japanese, Karui Hiroshi, 軽井広, Pon, Brave Bunko, Hifumi Shobo | F149: https://www.novelupdates.com/series/hokuo-bishojo-no-kurasumeito-ga-fianse-ni-nattara-deredere-no-amaama-ni-natte-shimatta-kudan-ni-tsuite/
A150: Date A Live Encore | B150: Date A Live Encore is a novel series of short stories within the Date A Live universe. | C150: Comedy, Ecchi, Fantasy, Harem, Mecha, Romance, School Life, Sci-fi, Shounen, Slice of Life | D150: デート・ア・ライブアンコール | E150: Light Novel, Comedy, Ecchi, Fantasy, Harem, Mecha, Romance, School Life, Sci-fi, Shounen, Slice of Life, Alternate World, Average-looking Protagonist, Beautiful Female Lead, Caring Protagonist, Loli, Male Protagonist, Siblings, Siblings Not Related by Blood, Spirits, Stoic Characters, Strong Love Interests, Tsundere, Younger Sisters, Japanese, Tachibana Koushi, 橘 公司, Tsunako, つなこ, Fujimi Shobo, Date A Live, Gyarugewe no Sekai yo, Youkoso!, Ore no Nounai Sentakushi ga, Gakuen Rabukome o Zenryoku de Jama Shite Iru, Unpopular As I Am, I Have To Meet a Heroine Within Five Days, | F150: https://www.novelupdates.com/series/date-a-live-encore/ | G150: 62
A151: Dual World Harem | B151: Touya Kougou quit his job at a shady retail company and became unemployed. When he rescued Kyui, a bird from another world that had collapsed by the roadside, he acquired Erot*c Skills that seduce women–!? Heading to another world with teleportation magic, he powers up and has a harem-filled life with noble ladies and beauties! Furthermore, he’s even popular in his world using his Erot*c Skills!? | C151: Action, Adult, Fantasy, Harem, Mature, Romance, Supernatural | D151: dwh I Will Rise From Unemployment! I, a NEET, Acquired a Special Skill and Formed a Harem in Both Japan and Another World!? 無職からの成り上がり！ ニートになった俺、特殊スキルを獲得して異世界と日本でハーレム完成!? | E151: Light Novel, Action, Adult, Fantasy, Harem, Mature, Romance, Supernatural, Adapted to Manga, Appearance Different from Actual Age, Arrogant Characters, Beautiful Female Lead, Caring Protagonist, C*nnilingus, Fantasy World, First-time Interc**rse, Harem-seeking Protagonist, Interdimensional Travel, Loli, Love Interest Falls in Love First, Magic, Male Protagonist, Modern Day, Overpowered Protagonist, Pe*verted Protagonist, Polygamy, Prostit**es, R-18, Returning from Another World, S*x Friends, Strong to Stronger, Transported to Another World, World Hopping, World Travel, Younger Love Interests, Japanese, Nekommi Zucchini, ネコミコズッキーニ, Metsubushi, メツブシ, Kadokawa, Inside the Cave of Obscenity, Bishoujo wo Jouzu ni Nikubenki ni Suru Houhou, Happy Peach | F151: https://www.novelupdates.com/series/dual-world-harem/
A152: The National Young Lady Bought Worthless Me for 300 Million (LN) | B152: Keiya, a young boy raised under the crushing oppression of toxic parents, is “purchased” for 300 million yen by a beautiful girl the moment he graduates from middle school. ​The girl’s name is Eina Ouhouin. She is a mysterious figure possessing overwhelming wealth and authority that surpasses even the power of the state. Due to the circumstances of a meeting during their childhood, Eina’s love for him is incredibly “heavy” and intense. ​”Because you look at me as a woman, I am always happy. I love you. I adore you, my Keiya.” ​Doted on by her in this way, Keiya begins a decadent yet blissful high school life. Meanwhile, disaster inevitably strikes those who would dare to mistreat his pure kindness… | C152: Drama, Ecchi, Psychological, Romance, School Life, Slice of Life | D152: 国家令嬢は価値なき俺を三億で | E152: Light Novel, Drama, Ecchi, Psychological, Romance, School Life, Slice of Life, Arrogant Characters, Beautiful Female Lead, Childhood Friends, Childhood Love, Cohabitation, Cruel Characters, Depictions of Cruelty, Devoted Love Interests, Different Social Status, Doting Love Interests, First Love, Maids, Male Protagonist, Manipulative Characters, Master-Servant Relationship, Modern Day, Mysterious Past, Obsessive Love, Past Plays a Big Role, Past Trauma, Psychopaths, R-15, Sudden Wealth, Twisted Personality, Wealthy Characters, Yandere, Japanese, 氷雨ユータ, 英エイスト, Hobby Japan | F152: https://www.novelupdates.com/series/the-national-young-lady-bought-worthless-me-for-300-million-ln/
A153: The Story of Me, Reincarnated as a TS, Setting Out to Seduce Every VTuber in My Agency | B153: Yumemi Renge, a current high school girl who’s a TS reincarnate obsessed with VTubers and also a hardcore yuri fan, has made a bold decision—“I will dominate the VTuber world with a mesugaki (bratty girl) persona!” After relentless effort, she successfully debuts as Hanayori Kohaku, and immediately sets out to seduce all her VTuber senpais and peers at her agency… but her bratty girl persona collapses almost immediately! Despite that, her viewers love it, commenting things like “Brat lol”, “She’s basically Mama Hanayori now lol”, and “Don’t push yourself, Hanayori”. Through collab streams and real-life interactions, she gradually charms her legendary senpais and quirky peers one by one—what will happen next!? | C153: Comedy, Gender Bender, Harem, Romance, Shounen, Slice of Life, Yuri | D153: TS tensei shita watashi ga shozoku suru Vtuber jimusho no liver wo zenin otoshiniku hanashi TS転生した私が所属するVTuber事務所のライバーを全員堕としにいく話 | E153: Light Novel, Comedy, Gender Bender, Harem, Romance, Shounen, Slice of Life, Yuri, Adapted to Manga, Beautiful Female Lead, Chat Rooms, Cute Story, Determined Protagonist, Famous Protagonist, Fast Learner, Female Protagonist, Livestreaming, Male to Female, Modern Day, Multiple POV, Popular Love Interests, Quirky Characters, Showbiz, Japanese, 恋狸, ほまでり, HJ Bunko, I Want To Become a Beautiful Girl, Be Spoiled, and Live Life on Easy Mode!, I’m a VTuber but I Forgot To Stop the Stream and Became a Legend | F153: https://www.novelupdates.com/series/the-story-of-me-reincarnated-as-a-ts-setting-out-to-seduce-every-vtuber-in-my-agency/
A154: After the Drop off, My Reemployment Office is The Strongest Order of Knights in Another World | B154: Believing her life had already failed beyond repair, Masumi Toudou thought she had died—only to be flung into another world and promptly accused of being a spy. Despite her desperate attempts to explain that she was nothing more than an ordinary person, not a suspicious intruder, no one believed her in the slightest. Pressed to prove her innocence, she is forced into work without even understanding where she is or what is happening. The labor environment of this other world turns out to be unimaginably brutal: a truly merciless black workplace where one trouble after another rains down without pause. This is the story of an unlikely duo striving for better working conditions: a woefully understaffed and somewhat pathetic knight, and a former violinist who once gave up on her own path. An offbeat partnership, determined to survive—and reform—the harshest workplace imaginable. | C154: Fantasy, Romance, Shoujo | D154: ドロップアウトからの再就職先は、異世界の最強騎士団でした～訳ありヴァイオリニスト、魔力回復役になる～ | E154: Light Novel, Fantasy, Romance, Shoujo, Adapted to Manga, Aristocracy, Fantasy World, Female Protagonist, Knights, Magic, Nobles, Transmigration, Japanese, 東 吉乃, Overlap | F154: https://www.novelupdates.com/series/after-the-drop-off-my-reemployment-office-is-the-strongest-order-of-knights-in-another-world/
A155: Villager A Wants to Save the Villainess no Matter What! (LN) | B155: Allen, an eight-year-old boy from a poor family in the royal capital, is living a poor but happy life together with his mother. One day, however, memories of his previous life suddenly come back to him and he remembers that he is in an dating sim game and that the capital will be destroyed by war if he doesn’t do something about it. If this continues, both he and his mother will be killed! With a sense of urgency, he decides to rise to the occasion in order to save his precious mother’s life and save his favorite character, the villainous young lady Anastasia, the only girl he liked in the game, from her all too tragic and ruinous end. | C155: Action, Adventure, Drama, Fantasy, Romance, School Life, Shounen | D155: Chounin A wa Akuyaku Reijou o Doushitemo Sukuitai: Dobu to Sora to Koori no Himegimi 町人Ａは悪役令嬢をどうしても救いたい～どぶと空と氷の姫君～ | E155: Light Novel, Action, Adventure, Drama, Fantasy, Romance, School Life, Shounen, Academy, Accelerated Growth, Adapted to Manga, Adventurers, Age Progression, Alchemy, Beautiful Female Lead, Betrayal, Devoted Love Interests, Different Social Status, Dungeons, Elves, Engagement, Fantasy World, Firearms, First-time Interc**rse, Game Elements, Guilds, Gunfighters, Hard-Working Protagonist, Hiding True Abilities, Kidnappings, Kind Love Interests, Kingdoms, Knights, Level System, Love Interest Falls in Love First, Male Protagonist, Manipulative Characters, Marriage, Mind Break, Mob Protagonist, Money Grubber, Multiple POV, Multiple Reincarnated Individuals, Naive Protagonist, Nobles, Otome Game, Politics, Previous Life Talent, R-15, Reincarnated in a Game World, Reverse Harem, Royalty, Schemes And Conspiracies, Strong Love Interests, Sword And Magic, Wars, Japanese, Isshiki Koutarou, 一色孝太郎, Parum, アース・スター エンターテイメント | F155: https://www.novelupdates.com/series/villager-a-wants-to-save-the-villainess-no-matter-what-ln/
A156: The Secret Life Of An Honor Student | B156: “If you keep my secret account hidden, I’ll do something good for you, okay?” “Ninety percent impure, ten percent pure love” — that was the beginning of a secret relationship just between the two of us. “If you promise not to tell, I’ll make sure you have a good time.” Aisaka Akito happened to discover that Mamiya Yuu, the model honor student who sat next to him, was actually a “secret account girl.” To keep his mouth shut, she made him tag along as her photographer for those hidden account photos. “Hey… let’s do something even crazier.” Their shoots started pushing into things they could never tell anyone about. Confused yet unable to resist, Akito found himself spending more and more time alone with her—meeting in secret, taking pictures, walking home together after detours. Each moment stacked upon the next, slowly revealing glimpses of her real self. A relationship that began as an impure secret soon started to shift into a soft, sweet love— The front and the back. The two faces she carried. A thrilling, secret romantic comedy with the girl who lived in both worlds. | C156: Comedy, Ecchi, Romance, School Life, Slice of Life | D156: Yūtōsei no Ura no Kao ~ jitsuwa ura aka joshidatta tonari no seki no bishōjo to hōkago futarikiri ~ 優等生のウラのカオ ～実は裏アカ女子だった隣の席の美少女と放課後二人きり～ | E156: Light Novel, Comedy, Ecchi, Romance, School Life, Slice of Life, Beautiful Female Lead, Blackmail, Male Protagonist, Modern Day, Japanese, Kurage, 海月くらげ, KR ki, ｋｒ木, GA Bunko, One Day, I Started to See Other People’s Secret, Gogaku Ryuugaku ni Kita Hazu no Kizoku Reijou, Naze ka Hanayome Shugyou Bakari Shite iru (LN), The Cool Beautiful Girl Sitting Next to Me That Everyone Envies Is Actually Way Too Le*d in Her Head, Tsun’na Megami-sama to Darenimoienai Himitsu no Kankei | F156: https://www.novelupdates.com/series/the-secret-life-of-an-honor-student/
A157: The Happy Contract Re-Marriage with the Ice Duke | B157: Leonie, who was forced into a political marriage at the age of 10, loved her husband Cassius, who was two years her elder. However, seven years after their marriage, one day, Cassius brought home a young lady of noble birth claiming to be pregnant with his child. This shattered her love and romantic feelings for him completely. Ironically, it happened the day before their wedding night, as was decided at the time of their marriage. Leonie immediately decided to divorce and returned to her family home to seek her father’s approval. However, her father opposed the divorce and refused to sign the necessary documents. As days passed, even her mother and brother, who had initially been supportive, turned against her. Desperate and cornered, Leonie finds herself in a dire situation. At that moment, she receives a letter. The sender of that letter is none other than Charlotte Claudia, the fiancé of Cassius’s mistress. He is known as the “Ice Duke.” What is his true purpose in reaching out to Leonie… ? | C157: Drama, Fantasy, Mature, Romance, Shoujo | D157: Koori no Koushaku-sama to Watashi no Shiawase na Keiyaku Saikon THCRMWTID We Will Be Happy Together, So Please Don't Worry and Stay Happy 改題前：私たち2人で幸せになりますので、どうかお気になさらずお幸せに。 氷の公爵様と私の幸せな契約再婚 | E157: Light Novel, Drama, Fantasy, Mature, Romance, Shoujo, Adapted to Manga, Arranged Marriage, Arrogant Characters, Beautiful Female Lead, Divorce, Early Romance, European Ambience, Female Protagonist, Handsome Male Lead, Marriage, Marriage of Convenience, Nobles, R-15, Japanese, Ayasaki Isagi, 綺咲 潔, Ahiru Morishita, アヒル森下, Futabasha, M Novels f, Mノベルスｆ, Syosetu, 双葉社 | F157: https://www.novelupdates.com/series/the-happy-contract-re-marriage-with-the-ice-duke/
A158: Kano Mama wa Hatsukoinohito. Hahatoko no Toripurupurei | B158: N/A | C158: Adult, Harem, Mature, Romance, Smut | D158: Kano Mama wa Hatsukoinohito. Hahatoko no Toripurupurei My girlfriend's Mother is my first love. Mother and daughter triple play カノママは初恋のひと。 母と娘のトリプルプレイ | E158: Light Novel, Adult, Harem, Mature, Romance, Smut, An*l, Adultery, Beautiful Female Lead, Breast Fetish, C*nnilingus, Early Romance, First Love, First-time Interc**rse, Flashbacks, F*llatio, H*ndjob, Male Protagonist, M*sturbation, Multiple POV, Nudity, Older Love Interests, Past Plays a Big Role, Past Trauma, Polygamy, Pregnancy, R-18, Reverse R*pe, Threesome, Japanese, サエキヨウスケオルタ, Minamoto, France Shoin, | F158: https://www.novelupdates.com/series/kano-mama-wa-hatsukoinohito-hahatoko-no-toripurupurei/
A159: Nameless Hero | B159: This is a story of heroes who will never make it into the history books. Winner of the 19th Shogakukan Light Novel Award Excellence Award! This is a “prequel” fantasy about those who risked their lives before the Hero saved the world. It is a chaotic era where humanity continues to fight against the savage monsters known as the ‘Jazoku’. Deep in the remote mountains, a boy lives alone with his sister, who suffers from an incurable disease. Amidst their grinding poverty, the boy volunteers to act as a guide for a group searching for the Hero’s Sword. His reward is medical treatment for his sister. However— “I can see the shadow of death on you. If you join this mission, you will lose your life.” One of the members of the special task force searching for the Hero’s Sword, a girl with the Evil Eye, prophesies his death. Even so, the boy decides to join them. All for the sake of his sister. The task force’s mission is to locate the missing Hero’s Sword and deliver it to the Hero on the front lines. Time remaining: only a few days. Even now, the Hero is facing down the ‘Jazoku’, shattering the swords in his hand one after another. What was supposed to be a simple guiding job turns into assisting the search, and finally transforms into a desperate escape drama while clutching the targeted Hero’s Sword— And the boy, who was supposed to be just a villager, becomes a “Nameless Hero.” Risk your life to deliver “hope.” Even if you aren’t a Hero, to save the world. This is a story of heroes who will never make it into the history books. | C159: Action, Adventure, Fantasy, Supernatural | D159: A Hero Known by None Namae no Nai Eiyuu 名前のない英雄 | E159: Light Novel, Action, Adventure, Fantasy, Supernatural, Award-winning Work, Demons, Determined Protagonist, Dungeons, Hunters, Magic, Male Protagonist, Siblings, Survival, Tsundere, Wars, Weak Protagonist, Japanese, Gutei Miyashita, 宮下 愚弟, Karasuro, カラスロ, Gagaga Bunko, Shogakukan | F159: https://www.novelupdates.com/series/nameless-hero/
A160: The Strongest and Laziest Mage of the Royal Academy ~The T*ash Noble Who Became a Teacher Was Actually the ‘Hero’ of the Strongest Magic Order~ | B160: Crow Breizel is the eldest son of a Duke who wants nothing more than to enjoy a life of total self-indulgence. Due to his degenerate lifestyle, he has earned quite a notorious reputation in high society as a “tr*sh Noble.” In reality, however, he is a member of the Kingdom’s strongest magic order—a group of elites where every individual possesses enough power to shift the tides of a battlefield single-handedly. One day, his secret identity as the “Hero” of the magic order is discovered by his younger adoptive sister, Iris, who harbors a serious brother complex. She begs him to take a teaching position at the Magic Academy. Although Crow refuses in hopes of maintaining his lazy lifestyle, Iris resort to threats, forcing him to reluctantly accept the job. The curtain rises on a fantasy saga of an unrivaled teacher taking the Academy by storm! | C160: Action, Adventure, Comedy, Fantasy, Harem, Romance, School Life, Shounen, Supernatural | D160: 王立アカデミーの最強で怠惰な魔法士 ～教師をすることになったクズ貴族、実は最強魔法士団の「英雄」でした～ | E160: Light Novel, Action, Adventure, Comedy, Fantasy, Harem, Romance, School Life, Shounen, Supernatural, Academy, Adopted Children, Beautiful Female Lead, Brother Complex, Dense Protagonist, Genius Protagonist, Handsome Male Lead, Hiding True Abilities, Hiding True Identity, Kidnappings, Lazy Protagonist, Magic, Male Protagonist, Misunderstandings, Nobles, Overpowered Protagonist, Priestesses, Protagonist Strong from the Start, Secret Identity, Siblings Not Related by Blood, Strong Love Interests, Student-Teacher Relationship, Teachers, Tsundere, Underestimated Protagonist, Yandere, Japanese, Kadehara Kōta, 楓原こうた, Karimarika, カリマリカ, 双葉社 | F160: https://www.novelupdates.com/series/the-strongest-and-laziest-mage-of-the-royal-academy-the-trash-noble-who-became-a-teacher-was-actually-the-hero-of-the-strongest-magic-order/
A161: The Girl I Met on the Matchmaking App Turned Out to Be My Student | B161: Shugo Kizaki, a high school teacher, starts using a dating app after the wedding of a friend. Through a chance encounter, he meets the highly popular (with over 1000 “likes”) beautiful girl “Sakuran” on the app. However, Sakuran turns out to be—his student (a high schooler)!? “You’re underestimating the app, Sensei! I’ll teach you how to become popular on the app!” After saving Sakuran from a crisis, Shugo is taught the secrets to gaining attention on the app as a reward. He begins his search for the ideal partner, charging ahead into the battlefield of dating apps! From Jun Minosaki, the author of Hundred series, comes a love hunting guide and romantic comedy!! | C161: Drama, Ecchi, Harem, Romance, School Life, Slice of Life | D161: Matching Appli de Deatta Kanojo wa Ore no Oshiego datta Ken The Girl I Met on a Matching App Was My Student The Girl I Met on the Dating App Turned Out to Be My Student マッチングアプリで出会った彼女は俺の教え子だった件 | E161: Light Novel, Drama, Ecchi, Harem, Romance, School Life, Slice of Life, Beautiful Female Lead, Emotionally Weak Protagonist, Male Protagonist, Student-Teacher Relationship, Teachers, Japanese, Jun Minosaki, Shio Koji, Softbank Creative | F161: https://www.novelupdates.com/series/the-girl-i-met-on-the-matchmaking-app-turned-out-to-be-my-student/
A162: The New Gate (LN) | B162: “THE NEW GATE”, an online game that trapped its players and turned into a death game, was now releasing the thousands of players that had been dragged into it, thanks to the efforts of Shin, one of the most powerful players. But after having defeated the last boss and freed everyone, he was swallowed up by a strange light and found himself inside the game world 500 years in the future and unable to leave. | C162: Action, Adventure, Fantasy, Harem, Shounen, Supernatural | D162: TNG ザ・ニュー・ゲート | E162: Light Novel, Action, Adventure, Fantasy, Harem, Shounen, Supernatural, Adapted to Anime, Adapted to Manga, Adventurers, Artifacts, Beast Companions, Beastkin, Beautiful Female Lead, Blacksmith, Boss-Subordinate Relationship, Calm Protagonist, Curses, Death of Loved Ones, Demi-Humans, Demons, Dense Protagonist, Dragons, Dungeons, Elves, Fantasy World, First-time Interc**rse, Game Elements, Guilds, Hiding True Abilities, Hiding True Identity, Indecisive Protagonist, Kingdoms, Late Romance, Level System, Love Interest Falls in Love First, Loyal Subordinates, Magic, Male Protagonist, Monsters, Multiple Transported Individuals, Overpowered Protagonist, Past Plays a Big Role, Pets, Protagonist Strong from the Start, Reincarnation, Romantic Subplot, Royalty, Secret Identity, Sentient Objects, Seven Deadly Sins, Strong Love Interests, Sword And Magic, Sword Wielder, Transformation Ability, Transmigration, Transported into a Game World, Unique Weapons, Japanese, Kazanami Shinogi, 風波 しのぎ, Hell's Resident, Makai no Juumin, 魔界の住民, AlphaPolis, Hanashi Media, My Death Flags Show No Sign of Ending, Dragon Maken War, Death March kara Hajimaru Isekai Kyusoukyoku (WN), The Amber Sword, A Wild Last Boss Appeared, Sevens, | F162: https://www.novelupdates.com/series/the-new-gate/
... A179: I Got a Cheat Ability in a Different World, and Became Extraordinary Even in the Real World (LN) | B179: Tenjou Yuuya has been a bullied boy since the past. He lives in the home of his beloved grandfather while he goes to school. As usual, he receives a harsh bullying, and he takes an extended absence from school to have some time to heal his wounds. While on this long time of absence, he takes the opportunity to clean his grandfather’s house and goes to a room he never went before, where his grandfather keep many different objects that he gathered from his travels around the world. While he was arranging the objects, he found a door not on a wall among the objects. Out of curiosity he opens this door, what he found on the other side was… | C179: Action, Adventure, Fantasy, Harem, Romance, School Life, Sci-fi, Slice of Life | D179: Cheat Skill I Got a Cheat Skill in Another World and Became Unrivaled in the Real World, Too Isekai de Cheat Skill wo Te ni Shita Ore wa, Genjitsu Sekai wo mo Musou Suru ~Level Up wa Jinsei wo Kaeta~ IseLeve 在異世界獲得超強能力的我，在現實世界照樣無敵 異世界でチート能力(スキル)を手にした俺は、現実世界をも無双する～レベルアップは人生を変えた～ 異世界でチート能力を手にした俺は、現実世界をも無双する | E179: Light Novel, Action, Adventure, Fantasy, Harem, Romance, School Life, Sci-fi, Slice of Life, Abandoned Children, Ability Steal, Academy, Accelerated Growth, Adapted to Anime, Adapted to Game, Adapted to Manga, Adventurers, Aliens, Angels, Appearance Changes, Assassins, Beast Companions, Beastkin, Beautiful Female Lead, Bullying, Caring Protagonist, Charming Protagonist, Cheats, Cohabitation, Cooking, Demi-Humans, Demon Lord, Demons, Dense Protagonist, Depictions of Cruelty, Devoted Love Interests, Discrimination, Dragon Slayers, Dragons, Evil Gods, Evolution, Family Conflict, Famous Protagonist, Fantasy Creatures, Fantasy World, Fat to Fit, Game Elements, Gate to Another World, Goddesses, Godly Powers, Gods, Handsome Male Lead, Hard-Working Protagonist, Harsh Training, Human-Nonhuman Relationship, Human Weapon, Inferiority Complex, Inheritance, Interdimensional Travel, Jack of All Trades, Kind Love Interests, Level System, Love Interest Falls in Love First, Male Protagonist, Master-Disciple Relationship, Monster Tamer, Multiple POV, Multiple Realms, Nobles, Obsessive Love, Older Love Interests, Overpowered Protagonist, Polygamy, Poor to Rich, Popular Love Interests, Priestesses, Race Change, Returning from Another World, Royalty, Saints, Saving the World, Sentient Objects, Sibling Rivalry, Skill Assimilation, Skill Creation, Special Abilities, Spirit Advisor, Strong Love Interests, Strong to Stronger, Sudden Strength Gain, Sudden Wealth, Summoning Magic, Sword And Magic, Time Paradox, Time Skip, Time Travel, Transported to Another World, Ugly to Beautiful, Unique Weapon User, Unique Weapons, Weak to Strong, Wealthy Characters, Younger Love Interests, Japanese, Miku, 美紅, Kuwashima Rein, 桑島 黎音, Kadokawa, Yen Press, What, Failure to Transition!?……Success!? (LN), Going Back and Forth Between Earth and The Other World with Space Time Magic, Arifureta Shokugyou de Sekai Saikyou (WN), Shinka no Mi (WN), That Time I Got Reincarnated as a Disappointing Prince, Instead of Being Transported to Another World Directly, I Was Given the Abilities of the Strongest Character in the Anime World | F179: https://www.novelupdates.com/series/i-got-a-cheat-ability-in-a-different-world-and-became-extraordinary-even-in-the-real-world-ln/
A180: Chitose-kun wa Ramune Bin no Naka | B180: Japanese most important Light Novel Award “KONORANO” winner of 2021 and 2022, second in 2023 As far as normies go, it’s hard to beat Saku Chitose. The most popular guy in his high school? Check. An ironclad reputation that can repel even vicious online attacks? Check. A group of friends as attractive on the outside as they are on the inside? Check. But when a teacher asks Saku to help rehabilitate a student who been shut away in their room for months to school life, his perfect world will never be the same. What is this, some kinda normie harem story? | C180: Comedy, Drama, Harem, Romance, School Life | D180: Chiramune Chitose-kun ha Ramune Bin no Naka Chitose Is In The Ramune Bottle Chitose trong chai Ramune チラムネ 千歳くんはラムネ瓶のなか 彈珠汽水瓶裡的千歲同學 | E180: Light Novel, Comedy, Drama, Harem, Romance, School Life, Adapted to Anime, Adapted to Manga, Award-winning Work, Beautiful Female Lead, Calm Protagonist, Carefree Protagonist, Character Growth, Confident Protagonist, Cunning Protagonist, Different Social Status, Handsome Male Lead, Male Protagonist, Mature Protagonist, Misunderstandings, Modern Day, Playful Protagonist, Popular Love Interests, Proactive Protagonist, Japanese, hiromu, 裕夢, Raemz, Gagaga Bunko, Shogakukan, Yen Press, Jaku-chara Tomozaki-kun, I Won’t Allow You to Have a Romantic Comedy With Someone Else | F180: https://www.novelupdates.com/series/chitose-kun-wa-ramune-bin-no-naka/ | G180: 31
A181: Wai no Hontō no Shokugyō ga [-sei kishi] Toka Ienai | B181: If it’s discovered that he’s not the strongest [Holy Knight] , he’ll be executed immediately!? —His weapon is none other than his own libido. It is a special profession bestowed by the gods upon those who turn 15, standing at the very pinnacle of all vocations. A certain boy named Ars also received his calling— “What the hell is a [s*xual Knight] !?!” What he was granted was the [s*xual Knight] , a class that consumes s*xual desire to activate its skills!? Yet, upon hearing Ars’s heartfelt scream, everyone around him mistook it for [Holy Knight] and went into a frenzy celebrating the birth of a new Holy Knight. Before he knew it, Ars was swept away to the royal capital and even granted an audience with the king as the [Holy Knight] … Falsifying one’s divinely granted profession is treason against the gods—an instant death sentence. However, in front of the king, his skill —powered by the sheer quantity of his libido—demonstrated absurd, overwhelming strength…!? Officially recognized as a [Holy Knight] , Ars is then assigned to protect the Saintess— but… ? | C181: Action, Adventure, Comedy, Ecchi, Fantasy, Harem, Romance, Supernatural | D181: ワイの本当の職業が【性騎士】とか言えない | E181: Light Novel, Action, Adventure, Comedy, Ecchi, Fantasy, Harem, Romance, Supernatural, Assassins, Beautiful Female Lead, Dense Protagonist, Fantasy World, Game Elements, Hard-Working Protagonist, Helpful Protagonist, Knights, Level System, Lucky Protagonist, Magic, Male Protagonist, Misunderstandings, Pe*verted Protagonist, Protagonist Strong from the Start, Saints, Secret Identity, Secrets, Strong Love Interests, Strong to Stronger, Sword And Magic, Japanese, Koitanuki, 恋狸, むつみまさと, Overlap | F181: https://www.novelupdates.com/series/wai-no-honto-no-shokugyo-ga-sei-kishi-toka-ienai/
A182: The Demon King’s Former Aides Pledge Loyalty Even After Reincarnating as Heroes | B182: Even in the world where they reincarnated as female heroes, the former aides want to serve the Demon King! Bard Barbatos—the strongest Demon King in history who brought an end and victory to the long war between the Human Race and the Demon Race, completely destroying the world. Grieving for the Six Demon Ministers—Silver Wolf, Black Dragon, True Ancestor, Violent Ogre, Evil Spirit, and Dream Demon—who swore loyalty to him and died in battle, Bard reincarnates his close aides into a new world… only to find they have become ‘Heroes’ in the form of beautiful girls!? “Lord Bard—the time has finally come, hasn’t it!” “Time, you say?” While Bard wished for them to have peaceful daily lives this time around, his former aides swear loyalty to exert their power for world conquest just like in their past lives, and on top of that, they are spoiling him!? A misunderstanding harem fantasy featuring a Demon King turned Academy City Headmaster and his former aides! | C182: Ecchi, Fantasy, Harem, Shounen | D182: Maou no Moto Sokkin wa Yuusha ni Tensei Shite mo Chuusei o Sasagu 魔王の元側近は勇者に転生しても忠誠を捧ぐ | E182: Light Novel, Ecchi, Fantasy, Harem, Shounen, Antihero Protagonist, Demon Lord, Fantasy World, Goddesses, Gods, Heroes, Loyal Subordinates, Male Protagonist, Masochistic Characters, Overpowered Protagonist, Protagonist Strong from the Start, Japanese, Tsukasa, ツカサ, Youta, Kadokawa | F182: https://www.novelupdates.com/series/the-demon-kings-former-aides-pledge-loyalty-even-after-reincarnating-as-heroes/
A183: I Reincarnated as a Villain, Saved the World, and Then Was Betrayed and Exiled, But for Some Reason, My Former Comrades Are Chasing After Me With Sick Eyes… | B183: I thought I’d live a slow life since I got exiled, but— For some reason, the heroines have gone crazy and came chasing after me!? “You are not fit to be a hero!” Phantom, who reincarnated as a villainous noble in a game world, supported the Hero’s party to avoid his own destruction and defeated the Demon King. However, because of his power known as the “Evil Eye,” which is abhorred by others, his achievements were stolen, and he was sentenced to exile from the country. On top of that, he was thrust with evidence that the comrades he thought he was close with had agreed to his exile, and he left the country in despair over being betrayed… Then, one year later. Phantom, who was living a slow life as an ordinary mid-ranking adventurer, encountered a scene where a certain girl was being exiled. Phantom saves the girl, Tia, and a new adventure begins… Or so he thought, but for some reason, his former party members are coming to look for the protagonist with desperate looks on their faces. | C183: Action, Adventure, Comedy, Ecchi, Fantasy, Harem, Romance, Shounen | D183: Akuyaku Tensei Shite Sekai o Sukutta Ato ni Uragirarete Tsuihou Sareta Ore, Nazeka Katsute no Nakama ga Yanda Me o Shite Oikakete Kichatta...... (LN) I Got Reincarnated as the Villain and Saved the World, but After the Ending I Was Betrayed and Exiled. I Just Wanted a Peaceful Life in the Frontier, but for Some Reason My Former Companions Started Chasing Me with Yandere Eyes… (LN) 悪役転生して世界を救った後に裏切られて追放された俺、なぜかかつての仲間が病んだ目をして追いかけてきちゃった…… (LN) | E183: Light Novel, Action, Adventure, Comedy, Ecchi, Fantasy, Harem, Romance, Shounen, Adventurers, Beautiful Female Lead, Fantasy World, Former Hero, Male Protagonist, Misunderstandings, Multiple POV, Multiple Reincarnated Individuals, Reincarnated in a Game World, Reincarnation, Secret Identity, Sword And Magic, Japanese, Takano Kei, 高野 ケイ, Genyaky, Softbank Creative | F183: https://www.novelupdates.com/series/i-reincarnated-as-a-villain-saved-the-world-and-then-was-betrayed-and-exiled-but-for-some-reason-my-former-comrades-are-chasing-after-me-with-sick-eyes/
A184: Our Secret Youth in the Night School (LN) | B184: “Listen here. I want to turn these nights after club activities into our very own springtime of youth.” The one who called out to Minase Shuuto—a loner in his first year of high school—was Tsukimi Kaede. A second-year student, she was the definition of perfection: top grades, incredible athleticism, and stunning looks. A total triple threat. Kaede led Shuuto to a place no one dared approach: the old gymnasium storage shed. Or, as they called it, the “Secret Base.” Inside, three other students were already kicking back. Kazemiya Kanon, the school idol every guy obsessed over. Ogino Misato, a music-loving gyaru who kept to herself. And Akazawa You, the happy-go-lucky class clown. To Shuuto, they were the social elite, people from a world he had no part in. But for some reason… they were acting completely different from their usual selves!? “Greetings, my fellow comrades! ‘Tis another fine evening, is it not?!” Hold on a second… isn’t Tsukimi-senpai the one whose personality flipped the hardest?! As Shuuto stood there dumbfounded, Kaede dubbed their little gathering the 『Don’t Want to Go Home Alliance.』 She extended a hand toward him. “Why don’t you join us?” Set against the backdrop of the school at night, this is a coming-of-age romantic comedy featuring boys and girls hiding secrets of their own! | C184: Drama, Romance, School Life, Slice of Life | D184: 秘密の青春は夜の学校で | E184: Light Novel, Drama, Romance, School Life, Slice of Life, Beautiful Female Lead, Loner Protagonist, Male Protagonist, Past Trauma, Personality Changes, Secrets, Senpai-Kouhai Relationship, Japanese, 雨宮和希, 椎名 くろ, Gagaga Bunko, Shogakukan | F184: https://www.novelupdates.com/series/our-secret-youth-in-the-night-school-ln/
A185: The Godspeed Dungeon Explorer ~The Speed-Min-Maxed Streamer Breaks Through Everything~ | B185: “We’re going to become famous together—fast enough that no one can catch up!” Following a meteorite impact, Japan has become a world overflowing with dungeons. Nonomura Nodoka, a 17-year-old amateur explorer, was worrying about her dungeon stream going poorly yet again today. It was then that she saved Hachisuka Subaru, a streamer whose popularity was on the rise, from being attacked by a large monster. Through this incident, a certain fact came to light: “Her movements are too fast to be captured on the stream camera.” Believing that streaming together would allow them to increase each other’s viewer counts, Subaru makes a proposal to Nodoka. “Hey, why don’t you become my buddy?” Thus begins the streaming life of a socially awkward godspeed girl and a calculating, yet hapless, magical girl. | C185: Action, Adventure, Comedy, Fantasy | D185: Shinsoku no Dungeon Seeker ~Speed Kyokufuri Haishinsha wa Subete o Buchinuku~ 神速のダンジョン探索者 〜スピード極振り配信者はすべてをブチ抜く〜 | E185: Light Novel, Action, Adventure, Comedy, Fantasy, Female Protagonist, Japanese, Kaeruda Ameko, U35, Drecom | F185: https://www.novelupdates.com/series/the-godspeed-dungeon-explorer-the-speed-min-maxed-streamer-breaks-through-everything/
A186: I Risked My Life to Save a Pair of Beautiful Twin Sisters, and Now These Secret Yanderes Are Totally Obsessed With Me (LN) | B186: “Let’s make it ours—just between us. We won’t let anyone else have you.” Reona and Riona Tsurugi—the most beautiful twin sisters at school—are suddenly rescued from a violent attacker by an unlikely savior: Ryoya Yagami, an ordinary, lonely high school boy with no special traits. From that moment, Ryoya’s quiet life is turned upside down. As thanks for saving their lives, the twins start showering him with affection, pulling him into a whirlwind of sweet, love-filled days. Unable to keep up with the twins’ relentless pace, Ryoya finds himself constantly flustered. But as the distance between them closes, he remains unaware that something about the situation just doesn’t feel quite right… A love-comedy packed with affection and chaos—welcome to the birth of a wild and unpredictable romantic rollercoaster! | C186: Comedy, Ecchi, Harem, Romance | D186: 何の取り柄もない平凡な俺が美人双子姉妹を命懸けで助けた結果、実はヤンデレだった二人をガチ惚れさせてしまった件 | E186: Light Novel, Comedy, Ecchi, Harem, Romance, Abusive Characters, Average-looking Protagonist, Beautiful Female Lead, Emotionally Weak Protagonist, Loner Protagonist, Male Protagonist, Manipulative Characters, Mob Protagonist, Multiple POV, Polygamy, Popular Love Interests, Possessive Characters, Twins, Yandere, Japanese, Mizushima Satori, 水島紗鳥, にわ田, Brave Bunko, Hifumi Shobo, | F186: https://www.novelupdates.com/series/i-risked-my-life-to-save-a-pair-of-beautiful-twin-sisters-and-now-these-secret-yanderes-are-totally-obsessed-with-me-ln/
A187: I, Who Longs To Be A Dependent, Have Decided To Be Owned By A Yandere (LN) | B187: If you don’t want to work a day in your future, isn’t getting kept by a yandere the answer? Akira Kiritani, a devoutly slothful high school student, is a male with a peculiar constitution: he has been a magnet for yanderes since early childhood. One day after school, he discovered Yui Minazuki—a classmate possessing both beauty and brains—in the act of obsessively sniffing his school bag. Realizing she harbored a pathological affection for him, he petitioned to be “kept” by Yui, deciding to let her take care of him well into his old age. “The collar is custom-made, so you’ll have to wait until it’s finished, okay?” Yui informed Akira with an angelic smile. However, the very moment his life of captivity in Yui’s home was set to begin, the doorbell rang…!? Will Akira truly be able to safely become a yandere’s himo? This is the story of Akira (scum) aiming to become a magnificent leech while navigating a turbulent school life—! | C187: Drama, Ecchi, Harem, Romance, School Life | D187: ヒモになりたい俺は、ヤンデレに飼われることにした | E187: Light Novel, Drama, Ecchi, Harem, Romance, School Life, Beautiful Female Lead, Brother Complex, Chuunibyou, Cohabitation, Confinement, Drugs, Handsome Male Lead, Kidnappings, Lazy Protagonist, Male Protagonist, Manipulative Characters, Misunderstandings, Modern Day, Multiple Personalities, Obsessive Love, Schemes And Conspiracies, Shameless Protagonist, Siblings Not Related by Blood, Stalkers, Student Council, Student-Teacher Relationship, Survival, Wealthy Characters, Yandere, Japanese, Ryo Hazakura, 端桜 了, 吉田ばな, Dash X Bunko | F187: https://www.novelupdates.com/series/i-who-longs-to-be-a-dependent-have-decided-to-be-owned-by-a-yandere-ln/
A188: E*oge no Hakushaku Reijou wo Hoshi Meido Ochisaseru Akuyaku Onzoushi ni Tensei shita Ore wa Zama wo Kaihi suru. Sono Kekka, Mein Heroin ga Yuusha Gakuin de Mainichi Gyaku Yobai ni Kuru no daga | B188: “Lord Nord… would you like some milk this morning?” I was reincarnated into the erot*c world I had just played, “The Resurrected Hero’s Harem Academy”. However, instead of being the hero protagonist, I became Nord, the son of the evil noble family who seized Elise, the heroine, and was eventually killed by the hero. This was no time to relax and enjoy milk from the maid! In order to avoid the flag of death and live a relaxed peaceful life, I tried my best to stay away from Elise… However, all my actions were misinterpreted by her, making her level of attraction to me increase even more “Please look at my innocent body that no one has ever seen before…” She fell in love with me seriously, voluntarily signed up as my personal maid, and even started coming to my room at night!?? Winner of the Special Award in the Rom-Com Category of the 9th Kakuyomu Web Novel Contest! | C188: Action, Adventure, Comedy, Ecchi, Fantasy, Harem, Romance | D188: Villainous Heir エロゲの伯爵令嬢を奉仕メイド墜ちさせる悪役御曹司に転生した俺はざまぁを回避する その結果、メインヒロインが勇者学院で毎日逆夜這いに来るのだが…… | E188: Light Novel, Action, Adventure, Comedy, Ecchi, Fantasy, Harem, Romance, Academy, Beast Companions, Blackmail, Breast Fetish, Brother Complex, Clingy Lover, Dark, Demon Lord, Determined Protagonist, First-time Interc**rse, Magic, Maids, Male Protagonist, Misunderstandings, Nobles, Obsessive Love, Overpowered Protagonist, Overprotective Siblings, Polygamy, Possession, Reincarnated in a Game World, Reincarnation, Royalty, R*pe, Strong Love Interests, Strong to Stronger, Sword And Magic, Transmigration, Japanese, Toui, Won | F188: https://www.novelupdates.com/series/eoge-no-hakushaku-reijou-wo-hoshi-meido-ochisaseru-akuyaku-onzoushi-ni-tensei-shita-ore-wa-zama-wo-kaihi-suru-sono-kekka-mein-heroin-ga-yuusha-gakuin-de-mainichi-gyaku-yobai-ni-kuru-no-daga/
A189: For Some Reason, the Light-Attribute Beauty Asahi-san Has Been Spending Every Weekend in My Room (LN) | B189: This is the story of a radiant girl of light and a brooding boy of darkness—falling in love in dazzling, rainbow-colored hues. They sit in the same room, doing nothing but playing games. And yet, as they spend those quiet moments together, the distance between their hearts begins to shrink. The beloved web hit finally comes to print! Asahi Hikari—school idol, tennis prodigy, and part-time model—is a sunshine-tier extrovert blessed with talent, looks, and popularity. In stark contrast, her classmate Kageyama Reiya is a hardcore gamer and a gloom-and-doom introvert with serious otaku energy. Two people from opposite worlds who were never meant to cross paths. But everything changes when a chance encounter on a bus reveals their shared love for games. From that day on, Hikari starts dropping by Reiya’s room every weekend. Same room. Same games. Just the two of them. As the weekends pile up, so does the warmth between them. “Alright then, I’ll be over tomorrow at the usual time, so get ready, okay?” This is the story of a girl of light and a boy of darkness—falling in love in a shimmer of rainbow colors. | C189: Comedy, Romance, School Life | D189: 光属性美少女の朝日さんがなぜか毎週末俺の部屋に入り浸るようになった件 | E189: Light Novel, Comedy, Romance, School Life, Beautiful Female Lead, Emotionally Weak Protagonist, Inferiority Complex, Introverted Protagonist, Loner Protagonist, Male Protagonist, Japanese, Shinjin, 日野 祐希, Mamyouda, 間明田, Softbank Creative | F189: https://www.novelupdates.com/series/for-some-reason-the-light-attribute-beauty-asahi-san-has-been-spending-every-weekend-in-my-room-ln/
A190: My Competent Junior Living Across From Me Just Wants to Be Spoiled on the Veranda (LN) | B190: Exhausting days… But when I come home, you’re always there—unguarded, just waiting for me. My only hobby is enjoying a quiet drink alone on my balcony. Living across from me? The most popular junior at our company—Shiraho Yo, flawless at work and adorable beyond reason. “Just being beside you in silence makes me happy, senpai.” For some reason, this perfect girl only ever lets her guard down around me—and starts getting all clingy!? | C190: Comedy, Romance, Slice of Life | D190: 向かいのしごでき後輩は、ベランダで甘えたい | E190: Light Novel, Comedy, Romance, Slice of Life, Male Protagonist, Modern Day, Office Romance, Japanese, Nanaten, 七転, 熊野だう, Kadokawa | F190: https://www.novelupdates.com/series/my-competent-junior-living-across-from-me-just-wants-to-be-spoiled-on-the-veranda-ln/
A191: A Toxic 20-Year-Old Game Streamer Accidentally Reveals His Nice Personality Because He Forgot to End the Stream | B191: “What happened today is a secret between us, okay?” Nakayama Haruto is a gaming commentator known for his toxicity as the streamer ‘Oni-chan’. After finishing his usual streaming session, Haruto accidentally forgot to end the stream. As a result, his secret life as a streamer working to support his younger sister’s education and living expenses is exposed. Furthermore, it’s also revealed that he meticulously prepares scripts to provoke others, all while being, in reality, a genuinely nice person! To make matters more complicated, during a livestream by the popular VTuber and professional gamer, Ayaya (aka Shirayuki Aya), Haruto unintentionally reveals his true personality once again. Unexpectedly, this led to them growing closer to each other as they continued to play games and go on outings together. Thus begins a one-on-one romantic comedy between the business-minded toxic streamer and the popular VTuber heroine! | C191: Comedy, Romance, Shounen, Slice of Life | D191: Aorikei Game Haishinsha (20-sai), Haishin no Kiri Wasure ni Yori Ii Hito Bare Suru. (LN) Aorikei Geimu Haishinsha (Hatachi), Haishin no Kiri Wasure ni Yori Ii Hito Bare Suru. (LN) Provocative-Style Game Streamer (20 years old) Accidentally Reveals His Kind Personality Due To Forgetting To End The Stream (LN) Toxic Game Streamer (LN) 煽り系ゲーム配信者（20歳）、配信の切り忘れによりいい人バレする。(LN) | E191: Light Novel, Comedy, Romance, Shounen, Slice of Life, Adapted to Manga, Beautiful Female Lead, Caring Protagonist, Famous Protagonist, Gamers, Hard-Working Protagonist, Kind Love Interests, Livestreaming, Love Triangles, Male Protagonist, Misunderstandings, Modern Day, Multiple POV, Past Plays a Big Role, Popular Love Interests, Siblings, Sister Complex, Younger Sisters, Japanese, Natsuno Minoru, 夏乃実, 麦うさぎ, Overlap, I Was a Crazy, Berserker-Type Dungeon Streamer, but When I Helped a Beautiful Dungeon Streamer and Treated Her Politely, It Was Revealed That I Was Actually a Normal Person | F191: https://www.novelupdates.com/series/a-toxic-20-year-old-game-streamer-accidentally-reveals-his-nice-personality-because-he-forgot-to-end-the-stream/
A192: Takane No Hana (LN) | B192: A high school boy, Itsuki Tomonari, gets involved in a kidnapping and ends up taking care of Hinako Konohana, a young lady from one of Japan’s largest conglomerates. On the surface, Hinako seems to be a brilliant and charming girl, but in reality, she is a lazy girl with no life skills. However, due to family reasons, Hinako has to play the role of the “perfect young lady” at school. Wanting to protect her, Itsuki takes care of her in a very caring manner. Eventually, Hinako begins to fawn on Itsuki with all her might… “Now…if Itsuki isn’t around, I would hate it.” This is a love story that begins with a cute young lady with a gap that transcends the master-servant relationship. | C192: Comedy, Drama, Harem, Romance, School Life, Shounen, Slice of Life | D192: Bảo mẫu bí mật của tiểu thư (Vietnamese Official) Rich Girl Caretaker (Official) Saijo no Osewa Saijo no Osewa Takane no Hana-darakena Meimon-kou de, Gakuin Ichi no Ojou-sama (Seikatsu Nouryoku Kaimu) wo Kagenagara Osewa suru Koto ni Narimashita 才女のお世話 高嶺の花だらけな名門校で、学院一のお嬢様（生活能力皆無）を陰ながらお世話することになりました | E192: Light Novel, Comedy, Drama, Harem, Romance, School Life, Shounen, Slice of Life, Adapted to Anime, Adapted to Manga, Beautiful Female Lead, Caring Protagonist, Clingy Lover, Love Interest Falls in Love First, Male Protagonist, Master-Servant Relationship, Modern Day, Wealthy Characters, Japanese, Yuusaku SAKAISHI, 坂石遊作, Miwabe Sakura, みわべさくら, HJ Bunko, Hobby Japan, Monogatari Novels, | F192: https://www.novelupdates.com/series/takane-no-hana-ln/ | G192: 25
A193: Hanasaku Iroha – The Place That Blooms Someday | B193: Will this be the revival of the long-established inn…… The now adult heroine’s “7th year revenge.” The all-new afterstory of P.A. Works’ original TV Anime “Hanasaku Iroha” (2011). Depicting the heroines after the Anime and a new ray of hope. 7 years after “Kissuisou,” the long-established inn in the hot spring town, Yunosagi, had, under the decision of Madam Manager, Sui Shijima, silently closed its doors. Sui’s granddaughter, Ohana Matsumae, with the ambition – “I want to be like Sui Shijima” = I want to rebuild Kissuisou with my own abilities one day – in her heart, returned to her life in Tokyo…… Reuniting with nostalgic faces, meeting new ones, and learning about the feelings of her deceased father for the very first time. Now a little more of an adult, Ohana’s battle for the “Revival of Kissuisou” begins. | C193: Comedy, Drama, Slice of Life | D193: Hanasaku Iroha ~Itsuka Saku Basho~ 花咲くいろは～いつか咲く場所～ | E193: Light Novel, Comedy, Drama, Slice of Life, Determined Protagonist, Family Business, Female Protagonist, Friendship, Heartwarming, Lack of Common Sense, Modern Day, Sharp-tongued Characters, Japanese, Fujimoto Tohru, Kohinata Iroha, P.A. Books, | F193: https://www.novelupdates.com/series/hanasaku-iroha-the-place-that-blooms-someday/
A194: Yuri Influencer – The Two’s Naughty Outdoor Activities | B194: Shou, who’s been living an actress career with no sprouts of success, suddenly ends up in an outdoor s*x relationship with Tsukasa, the song influencer who boasts overwhelming popularity on SNS! She’s forced to go along with Tsukasa’s fetishes, but it seems the original trigger actually lies with Shou herself…? | C194: Adult, Ecchi, Mature, Romance, Smut, Yuri | D194: 百合いんふるえんさー ふたりのエッチな野外活動 | E194: Light Novel, Adult, Ecchi, Mature, Romance, Smut, Yuri, Absent Parents, Acting, Beautiful Female Lead, Clingy Lover, C*nnilingus, Dense Protagonist, Early Romance, Emotionally Weak Protagonist, Exhibitionism, Female Protagonist, First-time Interc**rse, Inferiority Complex, Kind Love Interests, Love Interest Falls in Love First, M*sturbation, Modern Day, Nudity, Outdoor Interc**rse, Popular Love Interests, R-18, Secretive Protagonist, S*x Friends, Short Story, Showbiz, Voyeurism, Japanese, Araoshi Yuu, あらおし悠, Suzunone Rena, 鈴音れな, Kill Time Communication, I Reincarnated as a Villainess and Ended Up Raising Flags with the Yandere Main Heroine, My S*ave Self and the Princess – Yuri Blossoming in Another World, The Deal Between the Knight and the Demon – A Yuri Kiss, Yuri Infirmary – How to Heal a Heartbroken Girl, Yuri Lady’s Not-So-Elegant Magical Girl Life, Yuri Love S*ave – My Exclusive Class Rep | F194: https://www.novelupdates.com/series/yuri-influencer-the-twos-naughty-outdoor-activities/
A195: If a Mentally Unstable Girl Changed Into an Wife’s Apron… | B195: “Pien?” “Landmine?” But she’s a beautiful girl, so I’ll let it slide! “Let me ‘commute’ to Shinsuke’s house? I’ll do anything for you,” said Kotosaka Shizune, a university student and a mentally unstable beauty, as she suddenly proposed to Shinsuke Aigaki. Besides being a college student, she also had another identity as a ‘sugar baby’ called ‘Kotone.’ After Shinsuke found out about this, she asked him to become her ‘commuting husband’ as a way of keeping him quiet about her secret. “I thought I was done with mentally unstable girls. That’s what I thought.” Shinsuke had become cautious around women due to troubles with mentally unstable girls in the past. Nevertheless, he reluctantly agreed because of his concern for Shizune, and gradually, he found himself attracted to her dedicated role as his ‘commuting wife’!? A heartwarming and comedic story of cohabitation with a girl with a secret! | C195: Adult, Comedy, Psychological, Romance, School Life, Seinen, Slice of Life | D195: Menhera Ga Ai Tsuma Apron Ni Kigaetara When Menhera changes into his wife's apron メンヘラが愛妻エプロンに着替えたら 悶黑少女換上愛妻圍裙過後 | E195: Light Novel, Adult, Comedy, Psychological, Romance, School Life, Seinen, Slice of Life, Absent Parents, Apartment Life, Average-looking Protagonist, Beautiful Female Lead, Caring Protagonist, Cautious Protagonist, Character Growth, Child Abuse, Childhood Friends, Childhood Love, Cohabitation, College/University, Comedic Undertone, Determined Protagonist, Family Conflict, Friendship, Heartwarming, Helpful Protagonist, Late Romance, Male Protagonist, Mature Protagonist, Slow Romance, Japanese, Hanamiya Takuya, 花宮拓夜, Nardack, Kadokawa, A Story About a Suicidal Girl Who Attempted Sui**de but got Hindered, and Was Taken Out to Play, A Story Of Taking Home A Lonely Gal From My Class And Turning Her Into An Elegant Beauty, A Yandere As A Girlfriend, But That Doesn’t Matter Because When You Tell Her How Much You Love Her, She Gets All Twitchy And Cute, About the Time When I Lied to My Tsundere Childhood Friend That “I Got a Girlfriend”, Buying a Weeping Girl Under the Wintry Sky, and Making Her Too Happy, Can I Brag About My Very Devoted Wife to You? | F195: https://www.novelupdates.com/series/if-a-mentally-unstable-girl-changed-into-an-wifes-apron/
A196: Tsurune: Kazemai Koukou Kyuudoubu | B196: Tsurune follows Minato, a boy who used to be really into kyudo (Japanese archery) until something happened at his last competition in middle school, after which he lost his confidence and quit. When he goes to high school, he has no intention for joining the kyudo club, despite the urging of his friends, but when he stumbles upon an archer practicing in the woods, he decides to do kyudo once more. *Tsurune refers the “sound of a vibrating bowstring” | C196: Adventure, School Life, Slice of Life, Sports | D196: Tsurune: Kazemai High School Kyudo Club ツルネ ―風舞高校弓道部― | E196: Light Novel, Adventure, School Life, Slice of Life, Sports, Adapted to Anime, Archery, Calm Protagonist, Character Growth, Childhood Friends, Clubs, Friendship, Male Protagonist, Teachers, Japanese, Kotoko Ayano, Chinatsu Morimoto, Kyoto Animation, If I Fail to Debut, I’ll Get a Killer Disease | F196: https://www.novelupdates.com/series/tsurune-kazemai-koukou-kyuudoubu/
...

Sheet Match
A1: title | B1: id | C1: Name | D1: MAL ID | E1: Genre
A2: 5 Centimet Trên Giây | B2: 1 | C2: Byousoku 5 Centimeter | E2: =VLOOKUP(C2,NU!A:F,3,FALSE) -> Drama, Romance, Seinen, Slice of Life
A3: 5 Centimet Trên Giây - One More Side | B3: 2 | E3: Drama, Romance, Seinen, Slice of Life
A4: 86 Eighty Six | B4: 3 | C4: 86 | E4: =VLOOKUP(C4,NU!A:F,3,FALSE) -> Action, Drama, Mecha, Mystery, Romance, Sci-fi, Seinen, Supernatural, Tragedy
A5: 86-Eighty Six - Alter | B5: 4 | C5: 86 | E5: Action, Drama, Mecha, Mystery, Romance, Sci-fi, Seinen, Supernatural, Tragedy
A6: Ai Dám Bảo Rom-com Không Có Ngoài Đời Thực? | B6: 5 | C6: Genjitsu de Rabukome Dekinai to Dare ga Kimeta? | E6: =VLOOKUP(C6,NU!A:F,3,FALSE) -> Comedy, Drama, Harem, Romance, School Life, Shounen, Slice of Life
A7: Ai Đã Giết Anh Hùng | B7: 6 | C7: Who Killed the Hero? (LN) | E7: =VLOOKUP(C7,NU!A:F,3,FALSE) -> Action, Drama, Fantasy, Mystery, Seinen, Supernatural
A8: Amagi Công Viên Rực Rỡ | B8: 7 | C8: Amagi Brilliant Park | E8: =VLOOKUP(C8,NU!A:F,3,FALSE) -> Comedy, Fantasy, Harem, Shounen, Slice of Life
A9: Amaryllis Ở Xứ Sở Băng Giá | B9: 8 | C9: Amaryllis in the Ice Country | E9: =VLOOKUP(C9,NU!A:F,3,FALSE) -> Action, Adventure, Drama, Mystery, Psychological, Romance, Sci-fi, Slice of Life, Tragedy
A10: Ame Và Yuki - Những Đứa Con Của Sói | B10: 9 | C10: Ookami Kodomo no Ame to Yuki | E10: =VLOOKUP(C10,NU!A:F,3,FALSE) -> Drama, Fantasy, Romance, Seinen, Slice of Life, Tragedy
A11: Anh Hùng Diệt Thần & Bảy Thệ Ước | B11: 10 | C11: The God Slaying Hero and the Seven Covenants | E11: =VLOOKUP(C11,NU!A:F,3,FALSE) -> Action, Adventure, Comedy, Fantasy, Romance, Shounen, Slice of Life
A12: Anohana - Đóa Hoa Ngày Ấy | B12: 11 | C12: Anohana: The Flower We Saw That Day | E12: =VLOOKUP(C12,NU!A:F,3,FALSE) -> Slice of Life, Tragedy
A13: Another | B13: 12 | C13: Another | E13: =VLOOKUP(C13,NU!A:F,3,FALSE) -> Horror, Mystery, Psychological, School Life, Seinen, Supernatural
A14: Another S/O | B14: 13 | C14: Another | E14: Horror, Mystery, Psychological, School Life, Seinen, Supernatural
A15: Arifureta - Từ Tầm Thường Đến Bất Khả Chiến Bại | B15: 14 | C15: Arifureta Shokugyou de Sekai Saikyou (LN) | E15: =VLOOKUP(C15,NU!A:F,3,FALSE) -> Action, Adventure, Drama, Ecchi, Fantasy, Harem, Mature, Mecha, Mystery, Supernatural
A16: Arya Bàn Bên Thỉnh Thoảng Lại Trêu Ghẹo Tôi Bằng Tiếng Nga | B16: 15 | C16: The Neighboring Aarya-san who Sometimes Acts Affectionate and Murmuring in Russian | E16: =VLOOKUP(C16,NU!A:F,3,FALSE) -> Comedy, Drama, Ecchi, Harem, Romance, School Life, Shounen, Slice of Life
A17: Aura - Trận Chiến Cuối Cùng Của Maryuin Koga | B17: 16 | C17: Aura: Koga Maryuin’s Final Battle | E17: =VLOOKUP(C17,NU!A:F,3,FALSE) -> Comedy, Drama, Romance, School Life, Shounen
A18: Ba Ngày Hạnh Phúc | B18: 17 | C18: Three Days of Happiness | E18: =VLOOKUP(C18,NU!A:F,3,FALSE) -> Drama, Mature, Psychological, Romance, Seinen, Slice of Life, Supernatural, Tragedy
A19: Bakemonogatari | B19: 18 | C19: Monogatari Series | E19: =VLOOKUP(C19,NU!A:F,3,FALSE) -> Comedy, Drama, Ecchi, Harem, Mystery, Psychological, Romance, School Life, Supernatural
A20: Beatless | B20: 19 | C20: BEATLESS | E20: =VLOOKUP(C20,NU!A:F,3,FALSE) -> Action, Romance, Sci-fi
A21: Biên Niên Sử Đế Chế Alexis | B21: 20 | C21: The Alexis Empire Chronicle | E21: =VLOOKUP(C21,NU!A:F,3,FALSE) -> Action, Adventure, Drama, Fantasy, Seinen
A22: Bác Sĩ Cuối Cùng Dưới Tán Hoa Anh Đào | B22: 21 | E22: Drama
A23: Bên Kia Mây Trời, Là Nơi Hẹn Ước | B23: 22 | C23: Kumo no Mukou, Yakusoku no Basho | E23: =VLOOKUP(C23,NU!A:F,3,FALSE) -> Drama, Romance, Sci-fi
A24: Bí Mật Giao Ước Bóng Tối | B24: 23 | C24: Himitsu – Kuro no Chikai | E24: =VLOOKUP(C24,NU!A:F,3,FALSE) -> Drama, Fantasy, Gender Bender, Romance, Shoujo Ai, Supernatural, Tragedy
A25: Bạn Gái Vs. Bạn Thời Thơ Ấu | B25: 24 | C25: Ore no Kanojo to Osananajimi ga Shuraba Sugiru | E25: =VLOOKUP(C25,NU!A:F,3,FALSE) -> Comedy, Ecchi, Harem, Romance, School Life, Shounen
A26: Bảo Mẫu Bí Mật Của Tiểu Thư | B26: 25 | C26: Takane No Hana (LN) | E26: =VLOOKUP(C26,NU!A:F,3,FALSE) -> Comedy, Drama, Harem, Romance, School Life, Shounen, Slice of Life
A27: Bầu Trời Xanh Của Em | B27: 26 | E27: Drama, Romance
A28: Bị Đuổi Khỏi Nhóm Anh Hùng, Tôi Muốn Sống Tự Do Tự Tại Ở Vương Đô | B28: 27 | C28: Do You Think Someone Like You Can Defeat the Demon King? (LN) | E28: =VLOOKUP(C28,NU!A:F,3,FALSE) -> Action, Adventure, Drama, Fantasy, Horror, Mature, Tragedy, Yuri
A29: Bỗng Một Ngày Tôi Có Vị Hôn Thê Là Gal | B29: 28 | C29: One Day, Out of The Blue, I Got a Gal’s Forgiving Wife | E29: =VLOOKUP(C29,NU!A:F,3,FALSE) -> Comedy, Romance, School Life
A30: Bởi Vì Tôi Sẽ Gọi Tên Em | B30: 29 | C30: Because I Call Your Name | E30: =VLOOKUP(C30,NU!A:F,3,FALSE) -> Psychological, Sci-fi, Supernatural
A31: Calling You | B31: 30 | C31: Calling You | E31: =VLOOKUP(C31,NU!A:F,3,FALSE) -> Drama, Psychological, Supernatural, Tragedy
A32: Chitose Trong Chai Ramune | B32: 31 | C32: Chitose-kun wa Ramune Bin no Naka | E32: =VLOOKUP(C32,NU!A:F,3,FALSE) -> Comedy, Drama, Harem, Romance, School Life
A33: Chiếc Hộp Rỗng Và Maria Lần 0 | B33: 32 | C33: Utsuro no Hako to Zero no Maria | E33: =VLOOKUP(C33,NU!A:F,3,FALSE) -> Action, Drama, Horror, Mystery, Psychological, Romance, School Life, Seinen, Supernatural, Tragedy
A34: Chung Một Mái Nhà | B34: 33 | C34: Gimai Seikatsu | E34: =VLOOKUP(C34,NU!A:F,3,FALSE) -> Comedy, Drama, Psychological, Romance, School Life, Shounen, Slice of Life
A35: Chuyển Sinh Làm Người Sói, Tôi Trở Thành Cánh Tay Phải Của Ma Vương | B35: 34 | C35: Reincarnated into a Werewolf, the Demon Lord Servants | E35: =VLOOKUP(C35,NU!A:F,3,FALSE) -> Adventure, Fantasy, Romance, Seinen, Supernatural
A36: Chuyện Tình Hài Lãng Mạn Không Thể Chê Vào Đâu | B36: 35 | C36: Monku no Tsukeyou ga Nai Rabukome | E36: =VLOOKUP(C36,NU!A:F,3,FALSE) -> Comedy, Drama, Romance, School Life, Tragedy
A37: Chuyện Tình Thanh Xuân Bi Hài Của Tôi Quả Nhiên Là Sai Lầm | B37: 36 | C37: Yahari Ore no Seishun Love Come wa Machigatte Iru | E37: =VLOOKUP(C37,NU!A:F,3,FALSE) -> Comedy, Drama, Psychological, Romance, School Life, Seinen, Slice of Life
A38: Chàng thẩm định viên và Nữ tác giả tập sự | B38: 37 | C38: Manuscript Screening Boy and Manuscript Submitting Girl | E38: =VLOOKUP(C38,NU!A:F,3,FALSE) -> Drama, Romance, School Life, Slice of Life
A39: Chàng Trai Chuyển Kiếp Và Cô Gái Thiên Tài | B39: 38 | C39: About the Reckless Girl Who Kept Challenging a Reborn Man Like Me | E39: =VLOOKUP(C39,NU!A:F,3,FALSE) -> Drama, Fantasy, Romance, School Life, Shounen, Slice of Life
... A43: Chúa Tể Bóng Tối | B43: 42 | C43: To Be a Power in the Shadows! (LN) | E43: =VLOOKUP(C43,NU!A:F,3,FALSE) -> Action, Adventure, Comedy, Fantasy, Harem, School Life, Seinen
A44: Chủ Tiệm Bánh Chiến Binh Và Cô Phục Vụ Người Máy | B44: 43 | D44: 87498 | E44: Action, Comedy, Fantasy
A45: Con Gái Tôi Đã Đến Thủ Đô Và Trở Thành Mạo Hiểm Giả Hạng S | B45: 44 | C45: My Daughter Grew Up to “Rank S” Adventurer | E45: =VLOOKUP(C45,NU!A:F,3,FALSE) -> Comedy, Fantasy, Shounen, Slice of Life
A46: Cop Craft - Cảnh Sát Đến Từ Hai Thế Giới | B46: 45 | C46: Cop Craft – Dragnet Mirage Reloaded | E46: =VLOOKUP(C46,NU!A:F,3,FALSE) -> Action, Fantasy, Sci-fi
A47: Cuốn Sách Của Sự Kết Thúc | B47: 46 | C47: Shuuen no Shiori | E47: =VLOOKUP(C47,NU!A:F,3,FALSE) -> Horror, Mystery, Psychological, School Life, Shounen, Supernatural
A48: Cuộc Chiến Luân Hồi - All You Need Is Kill | B48: 47 | C48: All You Need Is Kill | E48: =VLOOKUP(C48,NU!A:F,3,FALSE) -> Action, Mecha, Mystery, Psychological, Romance, Sci-fi, Tragedy
A49: Cuộc Chiến Siêu Nhiên Giữa Đời Thường | B49: 48 | C49: Inou-Battle wa Nichijou-kei no Naka de | E49: =VLOOKUP(C49,NU!A:F,3,FALSE) -> Comedy, Harem, Romance, School Life, Slice of Life, Supernatural
A50: Cuộc Hôn Nhân Chính Trị Giả Với Thiếu Gia Ác Quỷ | B50: 49 | E50: =VLOOKUP(C50,NU!A:F,3,FALSE) -> #N/A
A51: Cuộc Nổi Dậy Của Cô Nàng Mọt Sách | B51: 50 | C51: Ascendance of a Bookworm | E51: =VLOOKUP(C51,NU!A:F,3,FALSE) -> Adventure, Comedy, Drama, Fantasy, Shoujo, Slice of Life, Supernatural
A52: Cách Sống Của Thiếu Nữ Hành Quyết - Và Rồi, Cô Ấy Được Tái Sinh | B52: 51 | C52: The Way of the Executioner Girl | E52: =VLOOKUP(C52,NU!A:F,3,FALSE) -> Adventure, Fantasy, Yuri
A53: Câu Chuyện Về Cô Bé Yêu Bánh Hạnh Nhân Đã Sống Một Nghìn Năm | B53: 52 | C53: The Story of a Macaron-Loving Girl Who Lived a Thousand Years Somehow. | E53: =VLOOKUP(C53,NU!A:F,3,FALSE) -> Romance, Sci-fi, Supernatural
A54: Câu Lạc Bộ Giỏi Và Sành Sỏi | B54: 53 | C54: GJ Bu | E54: =VLOOKUP(C54,NU!A:F,3,FALSE) -> Comedy, Harem, Romance, School Life, Shounen
A55: Cô Gái Văn Chương | B55: 54 | C55: Bungaku Shoujo | E55: =VLOOKUP(C55,NU!A:F,3,FALSE) -> Drama, Mystery, Psychological, Romance, School Life, Shounen
A56: Cô Nàng Otaku Nhà Tôi | B56: 55 | D56: 119919 | E56: Comedy, Romance, Ecchi
A57: Cô Nàng Shimotsuki Trót Phải Lòng Nhân Vật Nền | B57: 56 | C57: Shimotsuki-san Loves The Mob (LN) | E57: =VLOOKUP(C57,NU!A:F,3,FALSE) -> Drama, Psychological, Romance, School Life, Shounen, Slice of Life
A58: Công Chúa Ma Cà Rồng Quyền Năng Chỉ Muốn Có Một Cô Em Gái Mà Thôi | B58: 57 | E58: =VLOOKUP(C58,NU!A:F,3,FALSE) -> #N/A
A59: Công Cuộc Tái Thiết Vương Quốc Của Anh Hùng Chủ Nghĩa Hiện Thực | B59: 58 | C59: Genjitsushugi Yuusha no Oukoku Saikenki | E59: =VLOOKUP(C59,NU!A:F,3,FALSE) -> Action, Adventure, Drama, Fantasy, Harem, Romance, Seinen
A60: Công Việc Của Long Vương | B60: 59 | C60: Ryuuou no Oshigoto! | E60: =VLOOKUP(C60,NU!A:F,3,FALSE) -> Comedy, Drama, Harem, Romance, Sports
A61: Cấm Thư Ma Thuật Index | B61: 60 | C61: Toaru Majutsu no Index | E61: =VLOOKUP(C61,NU!A:F,3,FALSE) -> Action, Comedy, Drama, Fantasy, Harem, Romance, Sci-fi, Shounen, Supernatural
A62: Date A Live | B62: 61 | C62: Date A Live | E62: =VLOOKUP(C62,NU!A:F,3,FALSE) -> Action, Comedy, Drama, Ecchi, Fantasy, Harem, Mecha, Romance, School Life, Sci-fi, Shounen, Supernatural, Tragedy
A63: Date A Live Encore | B63: 62 | C63: Date A Live Encore | E63: =VLOOKUP(C63,NU!A:F,3,FALSE) -> Comedy, Ecchi, Fantasy, Harem, Mecha, Romance, School Life, Sci-fi, Shounen, Slice of Life
A64: Dear | B64: 63 | D64: 89386 | E64: Drama, Mystery, Supernatural
A65: Death Note - Another Note Labb Liên Hoàn Án | B65: 64 | E65: =VLOOKUP(C65,NU!A:F,3,FALSE) -> #N/A
A66: Diệt Slime Suốt 300 Năm Tôi Level Max Lúc Nào Chẳng Hay | B66: 65 | C66: While Killing Slimes for 300 Years, I Became the MAX Level Unknowingly | E66: =VLOOKUP(C66,NU!A:F,3,FALSE) -> Comedy, Fantasy, Slice of Life
A67: Durarara!! | B67: 66 | C67: Durarara!! | E67: =VLOOKUP(C67,NU!A:F,3,FALSE) -> Action, Comedy, Drama, Mystery, Psychological, Romance, School Life, Slice of Life, Supernatural
A68: Dã Ngoại Nơi Mặt Sau Của Thế Giới | B68: 67 | E68: =VLOOKUP(C68,NU!A:F,3,FALSE) -> #N/A
A69: Dưới Ánh Sáng Ma Pháp 0.2 Lux | B69: 68 | E69: =VLOOKUP(C69,NU!A:F,3,FALSE) -> #N/A
A70: Dược Sư Tự Sự | B70: 69 | C70: Kusuriya no Hitorigoto | E70: =VLOOKUP(C70,NU!A:F,3,FALSE) -> Comedy, Drama, Mystery, Romance, Seinen, Slice of Life
A71: Dạo Bước Phố Đêm | B71: 70 | E71: =VLOOKUP(C71,NU!A:F,3,FALSE) -> #N/A
A72: ECHO - Tiếng vọng | B72: 71 | E72: =VLOOKUP(C72,NU!A:F,3,FALSE) -> #N/A
A73: Em Là Người Sống, Tôi Là Người Chết, Thế Giới Đôi Lúc Lại Đảo Ngược | B73: 72 | E73: =VLOOKUP(C73,NU!A:F,3,FALSE) -> #N/A
A74: Em Là Ánh Sáng Giữa Đêm Trăng | B74: 73 | C74: You Shine in the Moonlit Night | E74: =VLOOKUP(C74,NU!A:F,3,FALSE) -> Drama, Romance, School Life, Tragedy
A75: Fate/Zero | B75: 74 | C75: Fate/Zero | E75: =VLOOKUP(C75,NU!A:F,3,FALSE) -> Action, Fantasy, Psychological, Seinen, Supernatural, Tragedy
A76: Gamers! | B76: 75 | C76: Gamers! | E76: =VLOOKUP(C76,NU!A:F,3,FALSE) -> Comedy, Drama, Harem, Romance, School Life, Slice of Life
A77: Gate: Lực Lượng Phòng Vệ Chiến Đấu Ở Tân Thế Giới | B77: 76 | C77: Gate – Jietai Kare no Chi nite, Kaku Tatakeri | E77: =VLOOKUP(C77,NU!A:F,3,FALSE) -> Action, Adventure, Comedy, Drama, Fantasy, Harem, Seinen, Supernatural, Tragedy
A78: Ghost Hunt | B78: 77 | C78: Ghost Hunt | E78: =VLOOKUP(C78,NU!A:F,3,FALSE) -> Comedy, Drama, Horror, Mystery, Psychological, Shoujo, Supernatural
A79: Gia Sư Của Công Chúa Quỷ | B79: 78 | E79: =VLOOKUP(C79,NU!A:F,3,FALSE) -> #N/A
A80: Gia Tộc Thần Bí | B80: 79 | C80: Uchouten Kazoku | E80: =VLOOKUP(C80,NU!A:F,3,FALSE) -> Adventure, Comedy, Drama, Fantasy
A81: Gosick | B81: 80 | C81: Gosick | E81: =VLOOKUP(C81,NU!A:F,3,FALSE) -> Adventure, Drama, Mystery, Romance
A82: Grimgar - Ảo ảnh và tro tàn | B82: 81 | C82: Grimgal of Ashes and Illusion | E82: =VLOOKUP(C82,NU!A:F,3,FALSE) -> Action, Adventure, Drama, Fantasy, Mystery, Shounen, Tragedy
A83: Hell Mode - Game Thủ Xuất Chúng Tung Hoành Chốn Dị Giới Hỗn Nguyên | B83: 82 | C83: Hellmode ~A Hardcore Gamer Becomes Peerless in Another World with Retro Game Settings~ | E83: Action, Adventure, Fantasy, Harem, Supernatural
A84: Hello World | B84: 83 | D84: 72351 | E84: Drama
A85: Hiệp Sĩ Lưu Ban | B85: 84 | C85: Rakudai Kishi no Eiyuutan | E85: =VLOOKUP(C85,NU!A:F,3,FALSE) -> Action, Drama, Ecchi, Fantasy, Martial Arts, Romance, School Life, Shounen
A86: Hiệp Sĩ Xương Trên Đường Du Hành Đến Thế Giới Khác | B86: 85 | C86: Skeleton Knight, in Another World | E86: =VLOOKUP(C86,NU!A:F,3,FALSE) -> Action, Adventure, Comedy, Fantasy, Harem, Shounen, Supernatural
A87: Holmes ở Kyoto | B87: 86 | C87: Holmes of Kyoto | E87: =VLOOKUP(C87,NU!A:F,3,FALSE) -> Mystery, Romance, Slice of Life
A88: Hoàng Tử Thiên Tài - Hành Trình Gây Dựng Lại Đất Nước Đang Lâm Nguy | B88: 87 | C88: Genius Prince's National Revitalization from State Deficit | E88: =VLOOKUP(C88,NU!A:F,3,FALSE) -> Adventure, Comedy, Fantasy, Romance, Shounen
A89: Hành Trình Của Elaina | B89: 88 | C89: Majo no Tabitabi | E89: =VLOOKUP(C89,NU!A:F,3,FALSE) -> Adventure, Comedy, Fantasy, Slice of Life, Tragedy
A90: Hành Trình Trở Thành Nhà Thám Hiểm Của Chàng Lính Đánh Thuê Bần Hàn | B90: 89 | C90: The Strange Adventure of a Broke Mercenary | E90: =VLOOKUP(C90,NU!A:F,3,FALSE) -> Action, Adventure, Comedy, Drama, Fantasy, Seinen
A91: Hành Trình Đến Tận Cùng Thế Giới | B91: 90 | C91: Tabi ni Deyou, Horobiyuku Sekai no Hate Made | E91: =VLOOKUP(C91,NU!A:F,3,FALSE) -> Adventure, Fantasy
A92: Hãy Đi Đi, Xanh Biếc | B92: 91 | E92: =VLOOKUP(C92,NU!A:F,3,FALSE) -> #N/A
A93: Hôn Nhân Hạnh Phúc Của Tôi | B93: 92 | C93: Watashi no Shiawase na Kekkon (LN) | E93: =VLOOKUP(C93,NU!A:F,3,FALSE) -> Drama, Romance, Shoujo, Slice of Life, Supernatural
A94: Hướng Dẫn Sử Dụng Thiên Sứ Vụng Về | B94: 93 | E94: =VLOOKUP(C94,NU!A:F,3,FALSE) -> #N/A
A95: Hướng Dẫn Thư Viện Dành Cho Người Ghét Đọc | B95: 94 | E95: =VLOOKUP(C95,NU!A:F,3,FALSE) -> #N/A
A96: Hẹn Hò Với Người Siêu Dễ Thương Như Tớ Đi! | B96: 95 | C96: Date This Super Cute Me! (LN) | E96: =VLOOKUP(C96,NU!A:F,3,FALSE) -> Comedy, Drama, Romance, School Life, Shounen, Slice of Life
A97: Hẹn Ước Mùa Hè | B97: 96 | E97: =VLOOKUP(C97,NU!A:F,3,FALSE) -> #N/A
A98: Hội Chứng Tuổi Thanh Xuân | B98: 97 | C98: Seishun Buta Yarou Series | E98: =VLOOKUP(C98,NU!A:F,3,FALSE) -> Comedy, Drama, Mystery, Psychological, Romance, School Life, Sci-fi, Supernatural
A99: Infinite Dendrogram | B99: 98 | C99: Infinite Dendrogram | E99: =VLOOKUP(C99,NU!A:F,3,FALSE) -> Action, Adventure, Comedy, Fantasy, Sci-fi, Shounen
A100: Iris Những Ngày Mưa | B100: 99 | C100: Ame no Hi no Iris | E100: =VLOOKUP(C100,NU!A:F,3,FALSE) -> Drama, Psychological, Romance, Sci-fi, Seinen, Slice of Life, Tragedy
A101: ISHURA - Tu la dị giới | B101: 100 | C101: Ishura | E101: =VLOOKUP(C101,NU!A:F,3,FALSE) -> Action, Drama, Fantasy
A102: Just Be Friends | B102: 101 | E102: =VLOOKUP(C102,NU!A:F,3,FALSE) -> #N/A
A103: Just Because! | B103: 102 | C103: Just Because! | E103: =VLOOKUP(C103,NU!A:F,3,FALSE) -> Drama, Romance, School Life, Seinen, Slice of Life
...

Sheet MAL
A1: MAL_ID | B1: title | C1: contributor_1 | D1: contributor_2 | E1: genres | F1: score | G1: scored_by | H1: popularity | I1: members | J1: favorites
A2: 14893 | B2: Monogatari Series: First Season | C2: NISIO, ISIN | D2: VOFAN | E2: Action, Comedy, Mystery, Romance, Supernatural | F2: 8.92 | G2: 18356 | H2: 282 | I2: 67162 | J2: 3289
A3: 23751 | B3: Monogatari Series: Second Season | C3: NISIO, ISIN | D3: VOFAN | E3: Comedy, Drama, Mystery, Supernatural | F3: 8.92 | G3: 8365 | H3: 766 | I3: 28216 | J3: 803
A4: 86769 | B4: Kusuriya no Hitorigoto | C4: Hyuuga, Natsu | D4: Shino, Touko | E4: Drama, Mystery | F4: 8.87 | G4: 6157 | H4: 848 | I4: 25914 | J4: 1619
A5: 44227 | B5: Monogatari Series: Final Season | C5: NISIO, ISIN | D5: VOFAN | E5: Comedy, Mystery, Supernatural | F5: 8.86 | G5: 6057 | H5: 949 | I5: 23411 | J5: 526
A6: 104039 | B6: 86 | C6: Shirabi | D6: Asato, Asato | E6: Action, Drama, Sci-Fi | F6: 8.86 | G6: 13227 | H6: 363 | I6: 52698 | J6: 3609
A7: 74697 | B7: Re:Zero kara Hajimeru Isekai Seikatsu | C7: Nagatsuki, Tappei | D7: Ootsuka, Shinichirou | E7: Drama, Fantasy, Suspense | F7: 8.85 | G7: 27423 | H7: 212 | I7: 85247 | J7: 6656
A8: 86119 | B8: Honzuki no Gekokujou: Shisho ni Naru Tame ni wa Shudan wo Erandeiraremasen | C8: Shiina, You | D8: Kazuki, Miya | E8: Fantasy | F8: 8.83 | G8: 6528 | H8: 993 | I8: 22341 | J8: 1393
A9: 70261 | B9: Mushoku Tensei: Isekai Ittara Honki Dasu | C9: Rifujin na Magonote | D9: Sirotaka | E9: Fantasy | F9: 8.82 | G9: 44376 | H9: 163 | I9: 101927 | J9: 9278
A10: 9115 | B10: Ookami to Koushinryou | C10: Hasekura, Isuna | D10: Ayakura, Juu | E10: Adventure, Drama, Fantasy, Romance, Supernatural | F10: 8.81 | G10: 17278 | H10: 258 | I10: 71126 | J10: 4269
A11: 102875 | B11: Fata Morgana no Yakata: Anata no Genten ni Itaru Monogatari | C11: Hanada, Keika | D11: Moyataro | E11: Drama, Horror, Mystery, Supernatural | F11: 8.79 | G11: 1953 | H11: 2750 | I11: 9212 | J11: 655
A12: 89357 | B12: Youkoso Jitsuryoku Shijou Shugi no Kyoushitsu e | C12: Tomose, Shunsaku | D12: Kinugasa, Shougo | E12: Drama | F12: 8.76 | G12: 37708 | H12: 174 | I12: 97829 | J12: 8397
A13: 40171 | B13: Yahari Ore no Seishun Love Comedy wa Machigatteiru. | C13: Watari, Wataru | D13: Ponkan⑧ | E13: Comedy, Romance | F13: 8.74 | G13: 21504 | H13: 231 | I13: 76926 | J13: 4186
A14: 123992 | B14: Youkoso Jitsuryoku Shijou Shugi no Kyoushitsu e: 2-nensei-hen | C14: Tomose, Shunsaku | D14: Kinugasa, Shougo | E14: Drama | F14: 8.72 | G14: 18183 | H14: 432 | I14: 45914 | J14: 2452
A15: 9726 | B15: Zaregoto Series | C15: NISIO, ISIN | D15: Take | E15: Action, Drama, Mystery, Supernatural | F15: 8.71 | G15: 5136 | H15: 761 | I15: 28444 | J15: 1344
A16: 26027 | B16: Mahoutsukai no Yoru | C16: Nasu, Kinoko | E16: Mystery, Supernatural | F16: 8.7 | G16: 1403 | H16: 2961 | I16: 8651 | J16: 266
A17: 55215 | B17: Utsuro no Hako to Zero no Maria | C17: Mikage, Eiji | D17: Tetsuo | E17: Action, Drama, Horror, Mystery, Romance, Supernatural, Suspense | F17: 8.69 | G17: 21858 | H17: 147 | I17: 110039 | J17: 5431
A18: 108177 | B18: Monogatari Series: Monster Season | C18: NISIO, ISIN | D18: VOFAN | E18: Comedy, Mystery, Supernatural | F18: 8.68 | G18: 1989 | H18: 2514 | I18: 9952 | J18: 109
A19: 98930 | B19: Violet Evergarden | C19: Akatsuki, Kana | D19: Takase, Akiko | E19: Drama, Fantasy | F19: 8.66 | G19: 7268 | H19: 651 | I19: 32512 | J19: 810
A20: 24875 | B20: Shinyaku Toaru Majutsu no Index | C20: Kamachi, Kazuma | D20: Haimura, Kiyotaka | E20: Action, Comedy, Fantasy, Sci-Fi, Supernatural | F20: 8.65 | G20: 5663 | H20: 1261 | I20: 18207 | J20: 1231
A21: 70399 | B21: Seishun Buta Yarou Series | C21: Kamoshida, Hajime | D21: Mizoguchi, Keiji | E21: Drama, Romance, Supernatural | F21: 8.65 | G21: 7412 | H21: 649 | I21: 32525 | J21: 1289
A22: 399 | B22: Kino no Tabi: The Beautiful World | C22: Sigsawa, Keiichi | D22: Kuroboshi, Kouhaku | E22: Adventure, Drama, Fantasy | F22: 8.62 | G22: 3282 | H22: 1008 | I22: 22028 | J22: 559
A23: 81669 | B23: Overlord | C23: Maruyama, Kugane | D23: so-bin | E23: Action, Fantasy | F23: 8.61 | G23: 23829 | H23: 269 | I23: 69130 | J23: 4068
A24: 60553 | B24: Kono Subarashii Sekai ni Shukufuku wo! | C24: Mishima, Kurone | D24: Akatsuki, Natsume | E24: Adventure, Comedy, Fantasy | F24: 8.6 | G24: 19598 | H24: 321 | I24: 59897 | J24: 3102
A25: 2062 | B25: Kara no Kyoukai: The Garden of Sinners | C25: Type-Moon | D25: Nasu, Kinoko | E25: Action, Fantasy, Mystery | F25: 8.57 | G25: 3789 | H25: 1193 | I25: 19201 | J25: 623
A26: 66517 | B26: Umineko no Naku Koro ni | C26: Ryukishi07 | D26: Tomohi | E26: Fantasy, Horror, Mystery, Supernatural, Suspense | F26: 8.56 | G26: 2323 | H26: 3154 | I26: 8112 | J26: 553
A27: 93097 | B27: Monogatari Series: Off Season | C27: NISIO, ISIN | D27: VOFAN | E27: Comedy, Drama, Mystery, Supernatural | F27: 8.55 | G27: 2122 | H27: 3142 | I27: 8147 | J27: 135
A28: 1342 | B28: Baccano! | C28: Narita, Ryohgo | D28: Enami, Katsumi | E28: Action, Fantasy, Mystery | F28: 8.54 | G28: 3379 | H28: 977 | I28: 22602 | J28: 499
... A48: 138481 | B48: Make Heroine ga Oosugiru! | C48: Imigimuru | D48: Amamori, Takibi | E48: Comedy, Romance | F48: 8.42 | G48: 1888 | H48: 2836 | I48: 8966 | J48: 342
A49: 48399 | B49: No Game No Life | C49: Kamiya, Yuu | E49: Comedy, Fantasy, Ecchi | F49: 8.41 | G49: 16255 | H49: 297 | I49: 63375 | J49: 2384
A50: 98380 | B50: Bungou Stray Dogs | C50: Asagiri, Kafka | D50: Harukawa35 | E50: Action, Mystery, Supernatural | F50: 8.41 | G50: 3214 | H50: 1907 | I50: 13106 | J50: 1420
A51: 12854 | B51: Toaru Majutsu no Index | C51: Kamachi, Kazuma | D51: Haimura, Kiyotaka | E51: Action, Fantasy, Sci-Fi | F51: 8.4 | G51: 10502 | H51: 616 | I51: 33870 | J51: 1897
A52: 142171 | B52: Silent Witch: Chinmoku no Majo no Kakushigoto | C52: Isora, Matsuri | D52: Fujimi, Nanna | E52: Fantasy | F52: 8.39 | G52: 948 | H52: 5816 | I52: 4270 | J52: 175
A53: 95012 | B53: Kumo desu ga, Nani ka? | C53: Kiryuu, Tsukasa | D53: Baba, Okina | E53: Action, Adventure, Comedy, Fantasy | F53: 8.38 | G53: 11973 | H53: 688 | I53: 30691 | J53: 2020
A54: 87953 | B54: Shousetsu Akatsuki no Yona: Onaji Tsuki no Shita de | C54: Kusanagi, Mizuho | D54: Fujitani, Touko | E54: Adventure, Romance | F54: 8.37 | G54: 3256 | H54: 1799 | I54: 13773 | J54: 339
A55: 106602 | B55: Bleach: Can't Fear Your Own World | C55: Kubo, Tite | D55: Narita, Ryohgo | E55: Action, Supernatural | F55: 8.36 | G55: 3303 | H55: 2333 | I55: 10590 | J55: 228
A56: 113819 | B56: Violet Evergarden Gaiden | C56: Akatsuki, Kana | D56: Takase, Akiko | E56: Drama, Fantasy | F56: 8.36 | G56: 1072 | H56: 5188 | I56: 4845 | J56: 56
A57: 138424 | B57: Watashi no Oshi wa Akuyaku Reijou.: Revolution | C57: Inori. | D57: Hanagata | E57: Comedy, Fantasy, Girls Love | F57: 8.35 | G57: 2558 | H57: 2971 | I57: 8616 | J57: 430
A58: 154545 | B58: Youkoso Jitsuryoku Shijou Shugi no Kyoushitsu e 0 | C58: Tomose, Shunsaku | D58: Kinugasa, Shougo | E58: Drama | F58: 8.35 | G58: 1709 | H58: 6998 | I58: 3466 | J58: 69
A59: 90531 | B59: Naruto Shinden Series | C59: Kishimoto, Masashi | D59: Yano, Takashi | E59: Action, Adventure, Fantasy | F59: 8.35 | G59: 5209 | H59: 1826 | I59: 13583 | J59: 331
A60: 95243 | B60: Re:Zero kara Hajimeru Isekai Seikatsu Ex | C60: Nagatsuki, Tappei | D60: Ootsuka, Shinichirou | E60: Fantasy | F60: 8.35 | G60: 1645 | H60: 3614 | I60: 7089 | J60: 129
A61: 18161 | B61: Katanagatari | C61: NISIO, ISIN | D61: Take | E61: Action, Adventure, Comedy, Romance | F61: 8.34 | G61: 1624 | H61: 2838 | I61: 8962 | J61: 134
... A83: 41865 | B83: Hajishirazu no Purple Haze: JoJo no Kimyou na Bouken yori | C83: Araki, Hirohiko | D83: Kadono, Kouhei | E83: Action, Adventure | F83: 8.16 | G83: 6005 | H83: 1498 | I83: 16041 | J83: 401
A84: 85773 | B84: Fate/stay night: Garden of Avalon | C84: Nasu, Kinoko | E84: Fantasy, Supernatural | F84: 8.15 | G84: 1406 | H84: 5009 | I84: 5054 | J84: 125
A85: 33297 | B85: Ao Haru Ride | C85: Sakisaka, Io | D85: Abe, Akiko | E85: Romance | F85: 8.15 | G85: 11532 | H85: 809 | I85: 26941 | J85: 2505
A86: 171320 | B86: Shuu ni Ichido Classmate wo Kau Hanashi: Futari no Jikan, Iiwake no 5000-en | C86: U35 | D86: Haneda, Usa | E86: Girls Love | F86: 8.15 | G86: 411 | H86: 14628 | I86: 1366 | J86: 142
A87: 134341 | B87: Tokidoki Bosotto Russia-go de Dereru Tonari no Alya-san | C87: Momoco | D87: Sun Sun, Sun | E87: Comedy, Romance | F87: 8.14 | G87: 5671 | H87: 1025 | I87: 21664 | J87: 1039
A88: 77573 | B88: Higurashi no Naku Koro ni Kai - Dai 2-wa: Tsumihoroboshi-hen | C88: Ryukishi07 | D88: Tomohi | E88: Drama, Horror, Mystery | F88: 8.13 | G88: 503 | H88: 15004 | I88: 1322 | J88: 40
A89: 77575 | B89: Higurashi no Naku Koro ni Kai - Dai 3-wa: Minagoroshi-hen | C89: Ryukishi07 | D89: Tomohi | E89: Drama, Horror, Mystery | F89: 8.13 | G89: 502 | H89: 15098 | I89: 1311 | J89: 17
A90: 142170 | B90: Mimoza no Kokuhaku | C90: Hachimoku, Mei | D90: Kukka | E90: Drama, Romance | F90: 8.12 | G90: 336 | H90: 9727 | I90: 2322 | J90: 80
A91: 10892 | B91: Full Metal Panic! | C91: Gatou, Shouji | D91: Shiki, Douji | E91: Action, Comedy, Drama, Romance, Sci-Fi | F91: 8.12 | G91: 2888 | H91: 2445 | I91: 10188 | J91: 239
A92: 77577 | B92: Higurashi no Naku Koro ni Kai - Dai 4-wa: Matsuribayashi-hen | C92: Ryukishi07 | D92: Tomohi | E92: Drama, Horror, Mystery | F92: 8.12 | G92: 465 | H92: 15234 | I92: 1296 | J92: 21
A93: 26201 | B93: Hikaru ga Chikyuu ni Ita Koro...... | C93: Nomura, Mizuki | D93: Takeoka, Miho | E93: Mystery, Romance, Supernatural | F93: 8.12 | G93: 1298 | H93: 4347 | I93: 5887 | J93: 134
A94: 90810 | B94: Nogi Wakaba wa Yuusha de Aru | C94: BUNBUN | D94: Takahiro | E94: Fantasy | F94: 8.12 | G94: 1581 | H94: 4917 | I94: 5175 | J94: 246
A95: 1313 | B95: Gosick | C95: Sakuraba, Kazuki | D95: Takeda, Hinata | E95: Drama, Mystery, Romance | F95: 8.11 | G95: 1677 | H95: 3024 | I95: 8447 | J95: 139
A96: 76965 | B96: Higurashi no Naku Koro ni - Dai 1-wa: Onikakushi-hen | C96: Ryukishi07 | D96: Tomohi | E96: Drama, Horror, Mystery | F96: 8.1 | G96: 897 | H96: 8792 | I96: 2633 | J96: 150
... A101: 95211 | B101: Orange | C101: Takano, Ichigo | D101: Tokiumi, Yui | E101: Drama, Romance, Sci-Fi | F101: 8.07 | G101: 3944 | H101: 2365 | I101: 10451 | J101: 304
A102: 42569 | B102: Medaka Box Gaiden: Good Loser Kumagawa | C102: NISIO, ISIN | D102: Akatsuki, Akira | F102: 8.07 | G102: 1517 | H102: 5475 | I102: 4579 | J102: 79
A103: 99821 | B103: Shinsetsu Ookami to Koushinryou: Ookami to Youhishi | C103: Hasekura, Isuna | D103: Ayakura, Juu | E103: Fantasy | F103: 8.07 | G103: 772 | H103: 3890 | I103: 6558 | J103: 85
A104: 49567 | B104: Saenai Heroine no Sodatekata | C104: Misaki, Kurehito | D104: Maruto, Fumiaki | E104: Comedy, Drama, Romance | F104: 8.07 | G104: 2058 | H104: 2244 | I104: 11068 | J104: 187
A105: 24464 | B105: Kyoukaisenjou no Horizon | C105: Kawakami, Minoru | D105: Satoyasu | E105: Action, Comedy, Fantasy, Sci-Fi | F105: 8.06 | G105: 708 | H105: 3694 | I105: 6903 | J105: 143
A106: 9114 | B106: D.Gray-man: Reverse | C106: Hoshino, Katsura | D106: Kizaki, Kaya | E106: Action, Adventure, Fantasy | F106: 8.06 | G106: 1624 | H106: 3687 | I106: 6916 | J106: 119
A107: 42867 | B107: Kagerou Daze | C107: Jin | D107: Sidu | E107: Comedy, Sci-Fi | F107: 8.06 | G107: 3052 | H107: 1769 | I107: 13933 | J107: 965
A108: 142819 | B108: Class de 2-banme ni Kawaii Onnanoko to Tomodachi ni Natta | C108: Hyuuga, Azuri | D108: Takata | E108: Comedy, Romance | F108: 8.05 | G108: 884 | H108: 6045 | I108: 4106 | J108: 123
A109: 18251 | B109: The Legend of the Sun Knight | C109: Yu, Wo | D109: Ya Sha | E109: Fantasy, Supernatural | F109: 8.05 | G109: 930 | H109: 7007 | I109: 3456 | J109: 84
A110: 173328 | B110: Honzuki no Gekokujou: Hannelore no Kizokuin Gonensei | C110: Shiina, You | D110: Kazuki, Miya | E110: Fantasy | F110: 8.05 | G110: 187 | H110: 25450 | I110: 575 | J110: 5
A111: 46024 | B111: Log Horizon | C111: Touno, Mamare | D111: Hara, Kazuhiro | E111: Action, Adventure, Fantasy | F111: 8.04 | G111: 2889 | H111: 1558 | I111: 15556 | J111: 282
A112: 57035 | B112: Owari no Seraph: Ichinose Guren, 16-sai no Catastrophe | C112: Yamamoto, Yamato | D112: Kagami, Takaya | E112: Action, Drama, Fantasy | F112: 8.04 | G112: 2499 | H112: 2685 | I112: 9413 | J112: 258
A113: 99815 | B113: Saihate no Paladin | C113: Rin, Kususaga | D113: Yanagino, Kanata | E113: Adventure, Fantasy | F113: 8.03 | G113: 2202 | H113: 2597 | I113: 9661 | J113: 112
A114: 10000 | B114: "Bungaku Shoujo" Series | C114: Nomura, Mizuki | D114: Takeoka, Miho | E114: Drama, Mystery, Romance | F114: 8.01 | G114: 1535 | H114: 3137 | I114: 8166 | J114: 203
... A119: 53537 | B119: Danganronpa Kirigiri | C119: Komatsuzaki, Rui | D119: Takekuni, Kitayama | E119: Action, Horror, Mystery | F119: 8 | G119: 883 | H119: 4348 | I119: 5886 | J119: 91
A120: 27861 | B120: Mahou Shoujo Madoka★Magica | C120: Ninomae, Hajime | E120: Drama, Fantasy | F120: 7.99 | G120: 975 | H120: 5763 | I120: 4317 | J120: 59
A121: 47957 | B121: Ano Hi Mita Hana no Namae wo Bokutachi wa Mada Shiranai. | C121: Okada, Mari | D121: Tanaka, Masayoshi | E121: Drama | F121: 7.99 | G121: 642 | H121: 7586 | I121: 3156 | J121: 51
A122: 11496 | B122: Code Geass: Hangyaku no Lelouch | C122: Taniguchi, Gorou | D122: Ookouchi, Ichirou | E122: Action, Adventure, Drama, Sci-Fi | F122: 7.99 | G122: 1442 | H122: 4918 | I122: 5175 | J122: 135
A123: 97200 | B123: Kono Subarashii Sekai ni Shukufuku wo! Spin-off: Kono Kamen no Akuma ni Soudan wo! | C123: Mishima, Kurone | D123: Akatsuki, Natsume | E123: Comedy, Fantasy | F123: 7.99 | G123: 1507 | H123: 5482 | I123: 4574 | J123: 24
A124: 138744 | B124: Tensei Oujo to Tensai Reijou no Mahou Kakumei | C124: Karasu, Piero | D124: Kisaragi, Yuri | E124: Comedy, Fantasy, Girls Love | F124: 7.99 | G124: 998 | H124: 5539 | I124: 4527 | J124: 131
A125: 103722 | B125: Shuumatsu Nani Shitemasu ka? Isogashii desu ka? Sukutte Moratte Ii desu ka? Ex | C125: Kareno, Akira | D125: ue | E125: Fantasy, Sci-Fi | F125: 7.99 | G125: 670 | H125: 7199 | I125: 3344 | J125: 28
A126: 100051 | B126: Kimi no Na wa. Another Side: Earthbound | C126: Tanaka, Masayoshi | D126: Kanou, Arata | E126: Drama, Supernatural | F126: 7.98 | G126: 1959 | H126: 3126 | I126: 8185 | J126: 87
A127: 77571 | B127: Higurashi no Naku Koro ni Kai - Dai 1-wa: Meakashi-hen | C127: Ryukishi07 | D127: Tomohi | E127: Drama, Horror, Mystery | F127: 7.97 | G127: 453 | H127: 13474 | I127: 1527 | J127: 35
A128: 79169 | B128: Shinigami wo Tabeta Shoujo | C128: Chomoran | D128: Nanasawa, Matari | E128: Fantasy | F128: 7.97 | G128: 623 | H128: 6414 | I128: 3834 | J128: 84
A129: 125340 | B129: Spy Kyoushitsu | C129: Tomari | D129: Takemachi | E129: Action, Mystery | F129: 7.97 | G129: 845 | H129: 5011 | I129: 5052 | J129: 82
A130: 127956 | B130: Watashi ga Koibito ni Nareru Wake Nai jan, Muri Muri! (※Muri ja Nakatta!?) | C130: Takeshima, Eku | D130: Mikami, Teren | E130: Comedy, Girls Love | F130: 7.96 | G130: 838 | H130: 6966 | I130: 3489 | J130: 133
A131: 133057 | B131: Boku no Hero Academia the Movie: Heroes:Rising | C131: Kuroda, Yousuke | D131: Horikoshi, Kouhei | E131: Action | F131: 7.96 | G131: 1175 | H131: 6216 | I131: 3972 | J131: 25
A132: 143948 | B132: Otome Game no Heroine de Saikyou Survival | C132: Harunohi, Biyori | D132: Hitaki, Yuu | E132: Action, Adventure, Fantasy | F132: 7.96 | G132: 319 | H132: 17798 | I132: 1036 | J132: 49
A133: 12070 | B133: Moribito Series | C133: Uehashi, Nahoko | E133: Fantasy | F133: 7.96 | G133: 486 | H133: 5964 | I133: 4157 | J133: 38
A134: 20777 | B134: Ouran Koukou Host Club | C134: Hatori, Bisco | D134: Katou, Youichi | E134: Comedy, Romance | F134: 7.96 | G134: 845 | H134: 6576 | I134: 3727 | J134: 67
A135: 120656 | B135: Gekijouban One Piece: Stampede | C135: Oda, Eiichiro | D135: Hamazaki, Tatsuya | E135: Action, Adventure, Comedy, Drama, Fantasy | F135: 7.96 | G135: 761 | H135: 8443 | I135: 2763 | J135: 23
A136: 21479 | B136: Sword Art Online | C136: BUNBUN | D136: Kawahara, Reki | E136: Action, Adventure, Fantasy, Romance | F136: 7.96 | G136: 25158 | H136: 286 | I136: 65778 | J136: 3565
A137: 30051 | B137: Sakura-sou no Pet na Kanojo | C137: Kamoshida, Hajime | D137: Mizoguchi, Keiji | E137: Comedy, Romance, Slice of Life | F137: 7.96 | G137: 3947 | H137: 1299 | I137: 17755 | J137: 417
A138: 57201 | B138: Rakudai Kishi no Cavalry | C138: Won | D138: Misora, Riku | E138: Action, Comedy, Fantasy, Romance, Ecchi | F138: 7.96 | G138: 4393 | H138: 1213 | I138: 18907 | J138: 500
A139: 90118 | B139: Tsuki ga Michibiku Isekai Douchuu | C139: Azumi, Kei | D139: Matsumoto, Mitsuaki | E139: Adventure, Fantasy | F139: 7.96 | G139: 3188 | H139: 2174 | I139: 11432 | J139: 246
A140: 22699 | B140: Black Lagoon | C140: Hiroe, Rei | D140: Urobuchi, Gen | E140: Action, Adventure, Comedy, Drama | F140: 7.95 | G140: 829 | H140: 5808 | I140: 4275 | J140: 173
A141: 61307 | B141: Rokujouma no Shinryakusha!? | C141: Poco | D141: Takehaya | E141: Comedy, Romance, Supernatural | F141: 7.95 | G141: 999 | H141: 4328 | I141: 5908 | J141: 128
A142: 66433 | B142: Dungeon ni Deai wo Motomeru no wa Machigatteiru Darou ka Gaiden: Sword Oratoria | C142: Haimura, Kiyotaka | D142: Omori, Fujino | E142: Action, Adventure, Fantasy | F142: 7.95 | G142: 1461 | H142: 4229 | I142: 6062 | J142: 98
A143: 103268 | B143: No Game No Life: Practical War Game | C143: Kamiya, Yuu | E143: Comedy, Fantasy | F143: 7.95 | G143: 1071 | H143: 5023 | I143: 5035 | J143: 40
A144: 109014 | B144: Kono Subarashii Sekai ni Shukufuku wo! Extra: Ano Orokamono ni mo Kyakkou wo! | C144: Yuuki, Hagure | D144: Hiru Kuma | E144: Comedy, Fantasy | F144: 7.95 | G144: 926 | H144: 5993 | I144: 4138 | J144: 24
A145: 14064 | B145: ½ Prince | C145: Yu, Wo | D145: Ya Sha | E145: Action, Adventure, Comedy, Fantasy, Romance, Sci-Fi, Supernatural | F145: 7.94 | G145: 2815 | H145: 3354 | I145: 7638 | J145: 245
A146: 120251 | B146: Saya no Uta | C146: Urobuchi, Gen | D146: Chuuou, Higashiguchi | E146: Drama, Horror, Romance, Supernatural | F146: 7.94 | G146: 858 | H146: 6214 | I146: 3974 | J146: 115
A147: 23942 | B147: Kimi ni Todoke | C147: Shiina, Karuho | D147: Shimokawa, Kanae | E147: Romance | F147: 7.94 | G147: 1154 | H147: 5215 | I147: 4821 | J147: 154
A148: 43605 | B148: Bleach: Spirits Are Forever with You | C148: Kubo, Tite | D148: Narita, Ryohgo | E148: Action, Supernatural | F148: 7.94 | G148: 1281 | H148: 5308 | I148: 4739 | J148: 69
...
